Workbook

Sheet Assumptions
A1: Assumption | B1: Value
A2: Interest Rate | B2: 0.065
A3: Down Payment % | B3: 0.2
A4: Loan Term Years | B4: 30
A5: Property Tax Rate | B5: 0.012
A6: Insurance $/mo | B6: 150
A7: Utilities $/mo | B7: 250
A8: Internet $/mo | B8: 60

Sheet Listings
A1: Address | B1: Town | C1: Zillow URL | D1: Price | E1: HOA/mo | F1: Beds/Baths | G1: Sq Ft | H1: In-Unit Laundry | I1: Parking | J1: Down Payment $ | K1: Loan Amount | L1: Monthly Mortgage | M1: Property Tax/mo | N1: Insurance/mo | O1: Utilities+Internet | P1: Total Monthly Cost | Q1: Area Rental Price (Roommate) | R1: Net Monthly Cost | S1: Drive to MBTA (min) | T1: Drive to Seaport (min) | U1: Drive to Google (min) | V1: Rating Score | W1: Rating
A2: 0 Gordon Rd, Medford, MA 02155 | B2: Medford | C2: https://www.zillow.com/homedetails/0-Gordon-Rd-Medford-MA-02155/2100126227_zpid/ | D2: 369000 | E2: 0 | F2: ?bd/?ba | G2: 9732 | H2: No | I2: None listed | J2: =D2*Assumptions!B3 | K2: =D2-J2 | L2: =-PMT(Assumptions!B2/12,Assumptions!B4*12,K2) | M2: =D2*Assumptions!B5/12 | N2: =Assumptions!B6 | O2: =Assumptions!B7+Assumptions!B8 | P2: =L2+E2+M2+N2+O2 | Q2: 1790 | R2: =P2-Q2 | S2: 5 | T2: 12.3 | U2: 12.6 | V2: 2.8 | W2: Green
A3: 1-Bedroom Plan, 20 Whitney | B3: Quincy | C3: https://www.zillow.com/community/20-whitney/456675877_zpid/ | D3: 399000 | E3: 0 | F3: 1bd/1.0ba | G3: 500 | H3: No | I3: Off Street | J3: =D3*Assumptions!B3 | K3: =D3-J3 | L3: =-PMT(Assumptions!B2/12,Assumptions!B4*12,K3) | M3: =D3*Assumptions!B5/12 | N3: =Assumptions!B6 | O3: =Assumptions!B7+Assumptions!B8 | P3: =L3+E3+M3+N3+O3 | Q3: 1315 | R3: =P3-Q3 | V3: 2.45 | W3: Green
A4: 975 Washington St, Newtonville, MA 02460 | B4: Newton | C4: https://www.zillow.com/homedetails/975-Washington-St-Newtonville-MA-02460/459474131_zpid/ | D4: 1 | E4: 0 | F4: ?bd/?ba | G4: 34210 | H4: No | I4: None listed | J4: =D4*Assumptions!B3 | K4: =D4-J4 | L4: =-PMT(Assumptions!B2/12,Assumptions!B4*12,K4) | M4: =D4*Assumptions!B5/12 | N4: =Assumptions!B6 | O4: =Assumptions!B7+Assumptions!B8 | P4: =L4+E4+M4+N4+O4 | Q4: 2200 | R4: =P4-Q4 | S4: 5.8 | T4: 16.2 | U4: 16.7 | V4: 2.45 | W4: Green
A5: 133 Warren St APT 3, Watertown, MA 02472 | B5: Watertown | C5: https://www.zillow.com/homedetails/133-Warren-St-APT-3-Watertown-MA-02472/56370749_zpid/ | D5: 375000 | E5: 350 | F5: 2bd/1.0ba | G5: 600 | H5: No | I5: Off Street, Assigned, Deeded | J5: =D5*Assumptions!B3 | K5: =D5-J5 | L5: =-PMT(Assumptions!B2/12,Assumptions!B4*12,K5) | M5: =D5*Assumptions!B5/12 | N5: =Assumptions!B6 | O5: =Assumptions!B7+Assumptions!B8 | P5: =L5+E5+M5+N5+O5 | Q5: 1224 | R5: =P5-Q5 | V5: 2.45 | W5: Green
A6: 194 Lexington St APT 1, Watertown, MA 02472 | B6: Watertown | C6: https://www.zillow.com/homedetails/194-Lexington-St-APT-1-Watertown-MA-02472/56370715_zpid/ | D6: 375000 | E6: 350 | F6: 2bd/1.0ba | G6: 600 | H6: No | I6: Off Street, Assigned, Driveway | J6: =D6*Assumptions!B3 | K6: =D6-J6 | L6: =-PMT(Assumptions!B2/12,Assumptions!B4*12,K6) | M6: =D6*Assumptions!B5/12 | N6: =Assumptions!B6 | O6: =Assumptions!B7+Assumptions!B8 | P6: =L6+E6+M6+N6+O6 | Q6: 1224 | R6: =P6-Q6 | V6: 2.45 | W6: Green
A7: 151 Tremont St #U-508, Boston, MA 02111 | B7: Cambridge | C7: https://www.zillow.com/homedetails/151-Tremont-St-U-508-Boston-MA-02111/431633767_zpid/ | D7: 56500 | E7: 192 | F7: ?bd/?ba | G7: 10018 | H7: No | I7: None listed | J7: =D7*Assumptions!B3 | K7: =D7-J7 | L7: =-PMT(Assumptions!B2/12,Assumptions!B4*12,K7) | M7: =D7*Assumptions!B5/12 | N7: =Assumptions!B6 | O7: =Assumptions!B7+Assumptions!B8 | P7: =L7+E7+M7+N7+O7 | Q7: 3514 | R7: =P7-Q7 | V7: 2.45 | W7: Green
A8: 133 Commander Shea Blvd APT 502, Quincy, MA 02171 | B8: Quincy | C8: https://www.zillow.com/homedetails/133-Commander-Shea-Blvd-APT-502-Quincy-MA-02171/56602111_zpid/ | D8: 349900 | E8: 0 | F8: 1bd/1.0ba | G8: 644 | H8: No | I8: Unknown | J8: =D8*Assumptions!B3 | K8: =D8-J8 | L8: =-PMT(Assumptions!B2/12,Assumptions!B4*12,K8) | M8: =D8*Assumptions!B5/12 | N8: =Assumptions!B6 | O8: =Assumptions!B7+Assumptions!B8 | P8: =L8+E8+M8+N8+O8 | Q8: 1800 | R8: =P8-Q8 | V8: 2.4 | W8: Green
A9: 1025 Hancock St Unit 2K, Quincy, MA 02169 | B9: Quincy | C9: https://www.zillow.com/homedetails/1025-Hancock-St-UNIT-2K-Quincy-MA-02169/66655529_zpid/ | D9: 264000 | E9: 0 | F9: ?bd/1.0ba | G9: 445 | H9: No | I9: Unknown | J9: =D9*Assumptions!B3 | K9: =D9-J9 | L9: =-PMT(Assumptions!B2/12,Assumptions!B4*12,K9) | M9: =D9*Assumptions!B5/12 | N9: =Assumptions!B6 | O9: =Assumptions!B7+Assumptions!B8 | P9: =L9+E9+M9+N9+O9 | Q9: 1800 | R9: =P9-Q9 | V9: 2.4 | W9: Green
A10: 88 Gordon St APT 304, Brighton, MA 02135 | B10: Brighton | C10: https://www.zillow.com/homedetails/88-Gordon-St-APT-304-Brighton-MA-02135/59162680_zpid/ | D10: 399000 | E10: 0 | F10: 1bd/1.0ba | G10: 533 | H10: No | I10: Unknown | J10: =D10*Assumptions!B3 | K10: =D10-J10 | L10: =-PMT(Assumptions!B2/12,Assumptions!B4*12,K10) | M10: =D10*Assumptions!B5/12 | N10: =Assumptions!B6 | O10: =Assumptions!B7+Assumptions!B8 | P10: =L10+E10+M10+N10+O10 | Q10: 2000 | R10: =P10-Q10 | V10: 2.4 | W10: Green
A11: 26 Chiswick Rd APT 6, Brighton, MA 02135 | B11: Brighton | C11: https://www.zillow.com/homedetails/26-Chiswick-Rd-APT-6-Brighton-MA-02135/59094013_zpid/ | D11: 368000 | E11: 0 | F11: 1bd/1.0ba | G11: 470 | H11: No | I11: Unknown | J11: =D11*Assumptions!B3 | K11: =D11-J11 | L11: =-PMT(Assumptions!B2/12,Assumptions!B4*12,K11) | M11: =D11*Assumptions!B5/12 | N11: =Assumptions!B6 | O11: =Assumptions!B7+Assumptions!B8 | P11: =L11+E11+M11+N11+O11 | Q11: 2000 | R11: =P11-Q11 | V11: 2.4 | W11: Green
A12: 10 Skyline Dr APT 5, Braintree, MA 02184 | B12: Quincy | C12: https://www.zillow.com/homedetails/10-Skyline-Dr-APT-5-Braintree-MA-02184/184109022_zpid/ | D12: 359000 | E12: 465 | F12: 2bd/1.0ba | G12: 850 | H12: No | I12: Deeded, Assigned | J12: =D12*Assumptions!B3 | K12: =D12-J12 | L12: =-PMT(Assumptions!B2/12,Assumptions!B4*12,K12) | M12: =D12*Assumptions!B5/12 | N12: =Assumptions!B6 | O12: =Assumptions!B7+Assumptions!B8 | P12: =L12+E12+M12+N12+O12 | Q12: 1140 | R12: =P12-Q12 | V12: 2.35 | W12: Green
A13: 66 Bryon Rd APT 2, Chestnut Hill, MA 02467 | B13: Newton | C13: https://www.zillow.com/homedetails/66-Bryon-Rd-APT-2-Chestnut-Hill-MA-02467/2128070393_zpid/ | D13: 385000 | E13: 422 | F13: 2bd/1.0ba | G13: 780 | H13: No | I13: Deeded, Paved | J13: =D13*Assumptions!B3 | K13: =D13-J13 | L13: =-PMT(Assumptions!B2/12,Assumptions!B4*12,K13) | M13: =D13*Assumptions!B5/12 | N13: =Assumptions!B6 | O13: =Assumptions!B7+Assumptions!B8 | P13: =L13+E13+M13+N13+O13 | Q13: 1386 | R13: =P13-Q13 | V13: 2.35 | W13: Green
A14: 60 Bryon Rd APT 1, Chestnut Hill, MA 02467 | B14: Newton | C14: https://www.zillow.com/homedetails/60-Bryon-Rd-APT-1-Chestnut-Hill-MA-02467/2107598505_zpid/ | D14: 348899 | E14: 358 | F14: 2bd/1.0ba | G14: 786 | H14: No | I14: None listed | J14: =D14*Assumptions!B3 | K14: =D14-J14 | L14: =-PMT(Assumptions!B2/12,Assumptions!B4*12,K14) | M14: =D14*Assumptions!B5/12 | N14: =Assumptions!B6 | O14: =Assumptions!B7+Assumptions!B8 | P14: =L14+E14+M14+N14+O14 | Q14: 1334 | R14: =P14-Q14 | V14: 2.35 | W14: Green
A15: 38 Carey Ave APT 3, Watertown, MA 02472 | B15: Watertown | C15: https://www.zillow.com/homedetails/38-Carey-Ave-APT-3-Watertown-MA-02472/56370676_zpid/ | D15: 374899 | E15: 350 | F15: 2bd/1.0ba | G15: 600 | H15: No | I15: None listed | J15: =D15*Assumptions!B3 | K15: =D15-J15 | L15: =-PMT(Assumptions!B2/12,Assumptions!B4*12,K15) | M15: =D15*Assumptions!B5/12 | N15: =Assumptions!B6 | O15: =Assumptions!B7+Assumptions!B8 | P15: =L15+E15+M15+N15+O15 | Q15: 1135 | R15: =P15-Q15 | V15: 2.35 | W15: Green
A16: 1641 Commonwealth Ave APT 16, Brighton, MA 02135 | B16: Brighton | C16: https://www.zillow.com/homedetails/1641-Commonwealth-Ave-APT-16-Brighton-MA-02135/59089337_zpid/ | D16: 349000 | E16: 399 | F16: 1bd/1.0ba | G16: 407 | H16: No | I16: On Street | J16: =D16*Assumptions!B3 | K16: =D16-J16 | L16: =-PMT(Assumptions!B2/12,Assumptions!B4*12,K16) | M16: =D16*Assumptions!B5/12 | N16: =Assumptions!B6 | O16: =Assumptions!B7+Assumptions!B8 | P16: =L16+E16+M16+N16+O16 | Q16: 1237 | R16: =P16-Q16 | V16: 2.35 | W16: Green
A17: 354 Market St APT 9, Brighton, MA 02135 | B17: Brighton | C17: https://www.zillow.com/homedetails/354-Market-St-APT-9-Brighton-MA-02135/59093859_zpid/ | D17: 374900 | E17: 311 | F17: 1bd/1.0ba | G17: 590 | H17: No | I17: Off Street, Assigned, Paved | J17: =D17*Assumptions!B3 | K17: =D17-J17 | L17: =-PMT(Assumptions!B2/12,Assumptions!B4*12,K17) | M17: =D17*Assumptions!B5/12 | N17: =Assumptions!B6 | O17: =Assumptions!B7+Assumptions!B8 | P17: =L17+E17+M17+N17+O17 | Q17: 1362 | R17: =P17-Q17 | V17: 2.35 | W17: Green
A18: 5 Braemore Rd APT 10, Brighton, MA 02135 | B18: Brighton | C18: https://www.zillow.com/homedetails/5-Braemore-Rd-APT-10-Brighton-MA-02135/59213457_zpid/ | D18: 315000 | E18: 352 | F18: 1bd/1.0ba | G18: 385 | H18: No | I18: On Street | J18: =D18*Assumptions!B3 | K18: =D18-J18 | L18: =-PMT(Assumptions!B2/12,Assumptions!B4*12,K18) | M18: =D18*Assumptions!B5/12 | N18: =Assumptions!B6 | O18: =Assumptions!B7+Assumptions!B8 | P18: =L18+E18+M18+N18+O18 | Q18: 1344 | R18: =P18-Q18 | V18: 2.35 | W18: Green
A19: 32 Almont St #1, Medford, MA 02155 | B19: Medford | C19: https://www.zillow.com/homedetails/32-Almont-St-1-Medford-MA-02155/71661241_zpid/ | D19: 330000 | E19: 241 | F19: 1bd/1.0ba | G19: 528 | H19: No | I19: Open | J19: =D19*Assumptions!B3 | K19: =D19-J19 | L19: =-PMT(Assumptions!B2/12,Assumptions!B4*12,K19) | M19: =D19*Assumptions!B5/12 | N19: =Assumptions!B6 | O19: =Assumptions!B7+Assumptions!B8 | P19: =L19+E19+M19+N19+O19 | Q19: 1284 | R19: =P19-Q19 | V19: 2.35 | W19: Green
A20: 212 Quincy Shore Dr #A, Quincy, MA 02171 | B20: Quincy | C20: https://www.zillow.com/homedetails/212-Quincy-Shore-Dr-A-Quincy-MA-02171/458571840_zpid/ | D20: 499900 | E20: 0 | F20: 2bd/1.0ba | G20: 864 | H20: No | I20: Unknown | J20: =D20*Assumptions!B3 | K20: =D20-J20 | L20: =-PMT(Assumptions!B2/12,Assumptions!B4*12,K20) | M20: =D20*Assumptions!B5/12 | N20: =Assumptions!B6 | O20: =Assumptions!B7+Assumptions!B8 | P20: =L20+E20+M20+N20+O20 | Q20: 1800 | R20: =P20-Q20 | V20: 2.3 | W20: Green
A21: 200 Falls Blvd Unit B305, Quincy, MA 02169 | B21: Quincy | C21: https://www.zillow.com/homedetails/200-Falls-Blvd-UNIT-B305-Quincy-MA-02169/56590577_zpid/ | D21: 463000 | E21: 0 | F21: 2bd/2.0ba | G21: 980 | H21: No | I21: Unknown | J21: =D21*Assumptions!B3 | K21: =D21-J21 | L21: =-PMT(Assumptions!B2/12,Assumptions!B4*12,K21) | M21: =D21*Assumptions!B5/12 | N21: =Assumptions!B6 | O21: =Assumptions!B7+Assumptions!B8 | P21: =L21+E21+M21+N21+O21 | Q21: 1800 | R21: =P21-Q21 | V21: 2.3 | W21: Green
A22: 16 Winter St APT 26C, Waltham, MA 02451 | B22: Waltham | C22: https://www.zillow.com/homedetails/16-Winter-St-APT-26C-Waltham-MA-02451/56360152_zpid/ | D22: 425000 | E22: 0 | F22: 2bd/2.0ba | G22: 1000 | H22: No | I22: Unknown | J22: =D22*Assumptions!B3 | K22: =D22-J22 | L22: =-PMT(Assumptions!B2/12,Assumptions!B4*12,K22) | M22: =D22*Assumptions!B5/12 | N22: =Assumptions!B6 | O22: =Assumptions!B7+Assumptions!B8 | P22: =L22+E22+M22+N22+O22 | Q22: 1900 | R22: =P22-Q22 | V22: 2.3 | W22: Green
A23: 164 Galen St APT 65, Watertown, MA 02472 | B23: Newton | C23: https://www.zillow.com/homedetails/164-Galen-St-APT-65-Watertown-MA-02472/56367887_zpid/ | D23: 409000 | E23: 0 | F23: 2bd/1.0ba | G23: 950 | H23: No | I23: Unknown | J23: =D23*Assumptions!B3 | K23: =D23-J23 | L23: =-PMT(Assumptions!B2/12,Assumptions!B4*12,K23) | M23: =D23*Assumptions!B5/12 | N23: =Assumptions!B6 | O23: =Assumptions!B7+Assumptions!B8 | P23: =L23+E23+M23+N23+O23 | Q23: 2200 | R23: =P23-Q23 | V23: 2.3 | W23: Green
A24: 45 Gordon St APT 4, Allston, MA 02134 | B24: Brighton | C24: https://www.zillow.com/homedetails/45-Gordon-St-APT-4-Allston-MA-02134/59088776_zpid/ | D24: 489000 | E24: 0 | F24: 2bd/1.0ba | G24: 675 | H24: No | I24: Unknown | J24: =D24*Assumptions!B3 | K24: =D24-J24 | L24: =-PMT(Assumptions!B2/12,Assumptions!B4*12,K24) | M24: =D24*Assumptions!B5/12 | N24: =Assumptions!B6 | O24: =Assumptions!B7+Assumptions!B8 | P24: =L24+E24+M24+N24+O24 | Q24: 2000 | R24: =P24-Q24 | V24: 2.3 | W24: Green
A25: 59 Brighton Ave APT A, Allston, MA 02134 | B25: Allston | C25: https://www.zillow.com/homedetails/59-Brighton-Ave-APT-A-Allston-MA-02134/59087457_zpid/ | D25: 479900 | E25: 0 | F25: 2bd/1.0ba | G25: 670 | H25: No | I25: Unknown | J25: =D25*Assumptions!B3 | K25: =D25-J25 | L25: =-PMT(Assumptions!B2/12,Assumptions!B4*12,K25) | M25: =D25*Assumptions!B5/12 | N25: =Assumptions!B6 | O25: =Assumptions!B7+Assumptions!B8 | P25: =L25+E25+M25+N25+O25 | Q25: 1900 | R25: =P25-Q25 | V25: 2.3 | W25: Green
A26: 195 Thomas Burgin Pkwy Unit 212, Quincy, MA 02169 | B26: Quincy | C26: https://www.zillow.com/homedetails/195-Thomas-Burgin-Pkwy-UNIT-212-Quincy-MA-02169/56587202_zpid/ | D26: 249900 | E26: 345 | F26: ?bd/1.0ba | G26: 355 | H26: No | I26: None listed | J26: =D26*Assumptions!B3 | K26: =D26-J26 | L26: =-PMT(Assumptions!B2/12,Assumptions!B4*12,K26) | M26: =D26*Assumptions!B5/12 | N26: =Assumptions!B6 | O26: =Assumptions!B7+Assumptions!B8 | P26: =L26+E26+M26+N26+O26 | Q26: 988 | R26: =P26-Q26 | V26: 2.25 | W26: Yellow
A27: 14-16 Cottage Pl, West Newton, MA 02465 | B27: Newton | C27: https://www.zillow.com/homedetails/14-16-Cottage-Pl-West-Newton-MA-02465/2062072214_zpid/ | D27: 549950 | E27: 0 | F27: 2bd/1.0ba | G27: 874 | H27: No | I27: Off Street | J27: =D27*Assumptions!B3 | K27: =D27-J27 | L27: =-PMT(Assumptions!B2/12,Assumptions!B4*12,K27) | M27: =D27*Assumptions!B5/12 | N27: =Assumptions!B6 | O27: =Assumptions!B7+Assumptions!B8 | P27: =L27+E27+M27+N27+O27 | Q27: 2134 | R27: =P27-Q27 | S27: 4.8 | T27: 17.4 | U27: 17.9 | V27: 2.25 | W27: Yellow
A28: 10 Hammond Pond Pkwy APT 606, Newton, MA 02467 | B28: Newton | C28: https://www.zillow.com/homedetails/10-Hammond-Pond-Pkwy-APT-606-Newton-MA-02467/56321646_zpid/ | D28: 350000 | E28: 459 | F28: ?bd/1.0ba | G28: 508 | H28: No | I28: Carport, Storage, Deeded | J28: =D28*Assumptions!B3 | K28: =D28-J28 | L28: =-PMT(Assumptions!B2/12,Assumptions!B4*12,K28) | M28: =D28*Assumptions!B5/12 | N28: =Assumptions!B6 | O28: =Assumptions!B7+Assumptions!B8 | P28: =L28+E28+M28+N28+O28 | Q28: 1398 | R28: =P28-Q28 | V28: 2.25 | W28: Yellow
A29: 1151 Walnut St #207, Newton Highlands, MA 02461 | B29: Newton | C29: https://www.zillow.com/homedetails/1151-Walnut-St-207-Newton-Highlands-MA-02461/457256057_zpid/ | D29: 450000 | E29: 165 | F29: ?bd/1.0ba | G29: 455 | H29: No | I29: Under, Assigned, Off Street | J29: =D29*Assumptions!B3 | K29: =D29-J29 | L29: =-PMT(Assumptions!B2/12,Assumptions!B4*12,K29) | M29: =D29*Assumptions!B5/12 | N29: =Assumptions!B6 | O29: =Assumptions!B7+Assumptions!B8 | P29: =L29+E29+M29+N29+O29 | Q29: 2200 | R29: =P29-Q29 | V29: 2.25 | W29: Yellow
A30: 1151 Walnut St #304, Newton Highlands, MA 02461 | B30: Newton | C30: https://www.zillow.com/homedetails/1151-Walnut-St-304-Newton-Highlands-MA-02461/459913262_zpid/ | D30: 495000 | E30: 197 | F30: ?bd/1.0ba | G30: 511 | H30: No | I30: Under, Assigned, Off Street | J30: =D30*Assumptions!B3 | K30: =D30-J30 | L30: =-PMT(Assumptions!B2/12,Assumptions!B4*12,K30) | M30: =D30*Assumptions!B5/12 | N30: =Assumptions!B6 | O30: =Assumptions!B7+Assumptions!B8 | P30: =L30+E30+M30+N30+O30 | Q30: 2200 | R30: =P30-Q30 | V30: 2.25 | W30: Yellow
A31: 88 Gordon St APT 305, Brighton, MA 02135 | B31: Brighton | C31: https://www.zillow.com/homedetails/88-Gordon-St-APT-305-Brighton-MA-02135/59091169_zpid/ | D31: 299000 | E31: 292 | F31: 1bd/1.0ba | G31: 283 | H31: No | I31: None listed | J31: =D31*Assumptions!B3 | K31: =D31-J31 | L31: =-PMT(Assumptions!B2/12,Assumptions!B4*12,K31) | M31: =D31*Assumptions!B5/12 | N31: =Assumptions!B6 | O31: =Assumptions!B7+Assumptions!B8 | P31: =L31+E31+M31+N31+O31 | Q31: 1655 | R31: =P31-Q31 | V31: 2.25 | W31: Yellow
A32: 198 Allston St #3, Allston, MA 02134 | B32: Brighton | C32: https://www.zillow.com/homedetails/198-Allston-St-3-Allston-MA-02134/440796556_zpid/ | D32: 270000 | E32: 295 | F32: 1bd/1.0ba | G32: 318 | H32: No | I32: None listed | J32: =D32*Assumptions!B3 | K32: =D32-J32 | L32: =-PMT(Assumptions!B2/12,Assumptions!B4*12,K32) | M32: =D32*Assumptions!B5/12 | N32: =Assumptions!B6 | O32: =Assumptions!B7+Assumptions!B8 | P32: =L32+E32+M32+N32+O32 | Q32: 2000 | R32: =P32-Q32 | V32: 2.25 | W32: Yellow
A33: 15 Commonwealth Ct APT 10, Brighton, MA 02135 | B33: Brighton | C33: https://www.zillow.com/homedetails/15-Commonwealth-Ct-APT-10-Brighton-MA-02135/59091656_zpid/ | D33: 379900 | E33: 500 | F33: 1bd/1.0ba | G33: 688 | H33: No | I33: Off Street, Deeded | J33: =D33*Assumptions!B3 | K33: =D33-J33 | L33: =-PMT(Assumptions!B2/12,Assumptions!B4*12,K33) | M33: =D33*Assumptions!B5/12 | N33: =Assumptions!B6 | O33: =Assumptions!B7+Assumptions!B8 | P33: =L33+E33+M33+N33+O33 | Q33: 1601 | R33: =P33-Q33 | V33: 2.25 | W33: Yellow
A34: 1564 Commonwealth Ave APT 3, Brighton, MA 02135 | B34: Brighton | C34: https://www.zillow.com/homedetails/1564-Commonwealth-Ave-APT-3-Brighton-MA-02135/59092148_zpid/ | D34: 315000 | E34: 370 | F34: ?bd/1.0ba | G34: 306 | H34: No | I34: None listed | J34: =D34*Assumptions!B3 | K34: =D34-J34 | L34: =-PMT(Assumptions!B2/12,Assumptions!B4*12,K34) | M34: =D34*Assumptions!B5/12 | N34: =Assumptions!B6 | O34: =Assumptions!B7+Assumptions!B8 | P34: =L34+E34+M34+N34+O34 | Q34: 1144 | R34: =P34-Q34 | V34: 2.25 | W34: Yellow
A35: 77 Pond Avenue #1103, Brookline, MA 02445 | B35: Brookline | C35: https://www.zillow.com/homedetails/77-Pond-Ave-APT-1103-Brookline-MA-02445/56571183_zpid/ | D35: 489900 | E35: 0 | F35: 1bd/1.0ba | G35: 860 | H35: No | I35: Unknown | J35: =D35*Assumptions!B3 | K35: =D35-J35 | L35: =-PMT(Assumptions!B2/12,Assumptions!B4*12,K35) | M35: =D35*Assumptions!B5/12 | N35: =Assumptions!B6 | O35: =Assumptions!B7+Assumptions!B8 | P35: =L35+E35+M35+N35+O35 | Q35: 2400 | R35: =P35-Q35 | V35: 2.25 | W35: Yellow
A36: 217-221 Highland Ave Unit 1, Malden, MA 02148 | B36: Medford | C36: https://www.zillow.com/homedetails/217-221-Highland-Ave-UNIT-1-Malden-MA-02148/459672098_zpid/ | D36: 499900 | E36: 390 | F36: 3bd/2.0ba | G36: 1183 | H36: No | I36: On Street, Assigned, Paved, Exclusive Parking | J36: =D36*Assumptions!B3 | K36: =D36-J36 | L36: =-PMT(Assumptions!B2/12,Assumptions!B4*12,K36) | M36: =D36*Assumptions!B5/12 | N36: =Assumptions!B6 | O36: =Assumptions!B7+Assumptions!B8 | P36: =L36+E36+M36+N36+O36 | Q36: 1900 | R36: =P36-Q36 | V36: 2.25 | W36: Yellow
A37: 24 South St APT 38, Medford, MA 02155 | B37: Medford | C37: https://www.zillow.com/homedetails/24-South-St-APT-38-Medford-MA-02155/56281218_zpid/ | D37: 449900 | E37: 0 | F37: 1bd/2.0ba | G37: 757 | H37: No | I37: Unknown | J37: =D37*Assumptions!B3 | K37: =D37-J37 | L37: =-PMT(Assumptions!B2/12,Assumptions!B4*12,K37) | M37: =D37*Assumptions!B5/12 | N37: =Assumptions!B6 | O37: =Assumptions!B7+Assumptions!B8 | P37: =L37+E37+M37+N37+O37 | Q37: 1900 | R37: =P37-Q37 | V37: 2.25 | W37: Yellow
A38: 80 Main St APT 4, Malden, MA 02148 | B38: Medford | C38: https://www.zillow.com/homedetails/80-Main-St-APT-4-Malden-MA-02148/56268453_zpid/ | D38: 335000 | E38: 430 | F38: 1bd/1.0ba | G38: 578 | H38: No | I38: Off Street | J38: =D38*Assumptions!B3 | K38: =D38-J38 | L38: =-PMT(Assumptions!B2/12,Assumptions!B4*12,K38) | M38: =D38*Assumptions!B5/12 | N38: =Assumptions!B6 | O38: =Assumptions!B7+Assumptions!B8 | P38: =L38+E38+M38+N38+O38 | Q38: 1293 | R38: =P38-Q38 | V38: 2.25 | W38: Yellow
A39: 80 Main St APT 9, Malden, MA 02148 | B39: Medford | C39: https://www.zillow.com/homedetails/80-Main-St-APT-9-Malden-MA-02148/56268458_zpid/ | D39: 359900 | E39: 426 | F39: 1bd/1.0ba | G39: 605 | H39: No | I39: Off Street | J39: =D39*Assumptions!B3 | K39: =D39-J39 | L39: =-PMT(Assumptions!B2/12,Assumptions!B4*12,K39) | M39: =D39*Assumptions!B5/12 | N39: =Assumptions!B6 | O39: =Assumptions!B7+Assumptions!B8 | P39: =L39+E39+M39+N39+O39 | Q39: 1276 | R39: =P39-Q39 | V39: 2.25 | W39: Yellow
A40: 100 Washington St APT 3, Brighton, MA 02135 | B40: Brighton | C40: https://www.zillow.com/homedetails/100-Washington-St-APT-3-Brighton-MA-02135/59092287_zpid/ | D40: 449000 | E40: 0 | F40: 1bd/1.0ba | G40: 682 | H40: No | I40: Unknown | J40: =D40*Assumptions!B3 | K40: =D40-J40 | L40: =-PMT(Assumptions!B2/12,Assumptions!B4*12,K40) | M40: =D40*Assumptions!B5/12 | N40: =Assumptions!B6 | O40: =Assumptions!B7+Assumptions!B8 | P40: =L40+E40+M40+N40+O40 | Q40: 2000 | R40: =P40-Q40 | V40: 2.2 | W40: Yellow
A41: 17 Buckingham St #3, Somerville, MA 02143 | B41: Cambridge | C41: https://www.zillow.com/homedetails/17-Buckingham-St-3-Somerville-MA-02143/2106999481_zpid/ | D41: 499999 | E41: 0 | F41: 1bd/1.0ba | G41: 595 | H41: No | I41: Unknown | J41: =D41*Assumptions!B3 | K41: =D41-J41 | L41: =-PMT(Assumptions!B2/12,Assumptions!B4*12,K41) | M41: =D41*Assumptions!B5/12 | N41: =Assumptions!B6 | O41: =Assumptions!B7+Assumptions!B8 | P41: =L41+E41+M41+N41+O41 | Q41: 2500 | R41: =P41-Q41 | V41: 2.2 | W41: Yellow
A42: 20 Whitney #U-1, Quincy, MA 02169 | B42: Quincy | C42: https://www.zillow.com/homedetails/20-Whitney-U-1-Quincy-MA-02169/460043102_zpid/ | D42: 499000 | E42: 200 | F42: 1bd/1.0ba | G42: 638 | H42: No | I42: None listed | J42: =D42*Assumptions!B3 | K42: =D42-J42 | L42: =-PMT(Assumptions!B2/12,Assumptions!B4*12,K42) | M42: =D42*Assumptions!B5/12 | N42: =Assumptions!B6 | O42: =Assumptions!B7+Assumptions!B8 | P42: =L42+E42+M42+N42+O42 | Q42: 1800 | R42: =P42-Q42 | V42: 2.15 | W42: Yellow
A43: 21 Totman St Suite 203, Quincy, MA 02169 | B43: Quincy | C43: https://www.zillow.com/homedetails/21-Totman-St-SUITE-203-Quincy-MA-02169/458714573_zpid/ | D43: 474900 | E43: 312 | F43: 1bd/1.0ba | G43: 679 | H43: No | I43: Under, Garage Door Opener, Deeded, Assigned, Garage Faces Side, Off Street, Available for Purchase, Paved | J43: =D43*Assumptions!B3 | K43: =D43-J43 | L43: =-PMT(Assumptions!B2/12,Assumptions!B4*12,K43) | M43: =D43*Assumptions!B5/12 | N43: =Assumptions!B6 | O43: =Assumptions!B7+Assumptions!B8 | P43: =L43+E43+M43+N43+O43 | Q43: 1800 | R43: =P43-Q43 | V43: 2.15 | W43: Yellow
A44: 1691 Commonwealth Ave APT 31, Brighton, MA 02135 | B44: Brighton | C44: https://www.zillow.com/homedetails/1691-Commonwealth-Ave-APT-31-Brighton-MA-02135/59092827_zpid/ | D44: 414900 | E44: 361 | F44: 1bd/1.0ba | G44: 520 | H44: No | I44: On Street | J44: =D44*Assumptions!B3 | K44: =D44-J44 | L44: =-PMT(Assumptions!B2/12,Assumptions!B4*12,K44) | M44: =D44*Assumptions!B5/12 | N44: =Assumptions!B6 | O44: =Assumptions!B7+Assumptions!B8 | P44: =L44+E44+M44+N44+O44 | Q44: 1355 | R44: =P44-Q44 | V44: 2.15 | W44: Yellow
A45: 5 Waldo Ave APT 2A, Somerville, MA 02143 | B45: Cambridge | C45: https://www.zillow.com/homedetails/5-Waldo-Ave-APT-2A-Somerville-MA-02143/71142493_zpid/ | D45: 425000 | E45: 317 | F45: 1bd/1.0ba | G45: 530 | H45: No | I45: On Street | J45: =D45*Assumptions!B3 | K45: =D45-J45 | L45: =-PMT(Assumptions!B2/12,Assumptions!B4*12,K45) | M45: =D45*Assumptions!B5/12 | N45: =Assumptions!B6 | O45: =Assumptions!B7+Assumptions!B8 | P45: =L45+E45+M45+N45+O45 | Q45: 1644 | R45: =P45-Q45 | V45: 2.15 | W45: Yellow
A46: 6 Goodwin Pl APT B, Boston, MA 02114 | B46: Cambridge | C46: https://www.zillow.com/homedetails/6-Goodwin-Pl-APT-B-Boston-MA-02114/59166441_zpid/ | D46: 412500 | E46: 319 | F46: ?bd/1.0ba | G46: 235 | H46: No | I46: On Street | J46: =D46*Assumptions!B3 | K46: =D46-J46 | L46: =-PMT(Assumptions!B2/12,Assumptions!B4*12,K46) | M46: =D46*Assumptions!B5/12 | N46: =Assumptions!B6 | O46: =Assumptions!B7+Assumptions!B8 | P46: =L46+E46+M46+N46+O46 | Q46: 1426 | R46: =P46-Q46 | V46: 2.15 | W46: Yellow
A47: 144 Newton St APT 1, Brighton, MA 02135 | B47: Newton | C47: https://www.zillow.com/homedetails/144-Newton-St-APT-1-Brighton-MA-02135/71505041_zpid/ | D47: 589000 | E47: 0 | F47: 3bd/1.0ba | G47: 1053 | H47: No | I47: Unknown | J47: =D47*Assumptions!B3 | K47: =D47-J47 | L47: =-PMT(Assumptions!B2/12,Assumptions!B4*12,K47) | M47: =D47*Assumptions!B5/12 | N47: =Assumptions!B6 | O47: =Assumptions!B7+Assumptions!B8 | P47: =L47+E47+M47+N47+O47 | Q47: 2200 | R47: =P47-Q47 | V47: 2.1 | W47: Yellow
A48: 20 Whitney Rd #101, Quincy, MA 02169 | B48: Quincy | C48: https://www.zillow.com/homedetails/20-Whitney-Rd-101-Quincy-MA-02169/455786544_zpid/ | D48: 499000 | E48: 0 | F48: 1bd/1.0ba | G48: 575 | H48: No | I48: Off Street | J48: =D48*Assumptions!B3 | K48: =D48-J48 | L48: =-PMT(Assumptions!B2/12,Assumptions!B4*12,K48) | M48: =D48*Assumptions!B5/12 | N48: =Assumptions!B6 | O48: =Assumptions!B7+Assumptions!B8 | P48: =L48+E48+M48+N48+O48 | Q48: 1380 | R48: =P48-Q48 | V48: 2.05 | W48: Yellow
A49: 10 Naviens Ln #1, Waltham, MA 02453 | B49: Waltham | C49: https://www.zillow.com/homedetails/10-Naviens-Ln-1-Waltham-MA-02453/56366974_zpid/ | D49: 499900 | E49: 134 | F49: 2bd/1.0ba | G49: 1008 | H49: No | I49: None listed | J49: =D49*Assumptions!B3 | K49: =D49-J49 | L49: =-PMT(Assumptions!B2/12,Assumptions!B4*12,K49) | M49: =D49*Assumptions!B5/12 | N49: =Assumptions!B6 | O49: =Assumptions!B7+Assumptions!B8 | P49: =L49+E49+M49+N49+O49 | Q49: 1342 | R49: =P49-Q49 | V49: 2.05 | W49: Yellow
A50: 7 Cypress Rd APT 703, Brighton, MA 02135 | B50: Brighton | C50: https://www.zillow.com/homedetails/7-Cypress-Rd-APT-703-Brighton-MA-02135/59091947_zpid/ | D50: 448000 | E50: 315 | F50: 2bd/1.0ba | G50: 576 | H50: No | I50: Off Street, Deeded | J50: =D50*Assumptions!B3 | K50: =D50-J50 | L50: =-PMT(Assumptions!B2/12,Assumptions!B4*12,K50) | M50: =D50*Assumptions!B5/12 | N50: =Assumptions!B6 | O50: =Assumptions!B7+Assumptions!B8 | P50: =L50+E50+M50+N50+O50 | Q50: 1449 | R50: =P50-Q50 | V50: 2.05 | W50: Yellow
A51: 367 Somerville Ave APT G, Somerville, MA 02143 | B51: Cambridge | C51: https://www.zillow.com/homedetails/367-Somerville-Ave-APT-G-Somerville-MA-02143/60111757_zpid/ | D51: 425000 | E51: 304 | F51: 1bd/1.0ba | G51: 419 | H51: No | I51: None listed | J51: =D51*Assumptions!B3 | K51: =D51-J51 | L51: =-PMT(Assumptions!B2/12,Assumptions!B4*12,K51) | M51: =D51*Assumptions!B5/12 | N51: =Assumptions!B6 | O51: =Assumptions!B7+Assumptions!B8 | P51: =L51+E51+M51+N51+O51 | Q51: 1350 | R51: =P51-Q51 | V51: 2.05 | W51: Yellow
A52: 21 Beacon St APT 6D, Boston, MA 02108 | B52: Cambridge | C52: https://www.zillow.com/homedetails/21-Beacon-St-APT-6D-Boston-MA-02108/59180776_zpid/ | D52: 445999 | E52: 338 | F52: ?bd/1.0ba | G52: 300 | H52: No | I52: None listed | J52: =D52*Assumptions!B3 | K52: =D52-J52 | L52: =-PMT(Assumptions!B2/12,Assumptions!B4*12,K52) | M52: =D52*Assumptions!B5/12 | N52: =Assumptions!B6 | O52: =Assumptions!B7+Assumptions!B8 | P52: =L52+E52+M52+N52+O52 | Q52: 1513 | R52: =P52-Q52 | V52: 2.05 | W52: Yellow
A53: 21 Beacon St APT 3K, Boston, MA 02108 | B53: Cambridge | C53: https://www.zillow.com/homedetails/21-Beacon-St-APT-3K-Boston-MA-02108/59180727_zpid/ | D53: 435000 | E53: 275 | F53: ?bd/1.0ba | G53: 262 | H53: No | I53: None listed | J53: =D53*Assumptions!B3 | K53: =D53-J53 | L53: =-PMT(Assumptions!B2/12,Assumptions!B4*12,K53) | M53: =D53*Assumptions!B5/12 | N53: =Assumptions!B6 | O53: =Assumptions!B7+Assumptions!B8 | P53: =L53+E53+M53+N53+O53 | Q53: 1475 | R53: =P53-Q53 | V53: 2.05 | W53: Yellow
A54: 231 Coolidge Ave APT 405, Watertown, MA 02472 | B54: Cambridge | C54: https://www.zillow.com/homedetails/231-Coolidge-Ave-APT-405-Watertown-MA-02472/56375483_zpid/ | D54: 389000 | E54: 408 | F54: ?bd/1.0ba | G54: 379 | H54: No | I54: Off Street | J54: =D54*Assumptions!B3 | K54: =D54-J54 | L54: =-PMT(Assumptions!B2/12,Assumptions!B4*12,K54) | M54: =D54*Assumptions!B5/12 | N54: =Assumptions!B6 | O54: =Assumptions!B7+Assumptions!B8 | P54: =L54+E54+M54+N54+O54 | Q54: 1216 | R54: =P54-Q54 | V54: 2.05 | W54: Yellow
A55: 50 Water St APT 24, Medford, MA 02155 | B55: Medford | C55: https://www.zillow.com/homedetails/50-Water-St-APT-24-Medford-MA-02155/56278371_zpid/ | D55: 389900 | E55: 465 | F55: 1bd/1.0ba | G55: 634 | H55: No | I55: Off Street, Deeded | J55: =D55*Assumptions!B3 | K55: =D55-J55 | L55: =-PMT(Assumptions!B2/12,Assumptions!B4*12,K55) | M55: =D55*Assumptions!B5/12 | N55: =Assumptions!B6 | O55: =Assumptions!B7+Assumptions!B8 | P55: =L55+E55+M55+N55+O55 | Q55: 1267 | R55: =P55-Q55 | V55: 2.05 | W55: Yellow
A56: 21 Totman St #404, Quincy, MA 02169 | B56: Quincy | C56: https://www.zillow.com/homedetails/21-Totman-St-404-Quincy-MA-02169/459618632_zpid/ | D56: 500000 | E56: 0 | F56: 1bd/1.0ba | G56: 679 | H56: No | I56: Unknown | J56: =D56*Assumptions!B3 | K56: =D56-J56 | L56: =-PMT(Assumptions!B2/12,Assumptions!B4*12,K56) | M56: =D56*Assumptions!B5/12 | N56: =Assumptions!B6 | O56: =Assumptions!B7+Assumptions!B8 | P56: =L56+E56+M56+N56+O56 | Q56: 1800 | R56: =P56-Q56 | V56: 2 | W56: Yellow
A57: 0 Franklin St, Milton, MA 02186 | B57: Quincy | C57: https://www.zillow.com/homedetails/0-Franklin-St-Milton-MA-02186/441747147_zpid/ | D57: 599000 | E57: 0 | F57: ?bd/?ba | H57: No | I57: Unknown | J57: =D57*Assumptions!B3 | K57: =D57-J57 | L57: =-PMT(Assumptions!B2/12,Assumptions!B4*12,K57) | M57: =D57*Assumptions!B5/12 | N57: =Assumptions!B6 | O57: =Assumptions!B7+Assumptions!B8 | P57: =L57+E57+M57+N57+O57 | Q57: 1800 | R57: =P57-Q57 | S57: 5.9 | T57: 13.9 | U57: 18 | V57: 2 | W57: Yellow
A58: 2-Bedrooms Plan, 20 Whitney | B58: Quincy | C58: https://www.zillow.com/community/20-whitney/456675884_zpid/ | D58: 599000 | E58: 0 | F58: 2bd/2.0ba | G58: 900 | H58: No | I58: Off Street | J58: =D58*Assumptions!B3 | K58: =D58-J58 | L58: =-PMT(Assumptions!B2/12,Assumptions!B4*12,K58) | M58: =D58*Assumptions!B5/12 | N58: =Assumptions!B6 | O58: =Assumptions!B7+Assumptions!B8 | P58: =L58+E58+M58+N58+O58 | Q58: 1555 | R58: =P58-Q58 | V58: 1.95 | W58: Yellow
A59: 31 Warren St APT B-1, Waltham, MA 02453 | B59: Waltham | C59: https://www.zillow.com/homedetails/31-Warren-St-APT-B-1-Waltham-MA-02453/56365634_zpid/ | D59: 429000 | E59: 497 | F59: 2bd/1.0ba | G59: 708 | H59: No | I59: Off Street, Exclusive Parking | J59: =D59*Assumptions!B3 | K59: =D59-J59 | L59: =-PMT(Assumptions!B2/12,Assumptions!B4*12,K59) | M59: =D59*Assumptions!B5/12 | N59: =Assumptions!B6 | O59: =Assumptions!B7+Assumptions!B8 | P59: =L59+E59+M59+N59+O59 | Q59: 1248 | R59: =P59-Q59 | V59: 1.95 | W59: Yellow
A60: 461 Washington St APT 301, Brighton, MA 02135 | B60: Newton | C60: https://www.zillow.com/homedetails/461-Washington-St-APT-301-Brighton-MA-02135/59095771_zpid/ | D60: 419900 | E60: 431 | F60: 2bd/1.0ba | G60: 696 | H60: No | I60: On Street | J60: =D60*Assumptions!B3 | K60: =D60-J60 | L60: =-PMT(Assumptions!B2/12,Assumptions!B4*12,K60) | M60: =D60*Assumptions!B5/12 | N60: =Assumptions!B6 | O60: =Assumptions!B7+Assumptions!B8 | P60: =L60+E60+M60+N60+O60 | Q60: 1331 | R60: =P60-Q60 | V60: 1.95 | W60: Yellow
A61: 147 Langdon Ave #1, Watertown, MA 02472 | B61: Watertown | C61: https://www.zillow.com/homedetails/147-Langdon-Ave-1-Watertown-MA-02472/2110639068_zpid/ | D61: 569000 | E61: 200 | F61: 2bd/1.0ba | G61: 940 | H61: No | I61: Off Street, Tandem, Exclusive Parking | J61: =D61*Assumptions!B3 | K61: =D61-J61 | L61: =-PMT(Assumptions!B2/12,Assumptions!B4*12,K61) | M61: =D61*Assumptions!B5/12 | N61: =Assumptions!B6 | O61: =Assumptions!B7+Assumptions!B8 | P61: =L61+E61+M61+N61+O61 | Q61: 1407 | R61: =P61-Q61 | V61: 1.95 | W61: Yellow
A62: 764 Cambridge St APT 6, Cambridge, MA 02141 | B62: Cambridge | C62: https://www.zillow.com/homedetails/764-Cambridge-St-APT-6-Cambridge-MA-02141/67080024_zpid/ | D62: 490000 | E62: 386 | F62: 1bd/1.0ba | G62: 620 | H62: No | I62: On Street | J62: =D62*Assumptions!B3 | K62: =D62-J62 | L62: =-PMT(Assumptions!B2/12,Assumptions!B4*12,K62) | M62: =D62*Assumptions!B5/12 | N62: =Assumptions!B6 | O62: =Assumptions!B7+Assumptions!B8 | P62: =L62+E62+M62+N62+O62 | Q62: 1498 | R62: =P62-Q62 | V62: 1.95 | W62: Yellow
A63: 33 Irving St APT 4, Boston, MA 02114 | B63: Cambridge | C63: https://www.zillow.com/homedetails/33-Irving-St-APT-4-Boston-MA-02114/59174199_zpid/ | D63: 499000 | E63: 291 | F63: 1bd/1.0ba | G63: 390 | H63: No | I63: On Street | J63: =D63*Assumptions!B3 | K63: =D63-J63 | L63: =-PMT(Assumptions!B2/12,Assumptions!B4*12,K63) | M63: =D63*Assumptions!B5/12 | N63: =Assumptions!B6 | O63: =Assumptions!B7+Assumptions!B8 | P63: =L63+E63+M63+N63+O63 | Q63: 1536 | R63: =P63-Q63 | V63: 1.95 | W63: Yellow
A64: 8 9th St APT 513, Medford, MA 02155 | B64: Medford | C64: https://www.zillow.com/homedetails/8-9th-St-APT-513-Medford-MA-02155/56284573_zpid/ | D64: 499000 | E64: 440 | F64: 2bd/2.0ba | G64: 1264 | H64: No | I64: Off Street | J64: =D64*Assumptions!B3 | K64: =D64-J64 | L64: =-PMT(Assumptions!B2/12,Assumptions!B4*12,K64) | M64: =D64*Assumptions!B5/12 | N64: =Assumptions!B6 | O64: =Assumptions!B7+Assumptions!B8 | P64: =L64+E64+M64+N64+O64 | Q64: 1606 | R64: =P64-Q64 | V64: 1.95 | W64: Yellow
A65: 9 Henry St #9, Belmont, MA 02478 | B65: Belmont | C65: https://www.zillow.com/homedetails/9-Henry-St-9-Belmont-MA-02478/2069694645_zpid/ | D65: 575000 | E65: 200 | F65: 2bd/1.0ba | G65: 724 | H65: No | I65: Off Street, Assigned, Deeded | J65: =D65*Assumptions!B3 | K65: =D65-J65 | L65: =-PMT(Assumptions!B2/12,Assumptions!B4*12,K65) | M65: =D65*Assumptions!B5/12 | N65: =Assumptions!B6 | O65: =Assumptions!B7+Assumptions!B8 | P65: =L65+E65+M65+N65+O65 | Q65: 2111 | R65: =P65-Q65 | V65: 1.95 | W65: Yellow
A66: 155 Kendrick Ave APT 502, Quincy, MA 02169 | B66: Quincy | C66: https://www.zillow.com/homedetails/155-Kendrick-Ave-APT-502-Quincy-MA-02169/56591171_zpid/ | D66: 599900 | E66: 0 | F66: 2bd/2.0ba | G66: 1628 | H66: No | I66: Unknown | J66: =D66*Assumptions!B3 | K66: =D66-J66 | L66: =-PMT(Assumptions!B2/12,Assumptions!B4*12,K66) | M66: =D66*Assumptions!B5/12 | N66: =Assumptions!B6 | O66: =Assumptions!B7+Assumptions!B8 | P66: =L66+E66+M66+N66+O66 | Q66: 1800 | R66: =P66-Q66 | V66: 1.9 | W66: Yellow
A67: 872 Massachusetts Ave APT 303, Cambridge, MA 02139 | B67: Cambridge | C67: https://www.zillow.com/homedetails/872-Massachusetts-Ave-APT-303-Cambridge-MA-02139/2106605883_zpid/ | D67: 598000 | E67: 0 | F67: 1bd/2.0ba | G67: 750 | H67: No | I67: Attached, Garage Door Opener, Off Street | J67: =D67*Assumptions!B3 | K67: =D67-J67 | L67: =-PMT(Assumptions!B2/12,Assumptions!B4*12,K67) | M67: =D67*Assumptions!B5/12 | N67: =Assumptions!B6 | O67: =Assumptions!B7+Assumptions!B8 | P67: =L67+E67+M67+N67+O67 | Q67: 1963 | R67: =P67-Q67 | V67: 1.9 | W67: Yellow
A68: 87 Franklin St Unit 105, Quincy, MA 02169 | B68: Quincy | C68: https://www.zillow.com/homedetails/87-Franklin-St-UNIT-105-Quincy-MA-02169/70884919_zpid/ | D68: 544900 | E68: 322 | F68: 2bd/2.0ba | G68: 1218 | H68: No | I68: Attached, Heated Garage, Common, Assigned, Guest | J68: =D68*Assumptions!B3 | K68: =D68-J68 | L68: =-PMT(Assumptions!B2/12,Assumptions!B4*12,K68) | M68: =D68*Assumptions!B5/12 | N68: =Assumptions!B6 | O68: =Assumptions!B7+Assumptions!B8 | P68: =L68+E68+M68+N68+O68 | Q68: 1577 | R68: =P68-Q68 | V68: 1.85 | W68: Yellow
A69: 1945 Commonwealth Ave APT 4, Brighton, MA 02135 | B69: Newton | C69: https://www.zillow.com/homedetails/1945-Commonwealth-Ave-APT-4-Brighton-MA-02135/59168559_zpid/ | D69: 439000 | E69: 364 | F69: 1bd/1.0ba | G69: 605 | H69: No | I69: None listed | J69: =D69*Assumptions!B3 | K69: =D69-J69 | L69: =-PMT(Assumptions!B2/12,Assumptions!B4*12,K69) | M69: =D69*Assumptions!B5/12 | N69: =Assumptions!B6 | O69: =Assumptions!B7+Assumptions!B8 | P69: =L69+E69+M69+N69+O69 | Q69: 1444 | R69: =P69-Q69 | V69: 1.85 | W69: Yellow
A70: 31 Aldrich Rd #1, Watertown, MA 02472 | B70: Newton | C70: https://www.zillow.com/homedetails/31-Aldrich-Rd-1-Watertown-MA-02472/66817446_zpid/ | D70: 500000 | E70: 225 | F70: 2bd/1.0ba | G70: 753 | H70: No | I70: Off Street, Assigned | J70: =D70*Assumptions!B3 | K70: =D70-J70 | L70: =-PMT(Assumptions!B2/12,Assumptions!B4*12,K70) | M70: =D70*Assumptions!B5/12 | N70: =Assumptions!B6 | O70: =Assumptions!B7+Assumptions!B8 | P70: =L70+E70+M70+N70+O70 | Q70: 1360 | R70: =P70-Q70 | V70: 1.85 | W70: Yellow
A71: 239 Kelton St APT 41, Allston, MA 02134 | B71: Brighton | C71: https://www.zillow.com/homedetails/239-Kelton-St-APT-41-Allston-MA-02134/59088967_zpid/ | D71: 475000 | E71: 498 | F71: 2bd/1.0ba | G71: 690 | H71: No | I71: None listed | J71: =D71*Assumptions!B3 | K71: =D71-J71 | L71: =-PMT(Assumptions!B2/12,Assumptions!B4*12,K71) | M71: =D71*Assumptions!B5/12 | N71: =Assumptions!B6 | O71: =Assumptions!B7+Assumptions!B8 | P71: =L71+E71+M71+N71+O71 | Q71: 1468 | R71: =P71-Q71 | V71: 1.85 | W71: Yellow
A72: 10 Scottfield Rd APT 2, Allston, MA 02134 | B72: Brighton | C72: https://www.zillow.com/homedetails/10-Scottfield-Rd-APT-2-Allston-MA-02134/59088845_zpid/ | D72: 474900 | E72: 408 | F72: 2bd/1.0ba | G72: 746 | H72: No | I72: None listed | J72: =D72*Assumptions!B3 | K72: =D72-J72 | L72: =-PMT(Assumptions!B2/12,Assumptions!B4*12,K72) | M72: =D72*Assumptions!B5/12 | N72: =Assumptions!B6 | O72: =Assumptions!B7+Assumptions!B8 | P72: =L72+E72+M72+N72+O72 | Q72: 1513 | R72: =P72-Q72 | V72: 1.85 | W72: Yellow
A73: 74 Gilman St APT 1, Somerville, MA 02145 | B73: Cambridge | C73: https://www.zillow.com/homedetails/74-Gilman-St-APT-1-Somerville-MA-02145/56537708_zpid/ | D73: 559000 | E73: 354 | F73: 2bd/2.0ba | G73: 885 | H73: No | I73: Off Street, Assigned | J73: =D73*Assumptions!B3 | K73: =D73-J73 | L73: =-PMT(Assumptions!B2/12,Assumptions!B4*12,K73) | M73: =D73*Assumptions!B5/12 | N73: =Assumptions!B6 | O73: =Assumptions!B7+Assumptions!B8 | P73: =L73+E73+M73+N73+O73 | Q73: 1659 | R73: =P73-Q73 | V73: 1.85 | W73: Yellow
A74: 501 Beacon St APT 1, Boston, MA 02215 | B74: Cambridge | C74: https://www.zillow.com/homedetails/501-Beacon-St-APT-1-Boston-MA-02215/59178524_zpid/ | D74: 479000 | E74: 452 | F74: 1bd/1.0ba | G74: 560 | H74: No | I74: Off Street, None | J74: =D74*Assumptions!B3 | K74: =D74-J74 | L74: =-PMT(Assumptions!B2/12,Assumptions!B4*12,K74) | M74: =D74*Assumptions!B5/12 | N74: =Assumptions!B6 | O74: =Assumptions!B7+Assumptions!B8 | P74: =L74+E74+M74+N74+O74 | Q74: 1775 | R74: =P74-Q74 | V74: 1.85 | W74: Yellow
A75: 6 Washington Ave APT 11, Cambridge, MA 02140 | B75: Cambridge | C75: https://www.zillow.com/homedetails/6-Washington-Ave-APT-11-Cambridge-MA-02140/56438004_zpid/ | D75: 469000 | E75: 320 | F75: ?bd/1.0ba | G75: 433 | H75: No | I75: None listed | J75: =D75*Assumptions!B3 | K75: =D75-J75 | L75: =-PMT(Assumptions!B2/12,Assumptions!B4*12,K75) | M75: =D75*Assumptions!B5/12 | N75: =Assumptions!B6 | O75: =Assumptions!B7+Assumptions!B8 | P75: =L75+E75+M75+N75+O75 | Q75: 1437 | R75: =P75-Q75 | V75: 1.85 | W75: Yellow
A76: 995 Massachusetts Ave APT 404, Arlington, MA 02476 | B76: Arlington | C76: https://www.zillow.com/homedetails/995-Massachusetts-Ave-APT-404-Arlington-MA-02476/56396638_zpid/ | D76: 498000 | E76: 426 | F76: 1bd/1.0ba | G76: 663 | H76: No | I76: Off Street, Deeded | J76: =D76*Assumptions!B3 | K76: =D76-J76 | L76: =-PMT(Assumptions!B2/12,Assumptions!B4*12,K76) | M76: =D76*Assumptions!B5/12 | N76: =Assumptions!B6 | O76: =Assumptions!B7+Assumptions!B8 | P76: =L76+E76+M76+N76+O76 | Q76: 1380 | R76: =P76-Q76 | V76: 1.85 | W76: Yellow
A77: 290 Pleasant St APT 113, Watertown, MA 02472 | B77: Newton | C77: https://www.zillow.com/homedetails/290-Pleasant-St-APT-113-Watertown-MA-02472/80392270_zpid/ | D77: 539900 | E77: 485 | F77: 1bd/1.0ba | G77: 941 | H77: No | I77: Off Street, Assigned | J77: =D77*Assumptions!B3 | K77: =D77-J77 | L77: =-PMT(Assumptions!B2/12,Assumptions!B4*12,K77) | M77: =D77*Assumptions!B5/12 | N77: =Assumptions!B6 | O77: =Assumptions!B7+Assumptions!B8 | P77: =L77+E77+M77+N77+O77 | Q77: 1590 | R77: =P77-Q77 | V77: 1.75 | W77: Yellow
A78: 35 Homer Ave APT 7, Cambridge, MA 02138 | B78: Watertown | C78: https://www.zillow.com/homedetails/35-Homer-Ave-APT-7-Cambridge-MA-02138/2145288738_zpid/ | D78: 500000 | E78: 325 | F78: 1bd/1.0ba | G78: 504 | H78: No | I78: Off Street | J78: =D78*Assumptions!B3 | K78: =D78-J78 | L78: =-PMT(Assumptions!B2/12,Assumptions!B4*12,K78) | M78: =D78*Assumptions!B5/12 | N78: =Assumptions!B6 | O78: =Assumptions!B7+Assumptions!B8 | P78: =L78+E78+M78+N78+O78 | Q78: 1423 | R78: =P78-Q78 | V78: 1.75 | W78: Yellow
A79: 60 Sutherland Rd APT 4, Brighton, MA 02135 | B79: Brighton | C79: https://www.zillow.com/homedetails/60-Sutherland-Rd-APT-4-Brighton-MA-02135/59093941_zpid/ | D79: 585000 | E79: 493 | F79: 2bd/1.0ba | G79: 877 | H79: No | I79: Off Street | J79: =D79*Assumptions!B3 | K79: =D79-J79 | L79: =-PMT(Assumptions!B2/12,Assumptions!B4*12,K79) | M79: =D79*Assumptions!B5/12 | N79: =Assumptions!B6 | O79: =Assumptions!B7+Assumptions!B8 | P79: =L79+E79+M79+N79+O79 | Q79: 1557 | R79: =P79-Q79 | V79: 1.75 | W79: Yellow
A80: 7 Lothian Rd #B, Boston, MA 02135 | B80: Brighton | C80: https://www.zillow.com/homedetails/7-Lothian-Rd-B-Boston-MA-02135/59093757_zpid/ | D80: 539900 | E80: 417 | F80: 3bd/1.0ba | G80: 900 | H80: No | I80: On Street | J80: =D80*Assumptions!B3 | K80: =D80-J80 | L80: =-PMT(Assumptions!B2/12,Assumptions!B4*12,K80) | M80: =D80*Assumptions!B5/12 | N80: =Assumptions!B6 | O80: =Assumptions!B7+Assumptions!B8 | P80: =L80+E80+M80+N80+O80 | Q80: 1515 | R80: =P80-Q80 | V80: 1.75 | W80: Yellow
A81: 15 Colliston Rd APT 6, Brighton, MA 02135 | B81: Brighton | C81: https://www.zillow.com/homedetails/15-Colliston-Rd-APT-6-Brighton-MA-02135/59089643_zpid/ | D81: 450000 | E81: 425 | F81: 1bd/1.0ba | G81: 577 | H81: No | I81: None listed | J81: =D81*Assumptions!B3 | K81: =D81-J81 | L81: =-PMT(Assumptions!B2/12,Assumptions!B4*12,K81) | M81: =D81*Assumptions!B5/12 | N81: =Assumptions!B6 | O81: =Assumptions!B7+Assumptions!B8 | P81: =L81+E81+M81+N81+O81 | Q81: 1394 | R81: =P81-Q81 | V81: 1.75 | W81: Yellow
A82: 100 Lanark Rd APT 8, Brighton, MA 02135 | B82: Brighton | C82: https://www.zillow.com/homedetails/100-Lanark-Rd-APT-8-Brighton-MA-02135/59093221_zpid/ | D82: 420000 | E82: 500 | F82: 1bd/1.0ba | G82: 560 | H82: No | I82: None listed | J82: =D82*Assumptions!B3 | K82: =D82-J82 | L82: =-PMT(Assumptions!B2/12,Assumptions!B4*12,K82) | M82: =D82*Assumptions!B5/12 | N82: =Assumptions!B6 | O82: =Assumptions!B7+Assumptions!B8 | P82: =L82+E82+M82+N82+O82 | Q82: 1368 | R82: =P82-Q82 | V82: 1.75 | W82: Yellow
A83: 4 Franklin St #202, Allston, MA 02134 | B83: Brighton | C83: https://www.zillow.com/homedetails/4-Franklin-St-202-Allston-MA-02134/348499954_zpid/ | D83: 588000 | E83: 244 | F83: 1bd/1.0ba | G83: 641 | H83: No | I83: Rented, On Street | J83: =D83*Assumptions!B3 | K83: =D83-J83 | L83: =-PMT(Assumptions!B2/12,Assumptions!B4*12,K83) | M83: =D83*Assumptions!B5/12 | N83: =Assumptions!B6 | O83: =Assumptions!B7+Assumptions!B8 | P83: =L83+E83+M83+N83+O83 | Q83: 1411 | R83: =P83-Q83 | V83: 1.75 | W83: Yellow
A84: 11 Cogswell Ave APT 15, Cambridge, MA 02140 | B84: Cambridge | C84: https://www.zillow.com/homedetails/11-Cogswell-Ave-APT-15-Cambridge-MA-02140/56437178_zpid/ | D84: 550000 | E84: 389 | F84: 1bd/1.0ba | G84: 575 | H84: No | I84: Off Street, Paved | J84: =D84*Assumptions!B3 | K84: =D84-J84 | L84: =-PMT(Assumptions!B2/12,Assumptions!B4*12,K84) | M84: =D84*Assumptions!B5/12 | N84: =Assumptions!B6 | O84: =Assumptions!B7+Assumptions!B8 | P84: =L84+E84+M84+N84+O84 | Q84: 1534 | R84: =P84-Q84 | V84: 1.75 | W84: Yellow
A85: 5 Cooney St #3, Somerville, MA 02143 | B85: Cambridge | C85: https://www.zillow.com/homedetails/5-Cooney-St-3-Somerville-MA-02143/120576672_zpid/ | D85: 597000 | E85: 200 | F85: 3bd/1.0ba | G85: 741 | H85: No | I85: On Street | J85: =D85*Assumptions!B3 | K85: =D85-J85 | L85: =-PMT(Assumptions!B2/12,Assumptions!B4*12,K85) | M85: =D85*Assumptions!B5/12 | N85: =Assumptions!B6 | O85: =Assumptions!B7+Assumptions!B8 | P85: =L85+E85+M85+N85+O85 | Q85: 1216 | R85: =P85-Q85 | V85: 1.75 | W85: Yellow
A86: 40 Chappie St #1, Charlestown, MA 02129 | B86: Cambridge | C86: https://www.zillow.com/homedetails/40-Chappie-St-1-Charlestown-MA-02129/71329755_zpid/ | D86: 549500 | E86: 255 | F86: 2bd/1.0ba | G86: 821 | H86: No | I86: None listed | J86: =D86*Assumptions!B3 | K86: =D86-J86 | L86: =-PMT(Assumptions!B2/12,Assumptions!B4*12,K86) | M86: =D86*Assumptions!B5/12 | N86: =Assumptions!B6 | O86: =Assumptions!B7+Assumptions!B8 | P86: =L86+E86+M86+N86+O86 | Q86: 1876 | R86: =P86-Q86 | V86: 1.75 | W86: Yellow
A87: 390 Riverway APT 24, Boston, MA 02115 | B87: Brookline | C87: https://www.zillow.com/homedetails/390-Riverway-APT-24-Boston-MA-02115/59171376_zpid/ | D87: 479000 | E87: 423 | F87: 1bd/1.0ba | G87: 555 | H87: No | I87: None listed | J87: =D87*Assumptions!B3 | K87: =D87-J87 | L87: =-PMT(Assumptions!B2/12,Assumptions!B4*12,K87) | M87: =D87*Assumptions!B5/12 | N87: =Assumptions!B6 | O87: =Assumptions!B7+Assumptions!B8 | P87: =L87+E87+M87+N87+O87 | Q87: 1548 | R87: =P87-Q87 | V87: 1.75 | W87: Yellow
A88: 120 Wyllis Ave Unit 401, Everett, MA 02149 | B88: Medford | C88: https://www.zillow.com/homedetails/120-Wyllis-Ave-UNIT-401-Everett-MA-02149/87868278_zpid/ | D88: 598000 | E88: 472 | F88: 1bd/2.0ba | G88: 1413 | H88: No | I88: Garage | J88: =D88*Assumptions!B3 | K88: =D88-J88 | L88: =-PMT(Assumptions!B2/12,Assumptions!B4*12,K88) | M88: =D88*Assumptions!B5/12 | N88: =Assumptions!B6 | O88: =Assumptions!B7+Assumptions!B8 | P88: =L88+E88+M88+N88+O88 | Q88: 1852 | R88: =P88-Q88 | V88: 1.75 | W88: Yellow
A89: 50-56 Leo M Birmingham Pkwy #303, Boston, MA 02135 | B89: Watertown | C89: https://www.zillow.com/homedetails/50-56-Leo-M-Birmingham-Pkwy-303-Boston-MA-02135/2068433731_zpid/ | D89: 598000 | E89: 466 | F89: 1bd/1.0ba | G89: 708 | H89: No | I89: Under, Deeded | J89: =D89*Assumptions!B3 | K89: =D89-J89 | L89: =-PMT(Assumptions!B2/12,Assumptions!B4*12,K89) | M89: =D89*Assumptions!B5/12 | N89: =Assumptions!B6 | O89: =Assumptions!B7+Assumptions!B8 | P89: =L89+E89+M89+N89+O89 | Q89: 1743 | R89: =P89-Q89 | V89: 1.7 | W89: Yellow
A90: 39 Commonwealth Ave APT 31, Newton, MA 02467 | B90: Newton | C90: https://www.zillow.com/homedetails/39-Commonwealth-Ave-APT-31-Newton-MA-02467/56316564_zpid/ | D90: 529000 | E90: 430 | F90: 1bd/1.0ba | G90: 695 | H90: No | I90: Off Street, Deeded | J90: =D90*Assumptions!B3 | K90: =D90-J90 | L90: =-PMT(Assumptions!B2/12,Assumptions!B4*12,K90) | M90: =D90*Assumptions!B5/12 | N90: =Assumptions!B6 | O90: =Assumptions!B7+Assumptions!B8 | P90: =L90+E90+M90+N90+O90 | Q90: 1632 | R90: =P90-Q90 | V90: 1.65 | W90: Red
A91: 99 Tremont St #105, Boston, MA 02135 | B91: Newton | C91: https://www.zillow.com/homedetails/99-Tremont-St-105-Boston-MA-02135/2090070412_zpid/ | D91: 520000 | E91: 437 | F91: ?bd/1.0ba | G91: 616 | H91: No | I91: Assigned, Deeded | J91: =D91*Assumptions!B3 | K91: =D91-J91 | L91: =-PMT(Assumptions!B2/12,Assumptions!B4*12,K91) | M91: =D91*Assumptions!B5/12 | N91: =Assumptions!B6 | O91: =Assumptions!B7+Assumptions!B8 | P91: =L91+E91+M91+N91+O91 | Q91: 1353 | R91: =P91-Q91 | V91: 1.65 | W91: Red
A92: 56 Commonwealth Ave APT 53, Boston, MA 02116 | B92: Cambridge | C92: https://www.zillow.com/homedetails/56-Commonwealth-Ave-APT-53-Boston-MA-02116/59176404_zpid/ | D92: 549000 | E92: 267 | F92: ?bd/1.0ba | G92: 340 | H92: No | I92: None listed | J92: =D92*Assumptions!B3 | K92: =D92-J92 | L92: =-PMT(Assumptions!B2/12,Assumptions!B4*12,K92) | M92: =D92*Assumptions!B5/12 | N92: =Assumptions!B6 | O92: =Assumptions!B7+Assumptions!B8 | P92: =L92+E92+M92+N92+O92 | Q92: 1773 | R92: =P92-Q92 | V92: 1.65 | W92: Red
A93: 483 Beacon St APT 37, Boston, MA 02115 | B93: Cambridge | C93: https://www.zillow.com/homedetails/483-Beacon-St-APT-37-Boston-MA-02115/59169165_zpid/ | D93: 580000 | E93: 350 | F93: 1bd/1.0ba | G93: 480 | H93: No | I93: None listed | J93: =D93*Assumptions!B3 | K93: =D93-J93 | L93: =-PMT(Assumptions!B2/12,Assumptions!B4*12,K93) | M93: =D93*Assumptions!B5/12 | N93: =Assumptions!B6 | O93: =Assumptions!B7+Assumptions!B8 | P93: =L93+E93+M93+N93+O93 | Q93: 1787 | R93: =P93-Q93 | V93: 1.65 | W93: Red
A94: 148 Berkshire St APT 4, Cambridge, MA 02141 | B94: Cambridge | C94: https://www.zillow.com/homedetails/148-Berkshire-St-APT-4-Cambridge-MA-02141/458474348_zpid/ | D94: 535000 | E94: 301 | F94: 1bd/1.0ba | G94: 530 | H94: No | I94: None listed | J94: =D94*Assumptions!B3 | K94: =D94-J94 | L94: =-PMT(Assumptions!B2/12,Assumptions!B4*12,K94) | M94: =D94*Assumptions!B5/12 | N94: =Assumptions!B6 | O94: =Assumptions!B7+Assumptions!B8 | P94: =L94+E94+M94+N94+O94 | Q94: 1566 | R94: =P94-Q94 | V94: 1.65 | W94: Red
A95: 65 Strathmore Rd APT 49, Brighton, MA 02135 | B95: Brighton | C95: https://www.zillow.com/homedetails/65-Strathmore-Rd-APT-49-Brighton-MA-02135/59093618_zpid/ | D95: 530000 | E95: 483 | F95: 1bd/1.0ba | G95: 764 | H95: No | I95: None listed | J95: =D95*Assumptions!B3 | K95: =D95-J95 | L95: =-PMT(Assumptions!B2/12,Assumptions!B4*12,K95) | M95: =D95*Assumptions!B5/12 | N95: =Assumptions!B6 | O95: =Assumptions!B7+Assumptions!B8 | P95: =L95+E95+M95+N95+O95 | Q95: 1528 | R95: =P95-Q95 | V95: 1.6 | W95: Red
A96: 138 Quincy Shore Dr Unit 170, Quincy, MA 02171 | B96: Quincy | C96: https://www.zillow.com/homedetails/138-Quincy-Shore-Dr-UNIT-170-Quincy-MA-02171/56601722_zpid/ | D96: 589999 | E96: 497 | F96: 2bd/3.0ba | G96: 1460 | H96: No | I96: Common, Off Street, Paved | J96: =D96*Assumptions!B3 | K96: =D96-J96 | L96: =-PMT(Assumptions!B2/12,Assumptions!B4*12,K96) | M96: =D96*Assumptions!B5/12 | N96: =Assumptions!B6 | O96: =Assumptions!B7+Assumptions!B8 | P96: =L96+E96+M96+N96+O96 | Q96: 1521 | R96: =P96-Q96 | V96: 1.55 | W96: Red
A97: 7 Hereford St APT 8, Boston, MA 02115 | B97: Cambridge | C97: https://www.zillow.com/homedetails/7-Hereford-St-APT-8-Boston-MA-02115/59169276_zpid/ | D97: 599000 | E97: 400 | F97: 1bd/1.0ba | G97: 440 | H97: No | I97: None listed | J97: =D97*Assumptions!B3 | K97: =D97-J97 | L97: =-PMT(Assumptions!B2/12,Assumptions!B4*12,K97) | M97: =D97*Assumptions!B5/12 | N97: =Assumptions!B6 | O97: =Assumptions!B7+Assumptions!B8 | P97: =L97+E97+M97+N97+O97 | Q97: 1718 | R97: =P97-Q97 | V97: 1.55 | W97: Red
A98: 364 Marlborough St APT 8, Boston, MA 02115 | B98: Cambridge | C98: https://www.zillow.com/homedetails/364-Marlborough-St-APT-8-Boston-MA-02115/59167303_zpid/ | D98: 527000 | E98: 446 | F98: 1bd/1.0ba | G98: 411 | H98: No | I98: None listed | J98: =D98*Assumptions!B3 | K98: =D98-J98 | L98: =-PMT(Assumptions!B2/12,Assumptions!B4*12,K98) | M98: =D98*Assumptions!B5/12 | N98: =Assumptions!B6 | O98: =Assumptions!B7+Assumptions!B8 | P98: =L98+E98+M98+N98+O98 | Q98: 1666 | R98: =P98-Q98 | V98: 1.55 | W98: Red
A99: 863 Massachusetts Ave APT 25, Cambridge, MA 02139 | B99: Cambridge | C99: https://www.zillow.com/homedetails/863-Massachusetts-Ave-APT-25-Cambridge-MA-02139/56431258_zpid/ | D99: 549000 | E99: 434 | F99: 1bd/1.0ba | G99: 450 | H99: No | I99: None listed | J99: =D99*Assumptions!B3 | K99: =D99-J99 | L99: =-PMT(Assumptions!B2/12,Assumptions!B4*12,K99) | M99: =D99*Assumptions!B5/12 | N99: =Assumptions!B6 | O99: =Assumptions!B7+Assumptions!B8 | P99: =L99+E99+M99+N99+O99 | Q99: 1584 | R99: =P99-Q99 | V99: 1.55 | W99: Red
