Workbook

Sheet Assumptions
A1: Assumption | B1: Value
A2: Interest Rate | B2: 0.065
A3: Down Payment % | B3: 0.2
A4: Loan Term Years | B4: 30
A5: Property Tax Rate | B5: 0.012
A6: Insurance $/mo | B6: 150
A7: Utilities $/mo | B7: 250
A8: Internet $/mo | B8: 60

Sheet Listings
A1: Address | B1: Town | C1: Listing URL | D1: Price | E1: HOA/mo | F1: Beds | G1: Baths | H1: Sq Ft | I1: In-Unit Laundry | J1: Parking | K1: Down Payment $ | L1: Loan Amount | M1: Monthly Mortgage | N1: Property Tax/mo | O1: Insurance/mo | P1: Utilities+Internet | Q1: Total Monthly Cost | R1: Area Rental Price (Roommate) | S1: Net Monthly Cost | T1: Drive to MBTA (min) | U1: Drive to Seaport (min) | V1: Drive to Google (min) | W1: Rating Score | X1: Rating
A2: 40 Cross St #1, Quincy, MA 02169 | B2: Quincy | C2: https://www.redfin.com/MA/Quincy/40-Cross-St-02169/unit-1/home/8963459 | D2: 379900 | E2: 360 | F2: 2 | G2: 1 | H2: 1244 | I2: No | J2: 1 space | K2: =D2*Assumptions!B3 | L2: =D2-K2 | M2: =-PMT(Assumptions!B2/12,Assumptions!B4*12,L2) | N2: =D2*Assumptions!B5/12 | O2: =Assumptions!B6 | P2: =Assumptions!B7+Assumptions!B8 | Q2: =M2+E2+N2+O2+P2 | R2: 1170 | S2: =Q2-R2 | T2: 5.7 | U2: 15.7 | V2: 19.8 | W2: 2.45 | X2: Green
A3: 186 Lexington St #8, Watertown, MA 02472 | B3: Watertown | C3: https://www.redfin.com/MA/Watertown/186-Lexington-St-02472/unit-8/home/11690422 | D3: 394900 | E3: 350 | F3: 2 | G3: 1 | H3: 600 | I3: No | J3: 1 space | K3: =D3*Assumptions!B3 | L3: =D3-K3 | M3: =-PMT(Assumptions!B2/12,Assumptions!B4*12,L3) | N3: =D3*Assumptions!B5/12 | O3: =Assumptions!B6 | P3: =Assumptions!B7+Assumptions!B8 | Q3: =M3+E3+N3+O3+P3 | R3: 1365 | S3: =Q3-R3 | T3: 12.1 | U3: 18.5 | V3: 17.2 | W3: 2.45 | X3: Green
A4: 8 Avon St #10, Somerville, MA 02143 | B4: Somerville | C4: https://www.redfin.com/MA/Somerville/8-Avon-St-02143/unit-10/home/8759429 | D4: 500000 | E4: 288 | F4: 2 | G4: 1 | H4: 645 | I4: No | J4: 1 space | K4: =D4*Assumptions!B3 | L4: =D4-K4 | M4: =-PMT(Assumptions!B2/12,Assumptions!B4*12,L4) | N4: =D4*Assumptions!B5/12 | O4: =Assumptions!B6 | P4: =Assumptions!B7+Assumptions!B8 | Q4: =M4+E4+N4+O4+P4 | R4: 1495 | S4: =Q4-R4 | T4: 3.4 | U4: 11.9 | V4: 7.6 | W4: 2.3 | X4: Green
A5: 195 Thomas Burgin Pkwy #301, Quincy, MA 02169 | B5: Quincy | C5: https://www.redfin.com/MA/Quincy/195-Thomas-Burgin-Pkwy-02169/unit-301/home/8931809 | D5: 250000 | E5: 393 | F5: 1 | G5: 1 | H5: 447 | I5: No | J5: 0 spaces | K5: =D5*Assumptions!B3 | L5: =D5-K5 | M5: =-PMT(Assumptions!B2/12,Assumptions!B4*12,L5) | N5: =D5*Assumptions!B5/12 | O5: =Assumptions!B6 | P5: =Assumptions!B7+Assumptions!B8 | Q5: =M5+E5+N5+O5+P5 | R5: 0 | S5: =Q5-R5 | T5: 2.2 | U5: 17.6 | V5: 21.7 | W5: 2.15 | X5: Yellow
A6: 64 Queensberry St #114, Boston, MA 02215 | B6: Brookline | C6: https://www.redfin.com/MA/Boston/64-Queensberry-St-02215/unit-114/home/9241481 | D6: 425000 | E6: 395 | F6: 0 | G6: 1 | H6: 390 | I6: No | J6: 0 spaces | K6: =D6*Assumptions!B3 | L6: =D6-K6 | M6: =-PMT(Assumptions!B2/12,Assumptions!B4*12,L6) | N6: =D6*Assumptions!B5/12 | O6: =Assumptions!B6 | P6: =Assumptions!B7+Assumptions!B8 | Q6: =M6+E6+N6+O6+P6 | R6: 0 | S6: =Q6-R6 | T6: 1.3 | U6: 11.9 | V6: 9.1 | W6: 2.1 | X6: Yellow
A7: 191 Washington St, Boston, MA 02135 | B7: Brighton | C7: https://www.redfin.com/MA/Boston/191-Washington-St-02135/home/184088757 | D7: 564800 | E7: 0 | F7: 1 | G7: 1 | H7: 498 | I7: No | J7: 0 spaces | K7: =D7*Assumptions!B3 | L7: =D7-K7 | M7: =-PMT(Assumptions!B2/12,Assumptions!B4*12,L7) | N7: =D7*Assumptions!B5/12 | O7: =Assumptions!B6 | P7: =Assumptions!B7+Assumptions!B8 | Q7: =M7+E7+N7+O7+P7 | R7: 0 | S7: =Q7-R7 | T7: 2.1 | U7: 13.6 | V7: 13.2 | W7: 2 | X7: Yellow
A8: 388 Washington St #101, Quincy, MA 02169 | B8: Quincy | C8: https://www.redfin.com/MA/Quincy/388-Washington-St-02169/unit-101/home/200568725 | D8: 599000 | E8: 375 | F8: 2 | G8: 2 | H8: 983 | I8: No | J8: 1 space | K8: =D8*Assumptions!B3 | L8: =D8-K8 | M8: =-PMT(Assumptions!B2/12,Assumptions!B4*12,L8) | N8: =D8*Assumptions!B5/12 | O8: =Assumptions!B6 | P8: =Assumptions!B7+Assumptions!B8 | Q8: =M8+E8+N8+O8+P8 | R8: 1170 | S8: =Q8-R8 | T8: 2.7 | U8: 18.8 | V8: 22.9 | W8: 1.85 | X8: Yellow
A9: 191 Washington St #317, Boston, MA 02135 | B9: Brighton | C9: https://www.redfin.com/MA/Boston/191-Washington-St-02135/unit-317/home/176134081 | D9: 535000 | E9: 457 | F9: 1 | G9: 1 | H9: 498 | I9: No | J9: 0 spaces | K9: =D9*Assumptions!B3 | L9: =D9-K9 | M9: =-PMT(Assumptions!B2/12,Assumptions!B4*12,L9) | N9: =D9*Assumptions!B5/12 | O9: =Assumptions!B6 | P9: =Assumptions!B7+Assumptions!B8 | Q9: =M9+E9+N9+O9+P9 | R9: 0 | S9: =Q9-R9 | T9: 1.3 | U9: 13.8 | V9: 13.4 | W9: 1.8 | X9: Yellow
A10: 585 Washington St #202, Quincy, MA 02169 | B10: Quincy | C10: https://www.redfin.com/MA/Quincy/585-Washington-St-02169/unit-202/home/200582027 | D10: 600000 | E10: 250 | F10: 2 | G10: 2 | H10: 1203 | I10: No | J10: 1 space | K10: =D10*Assumptions!B3 | L10: =D10-K10 | M10: =-PMT(Assumptions!B2/12,Assumptions!B4*12,L10) | N10: =D10*Assumptions!B5/12 | O10: =Assumptions!B6 | P10: =Assumptions!B7+Assumptions!B8 | Q10: =M10+E10+N10+O10+P10 | R10: 1170 | S10: =Q10-R10 | T10: 3.5 | U10: 19.7 | V10: 23.7 | W10: 1.75 | X10: Yellow
