Workbook

Sheet Assumptions
A1: Assumption | B1: Value
A2: Interest Rate | B2: 0.065
A3: Down Payment $ | B3: 20000
A4: Loan Term Years | B4: 30
A5: Property Tax Rate | B5: 0.012
A6: Insurance $/mo | B6: 150
A7: Utilities $/mo | B7: 250
A8: Internet $/mo | B8: 60

Sheet Listings
A1: Address | B1: Town | C1: Listing URL | D1: Price | E1: HOA/mo | F1: Beds | G1: Baths | H1: Sq Ft | I1: In-Unit Laundry | J1: Parking | K1: Down Payment $ | L1: Loan Amount | M1: Monthly Mortgage | N1: Property Tax/mo | O1: Insurance/mo | P1: Utilities+Internet | Q1: Total Monthly Cost | R1: Area Rental Price (Roommate) | S1: Net Monthly Cost | T1: Drive to MBTA (min) | U1: Drive to Seaport (min) | V1: Drive to Google (min) | W1: Rating Score | X1: Rating
A2: 60 Bryon Rd #1, Chestnut Hill, MA 02467 | B2: Newton | C2: https://www.redfin.com/MA/Chestnut-Hill/60-Bryon-Rd-02467/unit-1/home/9204335 | D2: 338399 | E2: 358 | F2: 2 | G2: 1 | H2: 786 | I2: No | J2: 1 space | K2: =Assumptions!B3 | L2: =D2-K2 | M2: =-PMT(Assumptions!B2/12,Assumptions!B4*12,L2) | N2: =D2*Assumptions!B5/12 | O2: =Assumptions!B6 | P2: =Assumptions!B7+Assumptions!B8 | Q2: =M2+E2+N2+O2+P2 | R2: 1430 | S2: =Q2-R2 | T2: 6.2 | U2: 23.2 | V2: 21.7 | W2: 2.45 | X2: Green
A3: 212-A Quincy Shore Dr, Quincy, MA 02171 | B3: Quincy | C3: https://www.redfin.com/MA/Quincy/212-Quincy-Shore-Dr-02171/home/9009303 | D3: 499900 | E3: 0 | F3: 2 | G3: 1 | H3: 864 | I3: No | J3: 0 spaces | K3: =Assumptions!B3 | L3: =D3-K3 | M3: =-PMT(Assumptions!B2/12,Assumptions!B4*12,L3) | N3: =D3*Assumptions!B5/12 | O3: =Assumptions!B6 | P3: =Assumptions!B7+Assumptions!B8 | Q3: =M3+E3+N3+O3+P3 | R3: 1170 | S3: =Q3-R3 | T3: 5 | U3: 12.6 | V3: 16.7 | W3: 2.4 | X3: Green
A4: 975 Washington Streeet, Newton, MA 02460 | B4: Newton | C4: https://www.redfin.com/MA/Newton/975-Washington-St-02460/home/199915977 | D4: 5 | E4: 0 | I4: No | J4: Unknown | K4: =Assumptions!B3 | L4: =D4-K4 | M4: =-PMT(Assumptions!B2/12,Assumptions!B4*12,L4) | N4: =D4*Assumptions!B5/12 | O4: =Assumptions!B6 | P4: =Assumptions!B7+Assumptions!B8 | Q4: =M4+E4+N4+O4+P4 | R4: 0 | S4: =Q4-R4 | T4: 6.1 | U4: 16.7 | V4: 17.3 | W4: 2.4 | X4: Green
A5: 7 Cypress Rd #703, Brighton, MA 02135 | B5: Watertown | C5: https://www.redfin.com/MA/Brighton/7-Cypress-Rd-02135/unit-703/home/9016137 | D5: 448000 | E5: 315 | F5: 2 | G5: 1 | H5: 576 | I5: No | J5: 1 space | K5: =Assumptions!B3 | L5: =D5-K5 | M5: =-PMT(Assumptions!B2/12,Assumptions!B4*12,L5) | N5: =D5*Assumptions!B5/12 | O5: =Assumptions!B6 | P5: =Assumptions!B7+Assumptions!B8 | Q5: =M5+E5+N5+O5+P5 | R5: 1365 | S5: =Q5-R5 | T5: 3.1 | U5: 13.2 | V5: 12.8 | W5: 2.4 | X5: Green
A6: 88 Gordon St #305, Brighton, MA 02135 | B6: Brighton | C6: https://www.redfin.com/MA/Brighton/88-Gordon-St-02135/unit-305/home/9012102 | D6: 299000 | E6: 292 | F6: 1 | G6: 1 | H6: 283 | I6: No | J6: 0 spaces | K6: =Assumptions!B3 | L6: =D6-K6 | M6: =-PMT(Assumptions!B2/12,Assumptions!B4*12,L6) | N6: =D6*Assumptions!B5/12 | O6: =Assumptions!B6 | P6: =Assumptions!B7+Assumptions!B8 | Q6: =M6+E6+N6+O6+P6 | R6: 0 | S6: =Q6-R6 | T6: 3.1 | U6: 12.6 | V6: 12.2 | W6: 2.4 | X6: Green
A7: 198 Allston St #3, Brighton, MA 02134 | B7: Brighton | C7: https://www.redfin.com/MA/Brighton/198-Allston-St-02135/unit-3/home/9013031 | D7: 270000 | E7: 295 | F7: 1 | G7: 1 | H7: 318 | I7: No | J7: 0 spaces | K7: =Assumptions!B3 | L7: =D7-K7 | M7: =-PMT(Assumptions!B2/12,Assumptions!B4*12,L7) | N7: =D7*Assumptions!B5/12 | O7: =Assumptions!B6 | P7: =Assumptions!B7+Assumptions!B8 | Q7: =M7+E7+N7+O7+P7 | R7: 0 | S7: =Q7-R7 | T7: 0.8 | U7: 12.4 | V7: 12 | W7: 2.4 | X7: Green
A8: 0 Gordon Rd, Medford, MA 02155 | B8: Medford | C8: https://www.redfin.com/MA/Medford/0-Gordon-Rd-02155/home/187063221 | D8: 369000 | E8: 0 | I8: No | J8: Unknown | K8: =Assumptions!B3 | L8: =D8-K8 | M8: =-PMT(Assumptions!B2/12,Assumptions!B4*12,L8) | N8: =D8*Assumptions!B5/12 | O8: =Assumptions!B6 | P8: =Assumptions!B7+Assumptions!B8 | Q8: =M8+E8+N8+O8+P8 | R8: 0 | S8: =Q8-R8 | T8: 5 | U8: 12.2 | V8: 12.4 | W8: 2.35 | X8: Green
A9: 18 Allerton St, Quincy, MA 02169 | B9: Quincy | C9: https://www.redfin.com/MA/Quincy/18-Allerton-St-02169/home/110011603 | D9: 200000 | E9: 0 | I9: No | J9: Unknown | K9: =Assumptions!B3 | L9: =D9-K9 | M9: =-PMT(Assumptions!B2/12,Assumptions!B4*12,L9) | N9: =D9*Assumptions!B5/12 | O9: =Assumptions!B6 | P9: =Assumptions!B7+Assumptions!B8 | Q9: =M9+E9+N9+O9+P9 | R9: 0 | S9: =Q9-R9 | T9: 8.4 | U9: 23.3 | V9: 27.4 | W9: 2.3 | X9: Green
A10: 461 Washington St #301, Brighton, MA 02135 | B10: Brighton | C10: https://www.redfin.com/MA/Brighton/461-Washington-St-02135/unit-301/home/11503967 | D10: 419900 | E10: 431 | F10: 2 | G10: 1 | H10: 696 | I10: No | J10: 0 spaces | K10: =Assumptions!B3 | L10: =D10-K10 | M10: =-PMT(Assumptions!B2/12,Assumptions!B4*12,L10) | N10: =D10*Assumptions!B5/12 | O10: =Assumptions!B6 | P10: =Assumptions!B7+Assumptions!B8 | Q10: =M10+E10+N10+O10+P10 | R10: 1300 | S10: =Q10-R10 | T10: 2.9 | U10: 14.6 | V10: 14.2 | W10: 2.3 | X10: Green
A11: 10 Scottfield Rd #2, Allston, MA 02134 | B11: Allston | C11: https://www.redfin.com/MA/Allston/10-Scottfield-Rd-02134/unit-2/home/9000250 | D11: 474900 | E11: 408 | F11: 2 | G11: 1 | H11: 746 | I11: No | J11: 0 spaces | K11: =Assumptions!B3 | L11: =D11-K11 | M11: =-PMT(Assumptions!B2/12,Assumptions!B4*12,L11) | N11: =D11*Assumptions!B5/12 | O11: =Assumptions!B6 | P11: =Assumptions!B7+Assumptions!B8 | Q11: =M11+E11+N11+O11+P11 | R11: 1235 | S11: =Q11-R11 | T11: 2 | U11: 12.2 | V11: 11.8 | W11: 2.3 | X11: Green
A12: 8 Avon St #10, Somerville, MA 02143 | B12: Somerville | C12: https://www.redfin.com/MA/Somerville/8-Avon-St-02143/unit-10/home/8759429 | D12: 500000 | E12: 288 | F12: 2 | G12: 1 | H12: 645 | I12: No | J12: 1 space | K12: =Assumptions!B3 | L12: =D12-K12 | M12: =-PMT(Assumptions!B2/12,Assumptions!B4*12,L12) | N12: =D12*Assumptions!B5/12 | O12: =Assumptions!B6 | P12: =Assumptions!B7+Assumptions!B8 | Q12: =M12+E12+N12+O12+P12 | R12: 1495 | S12: =Q12-R12 | T12: 3.4 | U12: 11.9 | V12: 7.6 | W12: 2.3 | X12: Green
A13: 199 Prospect St Unit A1, Cambridge, MA 02139 | B13: Cambridge | C13: https://www.redfin.com/MA/Cambridge/199-Prospect-St-02139/unit-A1/home/110093910 | D13: 399999 | E13: 183 | F13: 0 | G13: 1 | H13: 389 | I13: No | J13: 0 spaces | K13: =Assumptions!B3 | L13: =D13-K13 | M13: =-PMT(Assumptions!B2/12,Assumptions!B4*12,L13) | N13: =D13*Assumptions!B5/12 | O13: =Assumptions!B6 | P13: =Assumptions!B7+Assumptions!B8 | Q13: =M13+E13+N13+O13+P13 | R13: 0 | S13: =Q13-R13 | T13: 2.4 | U13: 11.2 | V13: 4.1 | W13: 2.3 | X13: Yellow
A14: 186 Lexington St #8, Watertown, MA 02472 | B14: Watertown | C14: https://www.redfin.com/MA/Watertown/186-Lexington-St-02472/unit-8/home/11690422 | D14: 394900 | E14: 350 | F14: 2 | G14: 1 | H14: 600 | I14: No | J14: 1 space | K14: =Assumptions!B3 | L14: =D14-K14 | M14: =-PMT(Assumptions!B2/12,Assumptions!B4*12,L14) | N14: =D14*Assumptions!B5/12 | O14: =Assumptions!B6 | P14: =Assumptions!B7+Assumptions!B8 | Q14: =M14+E14+N14+O14+P14 | R14: 1365 | S14: =Q14-R14 | T14: 12.1 | U14: 18.5 | V14: 17.2 | W14: 2.25 | X14: Yellow
A15: 194 Lexington St #1, Watertown, MA 02472 | B15: Watertown | C15: https://www.redfin.com/MA/Watertown/194-Lexington-St-02472/unit-1/home/11690433 | D15: 375000 | E15: 350 | F15: 2 | G15: 1 | H15: 600 | I15: No | J15: 1 space | K15: =Assumptions!B3 | L15: =D15-K15 | M15: =-PMT(Assumptions!B2/12,Assumptions!B4*12,L15) | N15: =D15*Assumptions!B5/12 | O15: =Assumptions!B6 | P15: =Assumptions!B7+Assumptions!B8 | Q15: =M15+E15+N15+O15+P15 | R15: 1365 | S15: =Q15-R15 | T15: 12.4 | U15: 18.9 | V15: 17 | W15: 2.25 | X15: Yellow
A16: 133 Warren St #3, Watertown, MA 02472 | B16: Watertown | C16: https://www.redfin.com/MA/Watertown/133-Warren-St-02472/unit-3/home/11690534 | D16: 375000 | E16: 350 | F16: 2 | G16: 1 | H16: 600 | I16: No | J16: 2 spaces | K16: =Assumptions!B3 | L16: =D16-K16 | M16: =-PMT(Assumptions!B2/12,Assumptions!B4*12,L16) | N16: =D16*Assumptions!B5/12 | O16: =Assumptions!B6 | P16: =Assumptions!B7+Assumptions!B8 | Q16: =M16+E16+N16+O16+P16 | R16: 1365 | S16: =Q16-R16 | T16: 12.3 | U16: 18.7 | V16: 17.3 | W16: 2.25 | X16: Yellow
A17: 38 Carey Ave #3, Watertown, MA 02472 | B17: Watertown | C17: https://www.redfin.com/MA/Watertown/38-Carey-Ave-02472/unit-3/home/11690323 | D17: 374899 | E17: 350 | F17: 2 | G17: 1 | H17: 600 | I17: No | J17: 1 space | K17: =Assumptions!B3 | L17: =D17-K17 | M17: =-PMT(Assumptions!B2/12,Assumptions!B4*12,L17) | N17: =D17*Assumptions!B5/12 | O17: =Assumptions!B6 | P17: =Assumptions!B7+Assumptions!B8 | Q17: =M17+E17+N17+O17+P17 | R17: 1365 | S17: =Q17-R17 | T17: 12.6 | U17: 19.1 | V17: 17.2 | W17: 2.25 | X17: Yellow
A18: 59 Terne Rd, Quincy, MA 02169 | B18: Quincy | C18: https://www.redfin.com/MA/Quincy/59-Terne-Rd-02169/home/11828578 | D18: 499900 | E18: 0 | F18: 3 | G18: 2 | H18: 1450 | I18: No | J18: 1 space | K18: =Assumptions!B3 | L18: =D18-K18 | M18: =-PMT(Assumptions!B2/12,Assumptions!B4*12,L18) | N18: =D18*Assumptions!B5/12 | O18: =Assumptions!B6 | P18: =Assumptions!B7+Assumptions!B8 | Q18: =M18+E18+N18+O18+P18 | R18: 1170 | S18: =Q18-R18 | T18: 5.8 | U18: 20.7 | V18: 24.8 | W18: 2.25 | X18: Yellow
A19: 1564 Commonwealth Ave #3, Brighton, MA 02135 | B19: Brighton | C19: https://www.redfin.com/MA/Brighton/1564-Commonwealth-Ave-02135/unit-3/home/9017145 | D19: 315000 | E19: 369 | F19: 0 | G19: 1 | H19: 306 | I19: No | J19: 0 spaces | K19: =Assumptions!B3 | L19: =D19-K19 | M19: =-PMT(Assumptions!B2/12,Assumptions!B4*12,L19) | N19: =D19*Assumptions!B5/12 | O19: =Assumptions!B6 | P19: =Assumptions!B7+Assumptions!B8 | Q19: =M19+E19+N19+O19+P19 | R19: 0 | S19: =Q19-R19 | T19: 2 | U19: 13.5 | V19: 13.1 | W19: 2.2 | X19: Yellow
A20: 45 Gordon St #4, Allston, MA 02134 | B20: Allston | C20: https://www.redfin.com/MA/Allston/45-Gordon-St-02134/unit-4/home/8999903 | D20: 489000 | E20: 350 | F20: 2 | G20: 1 | H20: 675 | I20: No | J20: 0 spaces | K20: =Assumptions!B3 | L20: =D20-K20 | M20: =-PMT(Assumptions!B2/12,Assumptions!B4*12,L20) | N20: =D20*Assumptions!B5/12 | O20: =Assumptions!B6 | P20: =Assumptions!B7+Assumptions!B8 | Q20: =M20+E20+N20+O20+P20 | R20: 1235 | S20: =Q20-R20 | T20: 3 | U20: 11.3 | V20: 10.9 | W20: 2.2 | X20: Yellow
A21: 69 Park Dr #10, Boston, MA 02215 | B21: Brookline | C21: https://www.redfin.com/MA/Boston/69-Park-Dr-02215/unit-10/home/9274080 | D21: 360000 | E21: 381 | F21: 0 | G21: 1 | H21: 320 | I21: No | J21: 0 spaces | K21: =Assumptions!B3 | L21: =D21-K21 | M21: =-PMT(Assumptions!B2/12,Assumptions!B4*12,L21) | N21: =D21*Assumptions!B5/12 | O21: =Assumptions!B6 | P21: =Assumptions!B7+Assumptions!B8 | Q21: =M21+E21+N21+O21+P21 | R21: 0 | S21: =Q21-R21 | T21: 1.7 | U21: 11.2 | V21: 9 | W21: 2.2 | X21: Yellow
A22: 7 Mortimer Pl #2, Somerville, MA 02145 | B22: Somerville | C22: https://www.redfin.com/MA/Somerville/7-Mortimer-Pl-02145/unit-2/home/12389682 | D22: 320000 | E22: 366 | F22: 0 | G22: 1 | H22: 429 | I22: No | J22: 1 space | K22: =Assumptions!B3 | L22: =D22-K22 | M22: =-PMT(Assumptions!B2/12,Assumptions!B4*12,L22) | N22: =D22*Assumptions!B5/12 | O22: =Assumptions!B6 | P22: =Assumptions!B7+Assumptions!B8 | Q22: =M22+E22+N22+O22+P22 | R22: 0 | S22: =Q22-R22 | T22: 1.6 | U22: 10.5 | V22: 7.1 | W22: 2.2 | X22: Yellow
A23: 195 Thomas Burgin Pkwy #301, Quincy, MA 02169 | B23: Quincy | C23: https://www.redfin.com/MA/Quincy/195-Thomas-Burgin-Pkwy-02169/unit-301/home/8931809 | D23: 250000 | E23: 393 | F23: 1 | G23: 1 | H23: 447 | I23: No | J23: 0 spaces | K23: =Assumptions!B3 | L23: =D23-K23 | M23: =-PMT(Assumptions!B2/12,Assumptions!B4*12,L23) | N23: =D23*Assumptions!B5/12 | O23: =Assumptions!B6 | P23: =Assumptions!B7+Assumptions!B8 | Q23: =M23+E23+N23+O23+P23 | R23: 0 | S23: =Q23-R23 | T23: 2.2 | U23: 17.6 | V23: 21.7 | W23: 2.15 | X23: Yellow
A24: 195 Thomas Burgin Pkwy #212, Quincy, MA 02169 | B24: Quincy | C24: https://www.redfin.com/MA/Quincy/195-Thomas-Burgin-Pkwy-02169/unit-212/home/8931803 | D24: 249900 | E24: 344 | F24: 0 | G24: 1 | H24: 355 | I24: No | J24: 0 spaces | K24: =Assumptions!B3 | L24: =D24-K24 | M24: =-PMT(Assumptions!B2/12,Assumptions!B4*12,L24) | N24: =D24*Assumptions!B5/12 | O24: =Assumptions!B6 | P24: =Assumptions!B7+Assumptions!B8 | Q24: =M24+E24+N24+O24+P24 | R24: 0 | S24: =Q24-R24 | T24: 2.2 | U24: 17.6 | V24: 21.7 | W24: 2.15 | X24: Yellow
A25: 10 Naviens Ln #1, Waltham, MA 02453 | B25: Waltham | C25: https://www.redfin.com/MA/Waltham/10-Naviens-Ln-02453/unit-1/home/76478882 | D25: 499900 | E25: 134 | F25: 2 | G25: 1 | H25: 1008 | I25: No | J25: 2 spaces | K25: =Assumptions!B3 | L25: =D25-K25 | M25: =-PMT(Assumptions!B2/12,Assumptions!B4*12,L25) | N25: =D25*Assumptions!B5/12 | O25: =Assumptions!B6 | P25: =Assumptions!B7+Assumptions!B8 | Q25: =M25+E25+N25+O25+P25 | R25: 1235 | S25: =Q25-R25 | T25: 10.9 | U25: 19.2 | V25: 19.7 | W25: 2.15 | X25: Yellow
A26: 66 Bryon Rd #2, Chestnut Hill, MA 02467 | B26: Newton | C26: https://www.redfin.com/MA/Chestnut-Hill/66-Bryon-Rd-02467/unit-2/home/9204203 | D26: 385000 | E26: 422 | F26: 2 | G26: 1 | H26: 780 | I26: No | J26: 2 spaces | K26: =Assumptions!B3 | L26: =D26-K26 | M26: =-PMT(Assumptions!B2/12,Assumptions!B4*12,L26) | N26: =D26*Assumptions!B5/12 | O26: =Assumptions!B6 | P26: =Assumptions!B7+Assumptions!B8 | Q26: =M26+E26+N26+O26+P26 | R26: 1430 | S26: =Q26-R26 | T26: 5.9 | U26: 22.9 | V26: 21.4 | W26: 2.15 | X26: Yellow
A27: 5 Braemore Rd #10, Brighton, MA 02135 | B27: Brighton | C27: https://www.redfin.com/MA/Brighton/5-Braemore-Rd-02135/unit-10/home/9308549 | D27: 315000 | E27: 352 | F27: 1 | G27: 1 | H27: 385 | I27: No | J27: 0 spaces | K27: =Assumptions!B3 | L27: =D27-K27 | M27: =-PMT(Assumptions!B2/12,Assumptions!B4*12,L27) | N27: =D27*Assumptions!B5/12 | O27: =Assumptions!B6 | P27: =Assumptions!B7+Assumptions!B8 | Q27: =M27+E27+N27+O27+P27 | R27: 0 | S27: =Q27-R27 | T27: 1.7 | U27: 15.9 | V27: 14.1 | W27: 2.15 | X27: Yellow
A28: 64 Bryon Rd #1, Chestnut Hill, MA 02467 | B28: Newton | C28: https://www.redfin.com/MA/Chestnut-Hill/64-Bryon-Rd-02467/unit-1/home/9204182 | D28: 399000 | E28: 422 | F28: 2 | G28: 1 | H28: 780 | I28: No | J28: 2 spaces | K28: =Assumptions!B3 | L28: =D28-K28 | M28: =-PMT(Assumptions!B2/12,Assumptions!B4*12,L28) | N28: =D28*Assumptions!B5/12 | O28: =Assumptions!B6 | P28: =Assumptions!B7+Assumptions!B8 | Q28: =M28+E28+N28+O28+P28 | R28: 1430 | S28: =Q28-R28 | T28: 5.8 | U28: 22.9 | V28: 21.4 | W28: 2.15 | X28: Yellow
A29: 1641 Commonwealth Ave #16, Brighton, MA 02135 | B29: Brighton | C29: https://www.redfin.com/MA/Brighton/1641-Commonwealth-Ave-02135/unit-16/home/9002891 | D29: 349000 | E29: 399 | F29: 1 | G29: 1 | H29: 407 | I29: No | J29: 0 spaces | K29: =Assumptions!B3 | L29: =D29-K29 | M29: =-PMT(Assumptions!B2/12,Assumptions!B4*12,L29) | N29: =D29*Assumptions!B5/12 | O29: =Assumptions!B6 | P29: =Assumptions!B7+Assumptions!B8 | Q29: =M29+E29+N29+O29+P29 | R29: 0 | S29: =Q29-R29 | T29: 0.4 | U29: 15 | V29: 14.6 | W29: 2.1 | X29: Yellow
A30: 239 Kelton St #41, Allston, MA 02134 | B30: Allston | C30: https://www.redfin.com/MA/Allston/239-Kelton-St-02134/unit-41/home/9001010 | D30: 475000 | E30: 497 | F30: 2 | G30: 1 | H30: 690 | I30: No | J30: 0 spaces | K30: =Assumptions!B3 | L30: =D30-K30 | M30: =-PMT(Assumptions!B2/12,Assumptions!B4*12,L30) | N30: =D30*Assumptions!B5/12 | O30: =Assumptions!B6 | P30: =Assumptions!B7+Assumptions!B8 | Q30: =M30+E30+N30+O30+P30 | R30: 1235 | S30: =Q30-R30 | T30: 2.6 | U30: 12.9 | V30: 12.5 | W30: 2.1 | X30: Yellow
A31: 466 Commonwealth Ave #305, Boston, MA 02215 | B31: Brookline | C31: https://www.redfin.com/MA/Boston/466-Commonwealth-Ave-02215/unit-305/home/9269210 | D31: 489000 | E31: 314 | F31: 0 | G31: 1 | H31: 346 | I31: No | J31: 0 spaces | K31: =Assumptions!B3 | L31: =D31-K31 | M31: =-PMT(Assumptions!B2/12,Assumptions!B4*12,L31) | N31: =D31*Assumptions!B5/12 | O31: =Assumptions!B6 | P31: =Assumptions!B7+Assumptions!B8 | Q31: =M31+E31+N31+O31+P31 | R31: 0 | S31: =Q31-R31 | T31: 1.3 | U31: 11.2 | V31: 7.7 | W31: 2.1 | X31: Yellow
A32: 64 Queensberry St #114, Boston, MA 02215 | B32: Brookline | C32: https://www.redfin.com/MA/Boston/64-Queensberry-St-02215/unit-114/home/9241481 | D32: 425000 | E32: 395 | F32: 0 | G32: 1 | H32: 390 | I32: No | J32: 0 spaces | K32: =Assumptions!B3 | L32: =D32-K32 | M32: =-PMT(Assumptions!B2/12,Assumptions!B4*12,L32) | N32: =D32*Assumptions!B5/12 | O32: =Assumptions!B6 | P32: =Assumptions!B7+Assumptions!B8 | Q32: =M32+E32+N32+O32+P32 | R32: 0 | S32: =Q32-R32 | T32: 1.3 | U32: 11.9 | V32: 9.1 | W32: 2.1 | X32: Yellow
A33: 32 Almont St Unit 32-1, Medford, MA 02155 | B33: Medford | C33: https://www.redfin.com/MA/Medford/32-Almont-St-02155/unit-32-1/home/11802621 | D33: 330000 | E33: 291 | F33: 1 | G33: 1 | H33: 528 | I33: No | J33: 0 spaces | K33: =Assumptions!B3 | L33: =D33-K33 | M33: =-PMT(Assumptions!B2/12,Assumptions!B4*12,L33) | N33: =D33*Assumptions!B5/12 | O33: =Assumptions!B6 | P33: =Assumptions!B7+Assumptions!B8 | Q33: =M33+E33+N33+O33+P33 | R33: 0 | S33: =Q33-R33 | T33: 3.4 | U33: 11.4 | V33: 11.2 | W33: 2.1 | X33: Yellow
A34: 84 Grant St #12, Somerville, MA 02145 | B34: Somerville | C34: https://www.redfin.com/MA/Somerville/84-Grant-St-02145/unit-12/home/8758283 | D34: 395000 | E34: 338 | F34: 1 | G34: 1 | H34: 640 | I34: No | J34: 1 space | K34: =Assumptions!B3 | L34: =D34-K34 | M34: =-PMT(Assumptions!B2/12,Assumptions!B4*12,L34) | N34: =D34*Assumptions!B5/12 | O34: =Assumptions!B6 | P34: =Assumptions!B7+Assumptions!B8 | Q34: =M34+E34+N34+O34+P34 | R34: 0 | S34: =Q34-R34 | T34: 3.2 | U34: 8.2 | V34: 6.8 | W34: 2.1 | X34: Yellow
A35: 500 Salem St #307, Medford, MA 02155 | B35: Medford | C35: https://www.redfin.com/MA/Medford/500-Salem-St-02155/unit-307/home/11784227 | D35: 549000 | E35: 332 | F35: 2 | G35: 2 | H35: 1086 | I35: No | J35: 2 spaces | K35: =Assumptions!B3 | L35: =D35-K35 | M35: =-PMT(Assumptions!B2/12,Assumptions!B4*12,L35) | N35: =D35*Assumptions!B5/12 | O35: =Assumptions!B6 | P35: =Assumptions!B7+Assumptions!B8 | Q35: =M35+E35+N35+O35+P35 | R35: 1235 | S35: =Q35-R35 | T35: 2.2 | U35: 11.6 | V35: 10.2 | W35: 2.1 | X35: Yellow
A36: 872 Massachusetts Ave #303, Cambridge, MA 02139 | B36: Cambridge | C36: https://www.redfin.com/MA/Cambridge/872-Massachusetts-Ave-02139/unit-303/home/136730647 | D36: 598000 | E36: 0 | F36: 1 | G36: 1.5 | H36: 750 | I36: No | J36: 1 space | K36: =Assumptions!B3 | L36: =D36-K36 | M36: =-PMT(Assumptions!B2/12,Assumptions!B4*12,L36) | N36: =D36*Assumptions!B5/12 | O36: =Assumptions!B6 | P36: =Assumptions!B7+Assumptions!B8 | Q36: =M36+E36+N36+O36+P36 | R36: 0 | S36: =Q36-R36 | T36: 1.2 | U36: 12.4 | V36: 5.8 | W36: 2.05 | X36: Yellow
A37: 32 Sidlaw #6, Brighton, MA 02135 | B37: Brighton | C37: https://www.redfin.com/MA/Brighton/32-Sidlaw-Rd-02135/unit-6/home/9006968 | D37: 335000 | E37: 332 | F37: 0 | G37: 1 | H37: 346 | I37: No | J37: 0 spaces | K37: =Assumptions!B3 | L37: =D37-K37 | M37: =-PMT(Assumptions!B2/12,Assumptions!B4*12,L37) | N37: =D37*Assumptions!B5/12 | O37: =Assumptions!B6 | P37: =Assumptions!B7+Assumptions!B8 | Q37: =M37+E37+N37+O37+P37 | R37: 0 | S37: =Q37-R37 | T37: 1.2 | U37: 16.1 | V37: 14.5 | W37: 2.05 | X37: Yellow
A38: 88 Gordon St #304, Brighton, MA 02135 | B38: Brighton | C38: https://www.redfin.com/MA/Brighton/88-Gordon-St-02135/unit-304/home/9226535 | D38: 399000 | E38: 436 | F38: 1 | G38: 1 | H38: 533 | I38: No | J38: 1 space | K38: =Assumptions!B3 | L38: =D38-K38 | M38: =-PMT(Assumptions!B2/12,Assumptions!B4*12,L38) | N38: =D38*Assumptions!B5/12 | O38: =Assumptions!B6 | P38: =Assumptions!B7+Assumptions!B8 | Q38: =M38+E38+N38+O38+P38 | R38: 0 | S38: =Q38-R38 | T38: 3.1 | U38: 12.6 | V38: 12.2 | W38: 2 | X38: Yellow
A39: 15 Commonwealth Ct #10, Brighton, MA 02135 | B39: Brighton | C39: https://www.redfin.com/MA/Brighton/15-Commonwealth-Ct-02135/unit-10/home/9014600 | D39: 379900 | E39: 500 | F39: 1 | G39: 1 | H39: 688 | I39: No | J39: 1 space | K39: =Assumptions!B3 | L39: =D39-K39 | M39: =-PMT(Assumptions!B2/12,Assumptions!B4*12,L39) | N39: =D39*Assumptions!B5/12 | O39: =Assumptions!B6 | P39: =Assumptions!B7+Assumptions!B8 | Q39: =M39+E39+N39+O39+P39 | R39: 0 | S39: =Q39-R39 | T39: 1.2 | U39: 12.8 | V39: 12.4 | W39: 2 | X39: Yellow
A40: 1691 Commonwealth Ave #31, Brighton, MA 02135 | B40: Brighton | C40: https://www.redfin.com/MA/Brighton/1691-Commonwealth-Ave-02135/unit-31/home/9020583 | D40: 414900 | E40: 360 | F40: 1 | G40: 1 | H40: 520 | I40: No | J40: 0 spaces | K40: =Assumptions!B3 | L40: =D40-K40 | M40: =-PMT(Assumptions!B2/12,Assumptions!B4*12,L40) | N40: =D40*Assumptions!B5/12 | O40: =Assumptions!B6 | P40: =Assumptions!B7+Assumptions!B8 | Q40: =M40+E40+N40+O40+P40 | R40: 0 | S40: =Q40-R40 | T40: 1.6 | U40: 14.9 | V40: 14.5 | W40: 2 | X40: Yellow
A41: 191 Washington St, Boston, MA 02135 | B41: Brighton | C41: https://www.redfin.com/MA/Boston/191-Washington-St-02135/home/184088757 | D41: 564800 | E41: 0 | F41: 1 | G41: 1 | H41: 498 | I41: No | J41: 0 spaces | K41: =Assumptions!B3 | L41: =D41-K41 | M41: =-PMT(Assumptions!B2/12,Assumptions!B4*12,L41) | N41: =D41*Assumptions!B5/12 | O41: =Assumptions!B6 | P41: =Assumptions!B7+Assumptions!B8 | Q41: =M41+E41+N41+O41+P41 | R41: 0 | S41: =Q41-R41 | T41: 2.1 | U41: 13.6 | V41: 13.2 | W41: 2 | X41: Yellow
A42: 17 Buckingham St #3, Somerville, MA 02143 | B42: Somerville | C42: https://www.redfin.com/MA/Somerville/17-Buckingham-St-02143/unit-3/home/200344678 | D42: 474999 | E42: 233 | F42: 1 | G42: 1 | H42: 595 | I42: No | J42: 1 space | K42: =Assumptions!B3 | L42: =D42-K42 | M42: =-PMT(Assumptions!B2/12,Assumptions!B4*12,L42) | N42: =D42*Assumptions!B5/12 | O42: =Assumptions!B6 | P42: =Assumptions!B7+Assumptions!B8 | Q42: =M42+E42+N42+O42+P42 | R42: 0 | S42: =Q42-R42 | T42: 3.2 | U42: 11.7 | V42: 5.9 | W42: 2 | X42: Yellow
A43: 367 Somerville Ave Unit G, Somerville, MA 02143 | B43: Somerville | C43: https://www.redfin.com/MA/Somerville/367-Somerville-Ave-02143/unit-G/home/8751476 | D43: 425000 | E43: 304 | F43: 1 | G43: 1 | H43: 419 | I43: No | J43: 0 spaces | K43: =Assumptions!B3 | L43: =D43-K43 | M43: =-PMT(Assumptions!B2/12,Assumptions!B4*12,L43) | N43: =D43*Assumptions!B5/12 | O43: =Assumptions!B6 | P43: =Assumptions!B7+Assumptions!B8 | Q43: =M43+E43+N43+O43+P43 | R43: 0 | S43: =Q43-R43 | T43: 2.1 | U43: 10.3 | V43: 6 | W43: 2 | X43: Yellow
A44: 5 Waldo Ave Unit 2A, Somerville, MA 02143 | B44: Somerville | C44: https://www.redfin.com/MA/Somerville/5-Waldo-Ave-02143/unit-2A/home/8759932 | D44: 425000 | E44: 317 | F44: 1 | G44: 1 | H44: 530 | I44: No | J44: 0 spaces | K44: =Assumptions!B3 | L44: =D44-K44 | M44: =-PMT(Assumptions!B2/12,Assumptions!B4*12,L44) | N44: =D44*Assumptions!B5/12 | O44: =Assumptions!B6 | P44: =Assumptions!B7+Assumptions!B8 | Q44: =M44+E44+N44+O44+P44 | R44: 0 | S44: =Q44-R44 | T44: 3.2 | U44: 11.7 | V44: 6 | W44: 2 | X44: Yellow
A45: 764 Cambridge St #6, Cambridge, MA 02141 | B45: Cambridge | C45: https://www.redfin.com/MA/Cambridge/764-Cambridge-St-02141/unit-6/home/11601252 | D45: 490000 | E45: 385 | F45: 1 | G45: 1 | H45: 620 | I45: No | J45: 0 spaces | K45: =Assumptions!B3 | L45: =D45-K45 | M45: =-PMT(Assumptions!B2/12,Assumptions!B4*12,L45) | N45: =D45*Assumptions!B5/12 | O45: =Assumptions!B6 | P45: =Assumptions!B7+Assumptions!B8 | Q45: =M45+E45+N45+O45+P45 | R45: 0 | S45: =Q45-R45 | T45: 2.9 | U45: 8.7 | V45: 3.7 | W45: 2 | X45: Yellow
A46: 50 Water St #24, Medford, MA 02155 | B46: Medford | C46: https://www.redfin.com/MA/Medford/50-Water-St-02155/unit-24/home/11787534 | D46: 389900 | E46: 465 | F46: 1 | G46: 1 | H46: 634 | I46: No | J46: 1 space | K46: =Assumptions!B3 | L46: =D46-K46 | M46: =-PMT(Assumptions!B2/12,Assumptions!B4*12,L46) | N46: =D46*Assumptions!B5/12 | O46: =Assumptions!B6 | P46: =Assumptions!B7+Assumptions!B8 | Q46: =M46+E46+N46+O46+P46 | R46: 0 | S46: =Q46-R46 | T46: 3.5 | U46: 10.3 | V46: 10.5 | W46: 2 | X46: Yellow
A47: 118 Riverway Unit 12A, Boston, MA 02215 | B47: Brookline | C47: https://www.redfin.com/MA/Boston/118-Riverway-02215/unit-12A/home/9262088 | D47: 519900 | E47: 330 | F47: 0 | G47: 1 | H47: 503 | I47: No | J47: 0 spaces | K47: =Assumptions!B3 | L47: =D47-K47 | M47: =-PMT(Assumptions!B2/12,Assumptions!B4*12,L47) | N47: =D47*Assumptions!B5/12 | O47: =Assumptions!B6 | P47: =Assumptions!B7+Assumptions!B8 | Q47: =M47+E47+N47+O47+P47 | R47: 0 | S47: =Q47-R47 | T47: 2.5 | U47: 14.1 | V47: 10.3 | W47: 2 | X47: Yellow
A48: 1-Bedroom Plan, Quincy, MA 02169 | B48: Quincy | C48: https://www.redfin.com/MA/Quincy/Quincy/1-Bedroom/home/197950895 | D48: 399000 | E48: 0 | F48: 1 | G48: 1 | H48: 500 | I48: No | J48: Unknown | K48: =Assumptions!B3 | L48: =D48-K48 | M48: =-PMT(Assumptions!B2/12,Assumptions!B4*12,L48) | N48: =D48*Assumptions!B5/12 | O48: =Assumptions!B6 | P48: =Assumptions!B7+Assumptions!B8 | Q48: =M48+E48+N48+O48+P48 | R48: 0 | S48: =Q48-R48 | T48: 1.4 | U48: 17.1 | V48: 21.2 | W48: 1.95 | X48: Yellow
A49: 2-Bedrooms Plan, Quincy, MA 02169 | B49: Quincy | C49: https://www.redfin.com/MA/Quincy/Quincy/2-Bedrooms/home/197950891 | D49: 599000 | E49: 0 | F49: 2 | G49: 2 | H49: 900 | I49: No | J49: Unknown | K49: =Assumptions!B3 | L49: =D49-K49 | M49: =-PMT(Assumptions!B2/12,Assumptions!B4*12,L49) | N49: =D49*Assumptions!B5/12 | O49: =Assumptions!B6 | P49: =Assumptions!B7+Assumptions!B8 | Q49: =M49+E49+N49+O49+P49 | R49: 1170 | S49: =Q49-R49 | T49: 1.4 | U49: 17.1 | V49: 21.2 | W49: 1.95 | X49: Yellow
A50: 31 Warren St Unit B1, Waltham, MA 02453 | B50: Waltham | C50: https://www.redfin.com/MA/Waltham/31-Warren-St-02453/unit-B1/home/11815449 | D50: 429000 | E50: 497 | F50: 2 | G50: 1 | H50: 708 | I50: No | J50: 2 spaces | K50: =Assumptions!B3 | L50: =D50-K50 | M50: =-PMT(Assumptions!B2/12,Assumptions!B4*12,L50) | N50: =D50*Assumptions!B5/12 | O50: =Assumptions!B6 | P50: =Assumptions!B7+Assumptions!B8 | Q50: =M50+E50+N50+O50+P50 | R50: 1235 | S50: =Q50-R50 | T50: 10.5 | U50: 19.2 | V50: 18 | W50: 1.95 | X50: Yellow
A51: 1151 Walnut #304, Newton, MA 02461 | B51: Newton | C51: https://www.redfin.com/MA/Newton/1151-Walnut-St-02461/unit-304/home/200156614 | D51: 495000 | E51: 196 | F51: 0 | G51: 1 | H51: 511 | I51: No | J51: 0 spaces | K51: =Assumptions!B3 | L51: =D51-K51 | M51: =-PMT(Assumptions!B2/12,Assumptions!B4*12,L51) | N51: =D51*Assumptions!B5/12 | O51: =Assumptions!B6 | P51: =Assumptions!B7+Assumptions!B8 | Q51: =M51+E51+N51+O51+P51 | R51: 0 | S51: =Q51-R51 | T51: 0.1 | U51: 19.4 | V51: 19.9 | W51: 1.95 | X51: Yellow
A52: 42 Bryon Rd #6, Chestnut Hill, MA 02132 | B52: Newton | C52: https://www.redfin.com/MA/Chestnut-Hill/42-Bryon-Rd-02467/unit-6/home/9204495 | D52: 449900 | E52: 465 | F52: 2 | G52: 1 | H52: 780 | I52: No | J52: 2 spaces | K52: =Assumptions!B3 | L52: =D52-K52 | M52: =-PMT(Assumptions!B2/12,Assumptions!B4*12,L52) | N52: =D52*Assumptions!B5/12 | O52: =Assumptions!B6 | P52: =Assumptions!B7+Assumptions!B8 | Q52: =M52+E52+N52+O52+P52 | R52: 1430 | S52: =Q52-R52 | T52: 6.1 | U52: 23.2 | V52: 21.6 | W52: 1.95 | X52: Yellow
A53: 7 Lothian Rd Unit B, Brighton, MA 02135 | B53: Brighton | C53: https://www.redfin.com/MA/Brighton/7-Lothian-Rd-02135/unit-B/home/9025402 | D53: 539900 | E53: 417 | F53: 3 | G53: 1 | H53: 900 | I53: No | J53: 0 spaces | K53: =Assumptions!B3 | L53: =D53-K53 | M53: =-PMT(Assumptions!B2/12,Assumptions!B4*12,L53) | N53: =D53*Assumptions!B5/12 | O53: =Assumptions!B6 | P53: =Assumptions!B7+Assumptions!B8 | Q53: =M53+E53+N53+O53+P53 | R53: 1300 | S53: =Q53-R53 | T53: 1.2 | U53: 16 | V53: 14.4 | W53: 1.95 | X53: Yellow
A54: 6 Washington Ave #11, Cambridge, MA 02140 | B54: Cambridge | C54: https://www.redfin.com/MA/Cambridge/6-Washington-Ave-02140/unit-11/home/11585376 | D54: 469000 | E54: 320 | F54: 0 | G54: 1 | H54: 433 | I54: No | J54: 0 spaces | K54: =Assumptions!B3 | L54: =D54-K54 | M54: =-PMT(Assumptions!B2/12,Assumptions!B4*12,L54) | N54: =D54*Assumptions!B5/12 | O54: =Assumptions!B6 | P54: =Assumptions!B7+Assumptions!B8 | Q54: =M54+E54+N54+O54+P54 | R54: 0 | S54: =Q54-R54 | T54: 2.1 | U54: 15.8 | V54: 10.3 | W54: 1.95 | X54: Yellow
A55: 31 Weston St #2, Waltham, MA 02453 | B55: Waltham | C55: https://www.redfin.com/MA/Waltham/31-Weston-St-02453/unit-2/home/11822835 | D55: 425000 | E55: 430 | F55: 2 | G55: 1 | H55: 1175 | I55: No | J55: 0 spaces | K55: =Assumptions!B3 | L55: =D55-K55 | M55: =-PMT(Assumptions!B2/12,Assumptions!B4*12,L55) | N55: =D55*Assumptions!B5/12 | O55: =Assumptions!B6 | P55: =Assumptions!B7+Assumptions!B8 | Q55: =M55+E55+N55+O55+P55 | R55: 1235 | S55: =Q55-R55 | T55: 9.8 | U55: 22.9 | V55: 22 | W55: 1.95 | X55: Yellow
A56: 1151 Walnut #207, Newton, MA 02461 | B56: Newton | C56: https://www.redfin.com/MA/Newton/1151-Walnut-St-02461/unit-207/home/198507382 | D56: 450000 | E56: 164 | F56: 0 | G56: 1 | H56: 455 | I56: No | J56: 0 spaces | K56: =Assumptions!B3 | L56: =D56-K56 | M56: =-PMT(Assumptions!B2/12,Assumptions!B4*12,L56) | N56: =D56*Assumptions!B5/12 | O56: =Assumptions!B6 | P56: =Assumptions!B7+Assumptions!B8 | Q56: =M56+E56+N56+O56+P56 | R56: 0 | S56: =Q56-R56 | T56: 0.1 | U56: 19.4 | V56: 19.9 | W56: 1.95 | X56: Yellow
A57: 138 Quincy Shore Dr #170, Quincy, MA 02171 | B57: Quincy | C57: https://www.redfin.com/MA/Quincy/138-Quincy-Shore-Dr-02171/unit-170/home/9010050 | D57: 589999 | E57: 497 | F57: 2 | G57: 2.5 | H57: 1460 | I57: No | J57: 2 spaces | K57: =Assumptions!B3 | L57: =D57-K57 | M57: =-PMT(Assumptions!B2/12,Assumptions!B4*12,L57) | N57: =D57*Assumptions!B5/12 | O57: =Assumptions!B6 | P57: =Assumptions!B7+Assumptions!B8 | Q57: =M57+E57+N57+O57+P57 | R57: 1170 | S57: =Q57-R57 | T57: 4.5 | U57: 12.1 | V57: 16.2 | W57: 1.9 | X57: Yellow
A58: 35 Homer Ave #7, Cambridge, MA 02138 | B58: Watertown | C58: https://www.redfin.com/MA/Cambridge/35-Homer-Ave-02138/unit-7/home/12442078 | D58: 500000 | E58: 325 | F58: 1 | G58: 1 | H58: 504 | I58: No | J58: 1 space | K58: =Assumptions!B3 | L58: =D58-K58 | M58: =-PMT(Assumptions!B2/12,Assumptions!B4*12,L58) | N58: =D58*Assumptions!B5/12 | O58: =Assumptions!B6 | P58: =Assumptions!B7+Assumptions!B8 | Q58: =M58+E58+N58+O58+P58 | R58: 0 | S58: =Q58-R58 | T58: 5 | U58: 14.2 | V58: 11.8 | W58: 1.9 | X58: Yellow
A59: 100 Lanark Rd #8, Brighton, MA 02135 | B59: Brighton | C59: https://www.redfin.com/MA/Brighton/100-Lanark-Rd-02135/unit-8/home/9022520 | D59: 420000 | E59: 500 | F59: 1 | G59: 1 | H59: 560 | I59: No | J59: 0 spaces | K59: =Assumptions!B3 | L59: =D59-K59 | M59: =-PMT(Assumptions!B2/12,Assumptions!B4*12,L59) | N59: =D59*Assumptions!B5/12 | O59: =Assumptions!B6 | P59: =Assumptions!B7+Assumptions!B8 | Q59: =M59+E59+N59+O59+P59 | R59: 0 | S59: =Q59-R59 | T59: 0.8 | U59: 14.8 | V59: 14 | W59: 1.9 | X59: Yellow
A60: 4 Franklin St #202, Boston, MA 02134 | B60: Allston | C60: https://www.redfin.com/MA/Boston/4-Franklin-St-02134/unit-202/home/190592119 | D60: 588000 | E60: 243 | F60: 1 | G60: 1 | H60: 641 | I60: No | J60: 1 space | K60: =Assumptions!B3 | L60: =D60-K60 | M60: =-PMT(Assumptions!B2/12,Assumptions!B4*12,L60) | N60: =D60*Assumptions!B5/12 | O60: =Assumptions!B6 | P60: =Assumptions!B7+Assumptions!B8 | Q60: =M60+E60+N60+O60+P60 | R60: 0 | S60: =Q60-R60 | T60: 1.4 | U60: 9.7 | V60: 9.3 | W60: 1.9 | X60: Yellow
A61: 148 Berkshire St Unit 148-4, Cambridge, MA 02141 | B61: Cambridge | C61: https://www.redfin.com/MA/Cambridge/148-Berkshire-St-02141/unit-148-4/home/200523526 | D61: 535000 | E61: 301 | F61: 1 | G61: 1 | H61: 530 | I61: No | J61: 0 spaces | K61: =Assumptions!B3 | L61: =D61-K61 | M61: =-PMT(Assumptions!B2/12,Assumptions!B4*12,L61) | N61: =D61*Assumptions!B5/12 | O61: =Assumptions!B6 | P61: =Assumptions!B7+Assumptions!B8 | Q61: =M61+E61+N61+O61+P61 | R61: 0 | S61: =Q61-R61 | T61: 3 | U61: 8.8 | V61: 3.8 | W61: 1.9 | X61: Yellow
A62: 111 Jersey St #15, Boston, MA 02215 | B62: Brookline | C62: https://www.redfin.com/MA/Boston/111-Jersey-St-02215/unit-15/home/9317643 | D62: 529000 | E62: 281 | F62: 1 | G62: 1 | H62: 395 | I62: No | J62: 0 spaces | K62: =Assumptions!B3 | L62: =D62-K62 | M62: =-PMT(Assumptions!B2/12,Assumptions!B4*12,L62) | N62: =D62*Assumptions!B5/12 | O62: =Assumptions!B6 | P62: =Assumptions!B7+Assumptions!B8 | Q62: =M62+E62+N62+O62+P62 | R62: 0 | S62: =Q62-R62 | T62: 1.1 | U62: 11.3 | V62: 8.4 | W62: 1.9 | X62: Yellow
A63: 24 Rush St Unit E, Somerville, MA 02145 | B63: Somerville | C63: https://www.redfin.com/MA/Somerville/24-Rush-St-02145/unit-E/home/172903953 | D63: 519000 | E63: 292 | F63: 1 | G63: 1 | H63: 644 | I63: No | J63: 1 space | K63: =Assumptions!B3 | L63: =D63-K63 | M63: =-PMT(Assumptions!B2/12,Assumptions!B4*12,L63) | N63: =D63*Assumptions!B5/12 | O63: =Assumptions!B6 | P63: =Assumptions!B7+Assumptions!B8 | Q63: =M63+E63+N63+O63+P63 | R63: 0 | S63: =Q63-R63 | T63: 3.3 | U63: 9.2 | V63: 7 | W63: 1.9 | X63: Yellow
A64: 388 Washington St #101, Quincy, MA 02169 | B64: Quincy | C64: https://www.redfin.com/MA/Quincy/388-Washington-St-02169/unit-101/home/200568725 | D64: 599000 | E64: 375 | F64: 2 | G64: 2 | H64: 983 | I64: No | J64: 1 space | K64: =Assumptions!B3 | L64: =D64-K64 | M64: =-PMT(Assumptions!B2/12,Assumptions!B4*12,L64) | N64: =D64*Assumptions!B5/12 | O64: =Assumptions!B6 | P64: =Assumptions!B7+Assumptions!B8 | Q64: =M64+E64+N64+O64+P64 | R64: 1170 | S64: =Q64-R64 | T64: 2.7 | U64: 18.8 | V64: 22.9 | W64: 1.85 | X64: Yellow
A65: 20 Whitney Unit U:1, Quincy, MA 02169 | B65: Quincy | C65: https://www.redfin.com/MA/Quincy/20-Whitney-Rd-02169/unit-U-1/home/200248173 | D65: 499000 | E65: 200 | F65: 1 | G65: 1 | H65: 638 | I65: No | J65: 1 space | K65: =Assumptions!B3 | L65: =D65-K65 | M65: =-PMT(Assumptions!B2/12,Assumptions!B4*12,L65) | N65: =D65*Assumptions!B5/12 | O65: =Assumptions!B6 | P65: =Assumptions!B7+Assumptions!B8 | Q65: =M65+E65+N65+O65+P65 | R65: 0 | S65: =Q65-R65 | T65: 1.4 | U65: 17.1 | V65: 21.2 | W65: 1.85 | X65: Yellow
A66: 20 Whitney Rd #101, Quincy, MA 02169 | B66: Quincy | C66: https://www.redfin.com/MA/Quincy/20-Whitney-Rd-02169/unit-101/home/196906729 | D66: 499000 | E66: 0 | F66: 1 | G66: 1 | H66: 575 | I66: No | J66: Unknown | K66: =Assumptions!B3 | L66: =D66-K66 | M66: =-PMT(Assumptions!B2/12,Assumptions!B4*12,L66) | N66: =D66*Assumptions!B5/12 | O66: =Assumptions!B6 | P66: =Assumptions!B7+Assumptions!B8 | Q66: =M66+E66+N66+O66+P66 | R66: 0 | S66: =Q66-R66 | T66: 1.4 | U66: 17.1 | V66: 21.2 | W66: 1.85 | X66: Yellow
A67: 56 Ralph St #3, Watertown, MA 02472 | B67: Watertown | C67: https://www.redfin.com/MA/Watertown/56-Ralph-St-02472/unit-3/home/57314411 | D67: 474900 | E67: 183 | F67: 1 | G67: 1 | H67: 983 | I67: No | J67: 2 spaces | K67: =Assumptions!B3 | L67: =D67-K67 | M67: =-PMT(Assumptions!B2/12,Assumptions!B4*12,L67) | N67: =D67*Assumptions!B5/12 | O67: =Assumptions!B6 | P67: =Assumptions!B7+Assumptions!B8 | Q67: =M67+E67+N67+O67+P67 | R67: 0 | S67: =Q67-R67 | T67: 8.9 | U67: 18.8 | V67: 16.4 | W67: 1.85 | X67: Yellow
A68: 60 Sutherland Rd #4, Brighton, MA 02135 | B68: Brighton | C68: https://www.redfin.com/MA/Brighton/60-Sutherland-Rd-02135/unit-4/home/9026345 | D68: 585000 | E68: 492 | F68: 2 | G68: 1 | H68: 877 | I68: No | J68: 1 space | K68: =Assumptions!B3 | L68: =D68-K68 | M68: =-PMT(Assumptions!B2/12,Assumptions!B4*12,L68) | N68: =D68*Assumptions!B5/12 | O68: =Assumptions!B6 | P68: =Assumptions!B7+Assumptions!B8 | Q68: =M68+E68+N68+O68+P68 | R68: 1300 | S68: =Q68-R68 | T68: 0.8 | U68: 15.3 | V68: 13.6 | W68: 1.85 | X68: Yellow
A69: 1945 Commonwealth Ave #4, Brighton, MA 02135 | B69: Brighton | C69: https://www.redfin.com/MA/Brighton/1945-Commonwealth-Ave-02135/unit-4/home/9242382 | D69: 439000 | E69: 364 | F69: 1 | G69: 1 | H69: 605 | I69: No | J69: 0 spaces | K69: =Assumptions!B3 | L69: =D69-K69 | M69: =-PMT(Assumptions!B2/12,Assumptions!B4*12,L69) | N69: =D69*Assumptions!B5/12 | O69: =Assumptions!B6 | P69: =Assumptions!B7+Assumptions!B8 | Q69: =M69+E69+N69+O69+P69 | R69: 0 | S69: =Q69-R69 | T69: 1.8 | U69: 16.7 | V69: 15 | W69: 1.85 | X69: Yellow
A70: 26 Chiswick Rd #6, Brighton, MA 02135 | B70: Brighton | C70: https://www.redfin.com/MA/Brighton/26-Chiswick-Rd-02135/unit-6/home/9026723 | D70: 368000 | E70: 472 | F70: 1 | G70: 1 | H70: 470 | I70: No | J70: 0 spaces | K70: =Assumptions!B3 | L70: =D70-K70 | M70: =-PMT(Assumptions!B2/12,Assumptions!B4*12,L70) | N70: =D70*Assumptions!B5/12 | O70: =Assumptions!B6 | P70: =Assumptions!B7+Assumptions!B8 | Q70: =M70+E70+N70+O70+P70 | R70: 0 | S70: =Q70-R70 | T70: 1.4 | U70: 15.6 | V70: 13.8 | W70: 1.85 | X70: Yellow
A71: 9 Henry St #9, Belmont, MA 02478 | B71: Belmont | C71: https://www.redfin.com/MA/Belmont/9-Henry-St-02478/unit-9/home/77513972 | D71: 575000 | E71: 200 | F71: 2 | G71: 1 | H71: 724 | I71: No | J71: 2 spaces | K71: =Assumptions!B3 | L71: =D71-K71 | M71: =-PMT(Assumptions!B2/12,Assumptions!B4*12,L71) | N71: =D71*Assumptions!B5/12 | O71: =Assumptions!B6 | P71: =Assumptions!B7+Assumptions!B8 | Q71: =M71+E71+N71+O71+P71 | R71: 1365 | S71: =Q71-R71 | T71: 7.3 | U71: 18.8 | V71: 16.4 | W71: 1.85 | X71: Yellow
A72: 99 Tremont St #105, Brighton, MA 02135 | B72: Watertown | C72: https://www.redfin.com/MA/Brighton/99-Tremont-St-02135/unit-105/home/144873670 | D72: 520000 | E72: 437 | F72: 0 | G72: 1 | H72: 616 | I72: No | J72: 1 space | K72: =Assumptions!B3 | L72: =D72-K72 | M72: =-PMT(Assumptions!B2/12,Assumptions!B4*12,L72) | N72: =D72*Assumptions!B5/12 | O72: =Assumptions!B6 | P72: =Assumptions!B7+Assumptions!B8 | Q72: =M72+E72+N72+O72+P72 | R72: 0 | S72: =Q72-R72 | T72: 6.1 | U72: 14.2 | V72: 14.7 | W72: 1.8 | X72: Yellow
A73: 191 Washington St #317, Boston, MA 02135 | B73: Brighton | C73: https://www.redfin.com/MA/Boston/191-Washington-St-02135/unit-317/home/176134081 | D73: 535000 | E73: 457 | F73: 1 | G73: 1 | H73: 498 | I73: No | J73: 0 spaces | K73: =Assumptions!B3 | L73: =D73-K73 | M73: =-PMT(Assumptions!B2/12,Assumptions!B4*12,L73) | N73: =D73*Assumptions!B5/12 | O73: =Assumptions!B6 | P73: =Assumptions!B7+Assumptions!B8 | Q73: =M73+E73+N73+O73+P73 | R73: 0 | S73: =Q73-R73 | T73: 1.3 | U73: 13.8 | V73: 13.4 | W73: 1.8 | X73: Yellow
A74: 863 Massachusetts Ave #25, Cambridge, MA 02139 | B74: Cambridge | C74: https://www.redfin.com/MA/Cambridge/863-Massachusetts-Ave-02139/unit-25/home/11566175 | D74: 549000 | E74: 433 | F74: 1 | G74: 1 | H74: 450 | I74: No | J74: 0 spaces | K74: =Assumptions!B3 | L74: =D74-K74 | M74: =-PMT(Assumptions!B2/12,Assumptions!B4*12,L74) | N74: =D74*Assumptions!B5/12 | O74: =Assumptions!B6 | P74: =Assumptions!B7+Assumptions!B8 | Q74: =M74+E74+N74+O74+P74 | R74: 0 | S74: =Q74-R74 | T74: 1 | U74: 12.1 | V74: 5.6 | W74: 1.8 | X74: Yellow
A75: 585 Washington St #202, Quincy, MA 02169 | B75: Quincy | C75: https://www.redfin.com/MA/Quincy/585-Washington-St-02169/unit-202/home/200582027 | D75: 600000 | E75: 250 | F75: 2 | G75: 2 | H75: 1203 | I75: No | J75: 1 space | K75: =Assumptions!B3 | L75: =D75-K75 | M75: =-PMT(Assumptions!B2/12,Assumptions!B4*12,L75) | N75: =D75*Assumptions!B5/12 | O75: =Assumptions!B6 | P75: =Assumptions!B7+Assumptions!B8 | Q75: =M75+E75+N75+O75+P75 | R75: 1170 | S75: =Q75-R75 | T75: 3.5 | U75: 19.7 | V75: 23.7 | W75: 1.75 | X75: Yellow
A76: 87 Franklin St #105, Quincy, MA 02169 | B76: Quincy | C76: https://www.redfin.com/MA/Quincy/87-Franklin-St-02169/unit-105/home/9037092 | D76: 544900 | E76: 322 | F76: 2 | G76: 2 | H76: 1218 | I76: No | J76: 2 spaces | K76: =Assumptions!B3 | L76: =D76-K76 | M76: =-PMT(Assumptions!B2/12,Assumptions!B4*12,L76) | N76: =D76*Assumptions!B5/12 | O76: =Assumptions!B6 | P76: =Assumptions!B7+Assumptions!B8 | Q76: =M76+E76+N76+O76+P76 | R76: 1170 | S76: =Q76-R76 | W76: 1.75 | X76: Yellow
A77: 21 Totman St #203, Quincy, MA 02169 | B77: Quincy | C77: https://www.redfin.com/MA/Quincy/21-Totman-St-02169/unit-203/home/199494634 | D77: 474900 | E77: 312 | F77: 1 | G77: 1 | H77: 679 | I77: No | J77: 1 space | K77: =Assumptions!B3 | L77: =D77-K77 | M77: =-PMT(Assumptions!B2/12,Assumptions!B4*12,L77) | N77: =D77*Assumptions!B5/12 | O77: =Assumptions!B6 | P77: =Assumptions!B7+Assumptions!B8 | Q77: =M77+E77+N77+O77+P77 | R77: 0 | S77: =Q77-R77 | T77: 2.3 | U77: 18.3 | V77: 22.4 | W77: 1.75 | X77: Yellow
A78: 15 Colliston Rd #6, Brighton, MA 02135 | B78: Brighton | C78: https://www.redfin.com/MA/Brighton/15-Colliston-Rd-02135/unit-6/home/9004520 | D78: 450000 | E78: 425 | F78: 1 | G78: 1 | H78: 577 | I78: No | J78: 0 spaces | K78: =Assumptions!B3 | L78: =D78-K78 | M78: =-PMT(Assumptions!B2/12,Assumptions!B4*12,L78) | N78: =D78*Assumptions!B5/12 | O78: =Assumptions!B6 | P78: =Assumptions!B7+Assumptions!B8 | Q78: =M78+E78+N78+O78+P78 | R78: 0 | S78: =Q78-R78 | T78: 1.2 | U78: 15.2 | V78: 14.1 | W78: 1.75 | X78: Yellow
A79: 11 Cogswell Ave #15, Cambridge, MA 02140 | B79: Cambridge | C79: https://www.redfin.com/MA/Cambridge/11-Cogswell-Ave-02140/unit-15/home/11583274 | D79: 550000 | E79: 388 | F79: 1 | G79: 1 | H79: 575 | I79: No | J79: 1 space | K79: =Assumptions!B3 | L79: =D79-K79 | M79: =-PMT(Assumptions!B2/12,Assumptions!B4*12,L79) | N79: =D79*Assumptions!B5/12 | O79: =Assumptions!B6 | P79: =Assumptions!B7+Assumptions!B8 | Q79: =M79+E79+N79+O79+P79 | R79: 0 | S79: =Q79-R79 | T79: 1.5 | U79: 15.1 | V79: 11.1 | W79: 1.75 | X79: Yellow
A80: 87 Village Dr #87, Quincy, MA 02169 | B80: Quincy | C80: https://www.redfin.com/MA/Quincy/87-Village-Dr-02169/unit-87/home/200729265 | D80: 539900 | E80: 473 | F80: 2 | G80: 2 | H80: 1117 | I80: No | J80: 1 space | K80: =Assumptions!B3 | L80: =D80-K80 | M80: =-PMT(Assumptions!B2/12,Assumptions!B4*12,L80) | N80: =D80*Assumptions!B5/12 | O80: =Assumptions!B6 | P80: =Assumptions!B7+Assumptions!B8 | Q80: =M80+E80+N80+O80+P80 | R80: 1170 | S80: =Q80-R80 | T80: 3.7 | U80: 19.9 | V80: 23.9 | W80: 1.75 | X80: Yellow
A81: 2 Avon St #6, Cambridge, MA 02138 | B81: Cambridge | C81: https://www.redfin.com/MA/Cambridge/2-Avon-St-02138/unit-6/home/196668755 | D81: 595738 | E81: 384 | F81: 1 | G81: 1 | H81: 520 | I81: No | J81: 0 spaces | K81: =Assumptions!B3 | L81: =D81-K81 | M81: =-PMT(Assumptions!B2/12,Assumptions!B4*12,L81) | N81: =D81*Assumptions!B5/12 | O81: =Assumptions!B6 | P81: =Assumptions!B7+Assumptions!B8 | Q81: =M81+E81+N81+O81+P81 | R81: 0 | S81: =Q81-R81 | T81: 3.4 | U81: 15.1 | V81: 10.2 | W81: 1.75 | X81: Yellow
A82: 21 Totman St #404, Quincy, MA 02169 | B82: Quincy | C82: https://www.redfin.com/MA/Quincy/21-Totman-St-02169/unit-404/home/199967272 | D82: 500000 | E82: 327 | F82: 1 | G82: 1 | H82: 679 | I82: No | J82: 1 space | K82: =Assumptions!B3 | L82: =D82-K82 | M82: =-PMT(Assumptions!B2/12,Assumptions!B4*12,L82) | N82: =D82*Assumptions!B5/12 | O82: =Assumptions!B6 | P82: =Assumptions!B7+Assumptions!B8 | Q82: =M82+E82+N82+O82+P82 | R82: 0 | S82: =Q82-R82 | T82: 2.3 | U82: 18.3 | V82: 22.4 | W82: 1.65 | X82: Red
A83: 28 Westgate Rd #3, Chestnut Hill, MA 02467 | B83: Newton | C83: https://www.redfin.com/MA/Chestnut-Hill/28-Westgate-Rd-02467/unit-3/home/9204984 | D83: 399900 | E83: 424 | F83: 1 | G83: 1 | H83: 575 | I83: No | J83: 1 space | K83: =Assumptions!B3 | L83: =D83-K83 | M83: =-PMT(Assumptions!B2/12,Assumptions!B4*12,L83) | N83: =D83*Assumptions!B5/12 | O83: =Assumptions!B6 | P83: =Assumptions!B7+Assumptions!B8 | Q83: =M83+E83+N83+O83+P83 | R83: 0 | S83: =Q83-R83 | T83: 6.5 | U83: 23.5 | V83: 22 | W83: 1.65 | X83: Red
A84: 1001 Marina Dr #213, Quincy, MA 02171 | B84: Quincy | C84: https://www.redfin.com/MA/Quincy/1001-Marina-Dr-02171/unit-213/home/9026436 | D84: 499900 | E84: 450 | F84: 1 | G84: 1 | H84: 820 | I84: No | J84: 2 spaces | K84: =Assumptions!B3 | L84: =D84-K84 | M84: =-PMT(Assumptions!B2/12,Assumptions!B4*12,L84) | N84: =D84*Assumptions!B5/12 | O84: =Assumptions!B6 | P84: =Assumptions!B7+Assumptions!B8 | Q84: =M84+E84+N84+O84+P84 | R84: 0 | S84: =Q84-R84 | T84: 7.4 | U84: 15.6 | V84: 19.7 | W84: 1.6 | X84: Red
A85: 290 Pleasant St #113, Watertown, MA 02471 | B85: Watertown | C85: https://www.redfin.com/MA/Watertown/290-Pleasant-St-02472/unit-113/home/12404099 | D85: 539900 | E85: 485 | F85: 1 | G85: 1 | H85: 941 | I85: No | J85: 2 spaces | K85: =Assumptions!B3 | L85: =D85-K85 | M85: =-PMT(Assumptions!B2/12,Assumptions!B4*12,L85) | N85: =D85*Assumptions!B5/12 | O85: =Assumptions!B6 | P85: =Assumptions!B7+Assumptions!B8 | Q85: =M85+E85+N85+O85+P85 | R85: 0 | S85: =Q85-R85 | T85: 10.2 | U85: 17.2 | V85: 17.8 | W85: 1.55 | X85: Red
A86: 995 Massachusetts Ave #404, Arlington, MA 02476 | B86: Arlington | C86: https://www.redfin.com/MA/Arlington/995-Massachusetts-Ave-02476/unit-404/home/8418935 | D86: 498000 | E86: 426 | F86: 1 | G86: 1 | H86: 663 | I86: No | J86: 1 space | K86: =Assumptions!B3 | L86: =D86-K86 | M86: =-PMT(Assumptions!B2/12,Assumptions!B4*12,L86) | N86: =D86*Assumptions!B5/12 | O86: =Assumptions!B6 | P86: =Assumptions!B7+Assumptions!B8 | Q86: =M86+E86+N86+O86+P86 | R86: 0 | S86: =Q86-R86 | T86: 6.7 | U86: 18.4 | V86: 17 | W86: 1.55 | X86: Red
