Workbook

Sheet Assumptions
A1: Assumption | B1: Value
A2: Interest Rate | B2: 0.065
A3: Down Payment $ | B3: 20000
A4: Loan Term Years | B4: 30
A5: Property Tax Rate | B5: 0.012
A6: Insurance $/mo | B6: 150
A7: Utilities $/mo | B7: 250
A8: Internet $/mo | B8: 60

Sheet Listings
A1: Address | B1: Town | C1: Listing URL | D1: Listed Date | E1: Price | F1: HOA/mo | G1: Beds | H1: Baths | I1: Sq Ft | J1: In-Unit Laundry | K1: Parking | L1: Down Payment $ | M1: Loan Amount | N1: Monthly Mortgage | O1: Property Tax/mo | P1: Insurance/mo | Q1: Utilities+Internet | R1: Total Monthly Cost | S1: Rent per Roommate | T1: Net Monthly Cost | U1: Drive to MBTA (min) | V1: Drive to Seaport (min) | W1: Drive to Google (min) | X1: Rating Score | Y1: Rating
A2: 5 Spofford Rd #17, Allston, MA 02134 | B2: Allston | C2: https://www.redfin.com/MA/Allston/5-Spofford-Rd-02134/unit-17/home/8995633 | D2: 2026-01-06 | E2: 225000 | F2: 198 | G2: 0 | H2: 1 | I2: 246 | J2: No | K2: 0 spaces | L2: =Assumptions!B3 | M2: =E2-L2 | N2: =-PMT(Assumptions!B2/12,Assumptions!B4*12,M2) | O2: =E2*Assumptions!B5/12 | P2: =Assumptions!B6 | Q2: =Assumptions!B7+Assumptions!B8 | R2: =N2+F2+O2+P2+Q2 | S2: 0 | T2: =R2-S2*MAX(IFERROR(G2-1,0),0) | U2: 1 | V2: 11.5 | W2: 11.2 | X2: 2.55 | Y2: Green
A3: 40-42 Upham St #1, Malden, MA 02148 | B3: Malden | C3: https://www.redfin.com/MA/Malden/40-Upham-St-02148/unit-1/home/187160997 | D3: 2025-12-11 | E3: 480000 | F3: 0 | G3: 2 | H3: 2 | I3: 933 | J3: No | K3: 1 space | L3: =Assumptions!B3 | M3: =E3-L3 | N3: =-PMT(Assumptions!B2/12,Assumptions!B4*12,M3) | O3: =E3*Assumptions!B5/12 | P3: =Assumptions!B6 | Q3: =Assumptions!B7+Assumptions!B8 | R3: =N3+F3+O3+P3+Q3 | S3: 1202 | T3: =R3-S3*MAX(IFERROR(G3-1,0),0) | U3: 2.3 | V3: 14.1 | W3: 11.6 | X3: 2.55 | Y3: Green
A4: 159 Madison St, Malden, MA 02148 | B4: Malden | C4: https://www.redfin.com/MA/Malden/159-Madison-St-02148/home/11391337 | D4: 2026-04-08 | E4: 524900 | F4: 0 | G4: 2 | H4: 1 | I4: 1091 | J4: No | K4: 2 spaces | L4: =Assumptions!B3 | M4: =E4-L4 | N4: =-PMT(Assumptions!B2/12,Assumptions!B4*12,M4) | O4: =E4*Assumptions!B5/12 | P4: =Assumptions!B6 | Q4: =Assumptions!B7+Assumptions!B8 | R4: =N4+F4+O4+P4+Q4 | S4: 1202 | T4: =R4-S4*MAX(IFERROR(G4-1,0),0) | U4: 2.2 | V4: 12.1 | W4: 10.5 | X4: 2.45 | Y4: Green
A5: 111 Devir #204, Malden, MA 02148 | B5: Malden | C5: https://www.redfin.com/MA/Malden/111-Devir-St-02148/unit-204/home/11388868 | D5: 2026-04-01 | E5: 469000 | F5: 343 | G5: 2 | H5: 1.5 | I5: 936 | J5: No | K5: 1 space | L5: =Assumptions!B3 | M5: =E5-L5 | N5: =-PMT(Assumptions!B2/12,Assumptions!B4*12,M5) | O5: =E5*Assumptions!B5/12 | P5: =Assumptions!B6 | Q5: =Assumptions!B7+Assumptions!B8 | R5: =N5+F5+O5+P5+Q5 | S5: 1202 | T5: =R5-S5*MAX(IFERROR(G5-1,0),0) | U5: 3.2 | V5: 11.1 | W5: 9.7 | X5: 2.45 | Y5: Green
A6: 212-A Quincy Shore Dr, Quincy, MA 02171 | B6: Quincy | C6: https://www.redfin.com/MA/Quincy/212-Quincy-Shore-Dr-02171/home/9009303 | E6: 499900 | F6: 0 | G6: 2 | H6: 1 | I6: 864 | J6: No | K6: 0 spaces | L6: =Assumptions!B3 | M6: =E6-L6 | N6: =-PMT(Assumptions!B2/12,Assumptions!B4*12,M6) | O6: =E6*Assumptions!B5/12 | P6: =Assumptions!B6 | Q6: =Assumptions!B7+Assumptions!B8 | R6: =N6+F6+O6+P6+Q6 | S6: 1170 | T6: =R6-S6*MAX(IFERROR(G6-1,0),0) | U6: 5 | V6: 12.6 | W6: 16.7 | X6: 2.4 | Y6: Green
A7: 198 Allston St #3, Brighton, MA 02134 | B7: Brighton | C7: https://www.redfin.com/MA/Brighton/198-Allston-St-02135/unit-3/home/9013031 | E7: 270000 | F7: 295 | G7: 1 | H7: 1 | I7: 318 | J7: No | K7: 0 spaces | L7: =Assumptions!B3 | M7: =E7-L7 | N7: =-PMT(Assumptions!B2/12,Assumptions!B4*12,M7) | O7: =E7*Assumptions!B5/12 | P7: =Assumptions!B6 | Q7: =Assumptions!B7+Assumptions!B8 | R7: =N7+F7+O7+P7+Q7 | S7: 0 | T7: =R7-S7*MAX(IFERROR(G7-1,0),0) | U7: 0.8 | V7: 12.4 | W7: 12 | X7: 2.4 | Y7: Green
A8: 0 Gordon Rd, Medford, MA 02155 | B8: Medford | C8: https://www.redfin.com/MA/Medford/0-Gordon-Rd-02155/home/187063221 | E8: 369000 | F8: 0 | J8: No | K8: Unknown | L8: =Assumptions!B3 | M8: =E8-L8 | N8: =-PMT(Assumptions!B2/12,Assumptions!B4*12,M8) | O8: =E8*Assumptions!B5/12 | P8: =Assumptions!B6 | Q8: =Assumptions!B7+Assumptions!B8 | R8: =N8+F8+O8+P8+Q8 | S8: 0 | T8: =R8-S8*MAX(IFERROR(G8-1,0),0) | U8: 5 | V8: 12.2 | W8: 12.4 | X8: 2.35 | Y8: Green
A9: 27 Sixth Ave, Quincy, MA 02169 | B9: Quincy | C9: https://www.redfin.com/MA/Quincy/27-6th-Ave-02169/home/8946597 | E9: 499000 | F9: 0 | G9: 3 | H9: 1 | I9: 1134 | J9: No | K9: 0 spaces | L9: =Assumptions!B3 | M9: =E9-L9 | N9: =-PMT(Assumptions!B2/12,Assumptions!B4*12,M9) | O9: =E9*Assumptions!B5/12 | P9: =Assumptions!B6 | Q9: =Assumptions!B7+Assumptions!B8 | R9: =N9+F9+O9+P9+Q9 | S9: 1170 | T9: =R9-S9*MAX(IFERROR(G9-1,0),0) | U9: 4 | V9: 20.1 | W9: 24.2 | X9: 2.35 | Y9: Green
A10: 1 Glenwood St #5, Malden, MA 02148 | B10: Malden | C10: https://www.redfin.com/MA/Malden/1-Glenwood-St-02148/unit-5/home/11429024 | D10: 2026-03-25 | E10: 499000 | F10: 327 | G10: 3 | H10: 2 | I10: 1098 | J10: No | K10: 0 spaces | L10: =Assumptions!B3 | M10: =E10-L10 | N10: =-PMT(Assumptions!B2/12,Assumptions!B4*12,M10) | O10: =E10*Assumptions!B5/12 | P10: =Assumptions!B6 | Q10: =Assumptions!B7+Assumptions!B8 | R10: =N10+F10+O10+P10+Q10 | S10: 1202 | T10: =R10-S10*MAX(IFERROR(G10-1,0),0) | U10: 0.3 | V10: 14.2 | W10: 12.7 | X10: 2.35 | Y10: Green
A11: 217-221 Highland Ave #2, Malden, MA 02148 | B11: Malden | C11: https://www.redfin.com/MA/Malden/217-Highland-Ave-02148/unit-2/home/137151214 | D11: 2025-06-17 | E11: 499800 | F11: 390 | G11: 3 | H11: 1.5 | I11: 1483 | J11: No | K11: 2 spaces | L11: =Assumptions!B3 | M11: =E11-L11 | N11: =-PMT(Assumptions!B2/12,Assumptions!B4*12,M11) | O11: =E11*Assumptions!B5/12 | P11: =Assumptions!B6 | Q11: =Assumptions!B7+Assumptions!B8 | R11: =N11+F11+O11+P11+Q11 | S11: 1202 | T11: =R11-S11*MAX(IFERROR(G11-1,0),0) | U11: 2 | V11: 11.2 | W11: 9.8 | X11: 2.35 | Y11: Green
A12: 18 Allerton St, Quincy, MA 02169 | B12: Quincy | C12: https://www.redfin.com/MA/Quincy/18-Allerton-St-02169/home/110011603 | E12: 200000 | F12: 0 | J12: No | K12: Unknown | L12: =Assumptions!B3 | M12: =E12-L12 | N12: =-PMT(Assumptions!B2/12,Assumptions!B4*12,M12) | O12: =E12*Assumptions!B5/12 | P12: =Assumptions!B6 | Q12: =Assumptions!B7+Assumptions!B8 | R12: =N12+F12+O12+P12+Q12 | S12: 0 | T12: =R12-S12*MAX(IFERROR(G12-1,0),0) | U12: 8.4 | V12: 23.3 | W12: 27.4 | X12: 2.3 | Y12: Green
A13: 10 Scottfield Rd #2, Allston, MA 02134 | B13: Allston | C13: https://www.redfin.com/MA/Allston/10-Scottfield-Rd-02134/unit-2/home/9000250 | E13: 474900 | F13: 408 | G13: 2 | H13: 1 | I13: 746 | J13: No | K13: 0 spaces | L13: =Assumptions!B3 | M13: =E13-L13 | N13: =-PMT(Assumptions!B2/12,Assumptions!B4*12,M13) | O13: =E13*Assumptions!B5/12 | P13: =Assumptions!B6 | Q13: =Assumptions!B7+Assumptions!B8 | R13: =N13+F13+O13+P13+Q13 | S13: 1235 | T13: =R13-S13*MAX(IFERROR(G13-1,0),0) | U13: 2 | V13: 12.2 | W13: 11.8 | X13: 2.3 | Y13: Green
A14: 199 Prospect St Unit A1, Cambridge, MA 02139 | B14: Cambridge | C14: https://www.redfin.com/MA/Cambridge/199-Prospect-St-02139/unit-A1/home/110093910 | E14: 399999 | F14: 183 | G14: 0 | H14: 1 | I14: 389 | J14: No | K14: 0 spaces | L14: =Assumptions!B3 | M14: =E14-L14 | N14: =-PMT(Assumptions!B2/12,Assumptions!B4*12,M14) | O14: =E14*Assumptions!B5/12 | P14: =Assumptions!B6 | Q14: =Assumptions!B7+Assumptions!B8 | R14: =N14+F14+O14+P14+Q14 | S14: 0 | T14: =R14-S14*MAX(IFERROR(G14-1,0),0) | U14: 2.4 | V14: 11.2 | W14: 4.1 | X14: 2.3 | Y14: Yellow
A15: 239 Kelton St #11, Allston, MA 02134 | B15: Allston | C15: https://www.redfin.com/MA/Allston/239-Kelton-St-02134/unit-11/home/9000947 | E15: 465000 | F15: 400 | G15: 2 | H15: 1 | I15: 690 | J15: No | K15: 1 space | L15: =Assumptions!B3 | M15: =E15-L15 | N15: =-PMT(Assumptions!B2/12,Assumptions!B4*12,M15) | O15: =E15*Assumptions!B5/12 | P15: =Assumptions!B6 | Q15: =Assumptions!B7+Assumptions!B8 | R15: =N15+F15+O15+P15+Q15 | S15: 1235 | T15: =R15-S15*MAX(IFERROR(G15-1,0),0) | U15: 2.6 | V15: 12.9 | W15: 12.5 | X15: 2.3 | Y15: Green
A16: 84 Grant St #7, Somerville, MA 02145 | B16: Somerville | C16: https://www.redfin.com/MA/Somerville/84-Grant-St-02145/unit-7/home/11650236 | E16: 469000 | F16: 439 | G16: 2 | H16: 1 | I16: 835 | J16: No | K16: 1 space | L16: =Assumptions!B3 | M16: =E16-L16 | N16: =-PMT(Assumptions!B2/12,Assumptions!B4*12,M16) | O16: =E16*Assumptions!B5/12 | P16: =Assumptions!B6 | Q16: =Assumptions!B7+Assumptions!B8 | R16: =N16+F16+O16+P16+Q16 | S16: 1495 | T16: =R16-S16*MAX(IFERROR(G16-1,0),0) | U16: 3.2 | V16: 8.2 | W16: 6.8 | X16: 2.3 | Y16: Green
A17: 186 Lexington St #8, Watertown, MA 02472 | B17: Watertown | C17: https://www.redfin.com/MA/Watertown/186-Lexington-St-02472/unit-8/home/11690422 | E17: 394900 | F17: 350 | G17: 2 | H17: 1 | I17: 600 | J17: No | K17: 1 space | L17: =Assumptions!B3 | M17: =E17-L17 | N17: =-PMT(Assumptions!B2/12,Assumptions!B4*12,M17) | O17: =E17*Assumptions!B5/12 | P17: =Assumptions!B6 | Q17: =Assumptions!B7+Assumptions!B8 | R17: =N17+F17+O17+P17+Q17 | S17: 1365 | T17: =R17-S17*MAX(IFERROR(G17-1,0),0) | U17: 12.1 | V17: 18.5 | W17: 17.2 | X17: 2.25 | Y17: Yellow
A18: 194 Lexington St #1, Watertown, MA 02472 | B18: Watertown | C18: https://www.redfin.com/MA/Watertown/194-Lexington-St-02472/unit-1/home/11690433 | E18: 375000 | F18: 350 | G18: 2 | H18: 1 | I18: 600 | J18: No | K18: 1 space | L18: =Assumptions!B3 | M18: =E18-L18 | N18: =-PMT(Assumptions!B2/12,Assumptions!B4*12,M18) | O18: =E18*Assumptions!B5/12 | P18: =Assumptions!B6 | Q18: =Assumptions!B7+Assumptions!B8 | R18: =N18+F18+O18+P18+Q18 | S18: 1365 | T18: =R18-S18*MAX(IFERROR(G18-1,0),0) | U18: 12.4 | V18: 18.9 | W18: 17 | X18: 2.25 | Y18: Yellow
A19: 133 Warren St #3, Watertown, MA 02472 | B19: Watertown | C19: https://www.redfin.com/MA/Watertown/133-Warren-St-02472/unit-3/home/11690534 | E19: 375000 | F19: 350 | G19: 2 | H19: 1 | I19: 600 | J19: No | K19: 2 spaces | L19: =Assumptions!B3 | M19: =E19-L19 | N19: =-PMT(Assumptions!B2/12,Assumptions!B4*12,M19) | O19: =E19*Assumptions!B5/12 | P19: =Assumptions!B6 | Q19: =Assumptions!B7+Assumptions!B8 | R19: =N19+F19+O19+P19+Q19 | S19: 1365 | T19: =R19-S19*MAX(IFERROR(G19-1,0),0) | U19: 12.3 | V19: 18.7 | W19: 17.3 | X19: 2.25 | Y19: Yellow
A20: 12 Gaston St, Medford, MA 02155 | B20: Medford | C20: https://www.redfin.com/MA/Medford/12-Gaston-St-02155/home/11778344 | E20: 375000 | F20: 0 | J20: No | K20: Unknown | L20: =Assumptions!B3 | M20: =E20-L20 | N20: =-PMT(Assumptions!B2/12,Assumptions!B4*12,M20) | O20: =E20*Assumptions!B5/12 | P20: =Assumptions!B6 | Q20: =Assumptions!B7+Assumptions!B8 | R20: =N20+F20+O20+P20+Q20 | S20: 0 | T20: =R20-S20*MAX(IFERROR(G20-1,0),0) | U20: 5.4 | V20: 12.3 | W20: 12.5 | X20: 2.25 | Y20: Yellow
A21: 77 Forest St, Watertown, MA 02472 | B21: Watertown | C21: https://www.redfin.com/MA/Watertown/77-Forest-St-02472/home/195635313 | E21: 299500 | F21: 0 | G21: 1 | H21: 1.5 | I21: 1040 | J21: No | K21: 0 spaces | L21: =Assumptions!B3 | M21: =E21-L21 | N21: =-PMT(Assumptions!B2/12,Assumptions!B4*12,M21) | O21: =E21*Assumptions!B5/12 | P21: =Assumptions!B6 | Q21: =Assumptions!B7+Assumptions!B8 | R21: =N21+F21+O21+P21+Q21 | S21: 0 | T21: =R21-S21*MAX(IFERROR(G21-1,0),0) | U21: 10.9 | V21: 17.3 | W21: 17.1 | X21: 2.25 | Y21: Yellow
A22: 69A Strathmore St Unit 69A, Boston, MA 02135 | B22: Brighton | C22: https://www.redfin.com/MA/Boston/69-Strathmore-Rd-02135/unit-69A/home/200893159 | E22: 489000 | F22: 373 | G22: 2 | H22: 1 | I22: 638 | J22: No | K22: 0 spaces | L22: =Assumptions!B3 | M22: =E22-L22 | N22: =-PMT(Assumptions!B2/12,Assumptions!B4*12,M22) | O22: =E22*Assumptions!B5/12 | P22: =Assumptions!B6 | Q22: =Assumptions!B7+Assumptions!B8 | R22: =N22+F22+O22+P22+Q22 | S22: 1300 | T22: =R22-S22*MAX(IFERROR(G22-1,0),0) | U22: 0.6 | V22: 16 | W22: 13.4 | X22: 2.25 | Y22: Yellow
A23: 185 Chestnut Hill Ave #3, Brighton, MA 02135 | B23: Brighton | C23: https://www.redfin.com/MA/Brighton/185-Chestnut-Hill-Ave-02135/unit-3/home/9036757 | E23: 395000 | F23: 442 | G23: 2 | H23: 1 | I23: 623 | J23: No | K23: 0 spaces | L23: =Assumptions!B3 | M23: =E23-L23 | N23: =-PMT(Assumptions!B2/12,Assumptions!B4*12,M23) | O23: =E23*Assumptions!B5/12 | P23: =Assumptions!B6 | Q23: =Assumptions!B7+Assumptions!B8 | R23: =N23+F23+O23+P23+Q23 | S23: 1300 | T23: =R23-S23*MAX(IFERROR(G23-1,0),0) | U23: 2.7 | V23: 15.7 | W23: 15.4 | X23: 2.25 | Y23: Yellow
A24: 82 Medford St #2, Malden, MA 02148 | B24: Malden | C24: https://www.redfin.com/MA/Malden/82-Medford-St-02148/unit-2/home/11431345 | D24: 2026-03-04 | E24: 549990 | F24: 207 | G24: 3 | H24: 1.5 | I24: 1319 | J24: No | K24: 3 spaces | L24: =Assumptions!B3 | M24: =E24-L24 | N24: =-PMT(Assumptions!B2/12,Assumptions!B4*12,M24) | O24: =E24*Assumptions!B5/12 | P24: =Assumptions!B6 | Q24: =Assumptions!B7+Assumptions!B8 | R24: =N24+F24+O24+P24+Q24 | S24: 1202 | T24: =R24-S24*MAX(IFERROR(G24-1,0),0) | U24: 2.3 | V24: 12 | W24: 10.2 | X24: 2.25 | Y24: Yellow
A25: 45 Gordon St #4, Allston, MA 02134 | B25: Allston | C25: https://www.redfin.com/MA/Allston/45-Gordon-St-02134/unit-4/home/8999903 | E25: 489000 | F25: 350 | G25: 2 | H25: 1 | I25: 675 | J25: No | K25: 0 spaces | L25: =Assumptions!B3 | M25: =E25-L25 | N25: =-PMT(Assumptions!B2/12,Assumptions!B4*12,M25) | O25: =E25*Assumptions!B5/12 | P25: =Assumptions!B6 | Q25: =Assumptions!B7+Assumptions!B8 | R25: =N25+F25+O25+P25+Q25 | S25: 1235 | T25: =R25-S25*MAX(IFERROR(G25-1,0),0) | U25: 3 | V25: 11.3 | W25: 10.9 | X25: 2.2 | Y25: Yellow
A26: 12-14 Shannon St #3, Brighton, MA 02135 | B26: Brighton | C26: https://www.redfin.com/MA/Brighton/12-14-Shannon-St-02135/unit-3/home/11838033 | E26: 599000 | F26: 280 | G26: 3 | H26: 1 | I26: 908 | J26: No | K26: 3 spaces | L26: =Assumptions!B3 | M26: =E26-L26 | N26: =-PMT(Assumptions!B2/12,Assumptions!B4*12,M26) | O26: =E26*Assumptions!B5/12 | P26: =Assumptions!B6 | Q26: =Assumptions!B7+Assumptions!B8 | R26: =N26+F26+O26+P26+Q26 | S26: 1300 | T26: =R26-S26*MAX(IFERROR(G26-1,0),0) | U26: 1.9 | V26: 13.6 | W26: 13.2 | X26: 2.2 | Y26: Yellow
A27: 102 Grant Unit B, Somerville, MA 02145 | B27: Somerville | C27: https://www.redfin.com/MA/Somerville/102-Grant-St-02145/unit-B/home/196668060 | E27: 599000 | F27: 200 | G27: 2 | H27: 1 | I27: 1162 | J27: No | K27: 0 spaces | L27: =Assumptions!B3 | M27: =E27-L27 | N27: =-PMT(Assumptions!B2/12,Assumptions!B4*12,M27) | O27: =E27*Assumptions!B5/12 | P27: =Assumptions!B6 | Q27: =Assumptions!B7+Assumptions!B8 | R27: =N27+F27+O27+P27+Q27 | S27: 1495 | T27: =R27-S27*MAX(IFERROR(G27-1,0),0) | U27: 3.7 | V27: 7.9 | W27: 6.5 | X27: 2.2 | Y27: Yellow
A28: 195 Thomas Burgin Pkwy #301, Quincy, MA 02169 | B28: Quincy | C28: https://www.redfin.com/MA/Quincy/195-Thomas-Burgin-Pkwy-02169/unit-301/home/8931809 | E28: 250000 | F28: 393 | G28: 1 | H28: 1 | I28: 447 | J28: No | K28: 0 spaces | L28: =Assumptions!B3 | M28: =E28-L28 | N28: =-PMT(Assumptions!B2/12,Assumptions!B4*12,M28) | O28: =E28*Assumptions!B5/12 | P28: =Assumptions!B6 | Q28: =Assumptions!B7+Assumptions!B8 | R28: =N28+F28+O28+P28+Q28 | S28: 0 | T28: =R28-S28*MAX(IFERROR(G28-1,0),0) | U28: 2.2 | V28: 17.6 | W28: 21.7 | X28: 2.15 | Y28: Yellow
A29: 10 Naviens Ln #1, Waltham, MA 02453 | B29: Waltham | C29: https://www.redfin.com/MA/Waltham/10-Naviens-Ln-02453/unit-1/home/76478882 | E29: 499900 | F29: 134 | G29: 2 | H29: 1 | I29: 1008 | J29: No | K29: 2 spaces | L29: =Assumptions!B3 | M29: =E29-L29 | N29: =-PMT(Assumptions!B2/12,Assumptions!B4*12,M29) | O29: =E29*Assumptions!B5/12 | P29: =Assumptions!B6 | Q29: =Assumptions!B7+Assumptions!B8 | R29: =N29+F29+O29+P29+Q29 | S29: 1235 | T29: =R29-S29*MAX(IFERROR(G29-1,0),0) | U29: 10.9 | V29: 19.2 | W29: 19.7 | X29: 2.15 | Y29: Yellow
A30: 66 Bryon Rd #2, Chestnut Hill, MA 02467 | B30: Newton | C30: https://www.redfin.com/MA/Chestnut-Hill/66-Bryon-Rd-02467/unit-2/home/9204203 | E30: 385000 | F30: 422 | G30: 2 | H30: 1 | I30: 780 | J30: No | K30: 2 spaces | L30: =Assumptions!B3 | M30: =E30-L30 | N30: =-PMT(Assumptions!B2/12,Assumptions!B4*12,M30) | O30: =E30*Assumptions!B5/12 | P30: =Assumptions!B6 | Q30: =Assumptions!B7+Assumptions!B8 | R30: =N30+F30+O30+P30+Q30 | S30: 1430 | T30: =R30-S30*MAX(IFERROR(G30-1,0),0) | U30: 5.9 | V30: 22.9 | W30: 21.4 | X30: 2.15 | Y30: Yellow
A31: 5 Braemore Rd #10, Brighton, MA 02135 | B31: Brighton | C31: https://www.redfin.com/MA/Brighton/5-Braemore-Rd-02135/unit-10/home/9308549 | E31: 315000 | F31: 352 | G31: 1 | H31: 1 | I31: 385 | J31: No | K31: 0 spaces | L31: =Assumptions!B3 | M31: =E31-L31 | N31: =-PMT(Assumptions!B2/12,Assumptions!B4*12,M31) | O31: =E31*Assumptions!B5/12 | P31: =Assumptions!B6 | Q31: =Assumptions!B7+Assumptions!B8 | R31: =N31+F31+O31+P31+Q31 | S31: 0 | T31: =R31-S31*MAX(IFERROR(G31-1,0),0) | U31: 1.7 | V31: 15.9 | W31: 14.1 | X31: 2.15 | Y31: Yellow
A32: 64 Bryon Rd #1, Chestnut Hill, MA 02467 | B32: Newton | C32: https://www.redfin.com/MA/Chestnut-Hill/64-Bryon-Rd-02467/unit-1/home/9204182 | E32: 399000 | F32: 422 | G32: 2 | H32: 1 | I32: 780 | J32: No | K32: 2 spaces | L32: =Assumptions!B3 | M32: =E32-L32 | N32: =-PMT(Assumptions!B2/12,Assumptions!B4*12,M32) | O32: =E32*Assumptions!B5/12 | P32: =Assumptions!B6 | Q32: =Assumptions!B7+Assumptions!B8 | R32: =N32+F32+O32+P32+Q32 | S32: 1430 | T32: =R32-S32*MAX(IFERROR(G32-1,0),0) | U32: 5.8 | V32: 22.9 | W32: 21.4 | X32: 2.15 | Y32: Yellow
A33: 1641 Commonwealth Ave #16, Brighton, MA 02135 | B33: Brighton | C33: https://www.redfin.com/MA/Brighton/1641-Commonwealth-Ave-02135/unit-16/home/9002891 | D33: 2026-04-08 | E33: 349000 | F33: 399 | G33: 1 | H33: 1 | I33: 407 | J33: No | K33: 0 spaces | L33: =Assumptions!B3 | M33: =E33-L33 | N33: =-PMT(Assumptions!B2/12,Assumptions!B4*12,M33) | O33: =E33*Assumptions!B5/12 | P33: =Assumptions!B6 | Q33: =Assumptions!B7+Assumptions!B8 | R33: =N33+F33+O33+P33+Q33 | S33: 0 | T33: =R33-S33*MAX(IFERROR(G33-1,0),0) | U33: 0.4 | V33: 15 | W33: 14.6 | X33: 2.15 | Y33: Yellow
A34: 1568 Commonwealth Ave #12, Brighton, MA 02135 | B34: Brighton | C34: https://www.redfin.com/MA/Brighton/1568-Commonwealth-Ave-02135/unit-12/home/9017105 | D34: 2026-04-09 | E34: 314900 | F34: 369 | G34: 1 | H34: 1 | I34: 306 | J34: No | K34: 0 spaces | L34: =Assumptions!B3 | M34: =E34-L34 | N34: =-PMT(Assumptions!B2/12,Assumptions!B4*12,M34) | O34: =E34*Assumptions!B5/12 | P34: =Assumptions!B6 | Q34: =Assumptions!B7+Assumptions!B8 | R34: =N34+F34+O34+P34+Q34 | S34: 0 | T34: =R34-S34*MAX(IFERROR(G34-1,0),0) | U34: 1.2 | V34: 13.7 | W34: 13.3 | X34: 2.15 | Y34: Yellow
A35: 10 Scottfield Rd #34, Allston, MA 02134 | B35: Allston | C35: https://www.redfin.com/MA/Allston/10-Scottfield-Rd-02134/unit-34/home/9000321 | D35: 2026-04-08 | E35: 499000 | F35: 408 | G35: 2 | H35: 1 | I35: 746 | J35: No | K35: 1 space | L35: =Assumptions!B3 | M35: =E35-L35 | N35: =-PMT(Assumptions!B2/12,Assumptions!B4*12,M35) | O35: =E35*Assumptions!B5/12 | P35: =Assumptions!B6 | Q35: =Assumptions!B7+Assumptions!B8 | R35: =N35+F35+O35+P35+Q35 | S35: 1235 | T35: =R35-S35*MAX(IFERROR(G35-1,0),0) | U35: 2 | V35: 12.2 | W35: 11.8 | X35: 2.15 | Y35: Yellow
A36: 239 Kelton St #41, Allston, MA 02134 | B36: Allston | C36: https://www.redfin.com/MA/Allston/239-Kelton-St-02134/unit-41/home/9001010 | E36: 475000 | F36: 497 | G36: 2 | H36: 1 | I36: 690 | J36: No | K36: 0 spaces | L36: =Assumptions!B3 | M36: =E36-L36 | N36: =-PMT(Assumptions!B2/12,Assumptions!B4*12,M36) | O36: =E36*Assumptions!B5/12 | P36: =Assumptions!B6 | Q36: =Assumptions!B7+Assumptions!B8 | R36: =N36+F36+O36+P36+Q36 | S36: 1235 | T36: =R36-S36*MAX(IFERROR(G36-1,0),0) | U36: 2.6 | V36: 12.9 | W36: 12.5 | X36: 2.1 | Y36: Yellow
A37: 34 Channing St #2, Newton, MA 02458 | B37: Newton | C37: https://www.redfin.com/MA/Newton/34-Channing-St-02458/unit-2/home/196688205 | E37: 598000 | F37: 237 | G37: 3 | H37: 1 | I37: 1387 | J37: No | K37: 1 space | L37: =Assumptions!B3 | M37: =E37-L37 | N37: =-PMT(Assumptions!B2/12,Assumptions!B4*12,M37) | O37: =E37*Assumptions!B5/12 | P37: =Assumptions!B6 | Q37: =Assumptions!B7+Assumptions!B8 | R37: =N37+F37+O37+P37+Q37 | S37: 1430 | T37: =R37-S37*MAX(IFERROR(G37-1,0),0) | U37: 8 | V37: 14.3 | W37: 14.9 | X37: 2.1 | Y37: Yellow
A38: 57 Brighton Ave #6, Allston, MA 02134 | B38: Allston | C38: https://www.redfin.com/MA/Allston/57-Brighton-Ave-02134/unit-6/home/8991939 | E38: 429000 | F38: 0 | G38: 1 | H38: 1 | I38: 620 | J38: No | K38: Unknown | L38: =Assumptions!B3 | M38: =E38-L38 | N38: =-PMT(Assumptions!B2/12,Assumptions!B4*12,M38) | O38: =E38*Assumptions!B5/12 | P38: =Assumptions!B6 | Q38: =Assumptions!B7+Assumptions!B8 | R38: =N38+F38+O38+P38+Q38 | S38: 0 | T38: =R38-S38*MAX(IFERROR(G38-1,0),0) | U38: 2.2 | V38: 10.6 | W38: 10.3 | X38: 2.1 | Y38: Yellow
A39: 297 Main St #3, Medford, MA 02155 | B39: Medford | C39: https://www.redfin.com/MA/Medford/297-Main-St-02155/unit-3/home/11796231 | E39: 368000 | F39: 324 | G39: 1 | H39: 1 | I39: 596 | J39: No | K39: 1 space | L39: =Assumptions!B3 | M39: =E39-L39 | N39: =-PMT(Assumptions!B2/12,Assumptions!B4*12,M39) | O39: =E39*Assumptions!B5/12 | P39: =Assumptions!B6 | Q39: =Assumptions!B7+Assumptions!B8 | R39: =N39+F39+O39+P39+Q39 | S39: 0 | T39: =R39-S39*MAX(IFERROR(G39-1,0),0) | U39: 1.8 | V39: 11 | W39: 9.6 | X39: 2.1 | Y39: Yellow
A40: , Boston, MA 02135 | B40: Brighton | C40: https://www.redfin.com/MA/Brighton/Undisclosed-address-02135/home/9013888 | E40: 469000 | F40: 0 | G40: 1 | H40: 1 | I40: 560 | J40: No | K40: Unknown | L40: =Assumptions!B3 | M40: =E40-L40 | N40: =-PMT(Assumptions!B2/12,Assumptions!B4*12,M40) | O40: =E40*Assumptions!B5/12 | P40: =Assumptions!B6 | Q40: =Assumptions!B7+Assumptions!B8 | R40: =N40+F40+O40+P40+Q40 | S40: 0 | T40: =R40-S40*MAX(IFERROR(G40-1,0),0) | U40: 0.7 | V40: 12.8 | W40: 12.5 | X40: 2.1 | Y40: Yellow
A41: 32 Sidlaw #6, Brighton, MA 02135 | B41: Brighton | C41: https://www.redfin.com/MA/Brighton/32-Sidlaw-Rd-02135/unit-6/home/9006968 | E41: 335000 | F41: 332 | G41: 0 | H41: 1 | I41: 346 | J41: No | K41: 0 spaces | L41: =Assumptions!B3 | M41: =E41-L41 | N41: =-PMT(Assumptions!B2/12,Assumptions!B4*12,M41) | O41: =E41*Assumptions!B5/12 | P41: =Assumptions!B6 | Q41: =Assumptions!B7+Assumptions!B8 | R41: =N41+F41+O41+P41+Q41 | S41: 0 | T41: =R41-S41*MAX(IFERROR(G41-1,0),0) | U41: 1.2 | V41: 16.1 | W41: 14.5 | X41: 2.05 | Y41: Yellow
A42: 115 W Squantum St #203, Quincy, MA 02171 | B42: Quincy | C42: https://www.redfin.com/MA/Quincy/115-W-Squantum-St-02171/unit-203/home/11722276 | E42: 390000 | F42: 370 | G42: 1 | H42: 1 | I42: 765 | J42: No | K42: 1 space | L42: =Assumptions!B3 | M42: =E42-L42 | N42: =-PMT(Assumptions!B2/12,Assumptions!B4*12,M42) | O42: =E42*Assumptions!B5/12 | P42: =Assumptions!B6 | Q42: =Assumptions!B7+Assumptions!B8 | R42: =N42+F42+O42+P42+Q42 | S42: 0 | T42: =R42-S42*MAX(IFERROR(G42-1,0),0) | U42: 2.6 | V42: 13.4 | W42: 17.4 | X42: 2.05 | Y42: Yellow
A43: 17 Radcliffe Rd #10, Allston, MA 02134 | B43: Allston | C43: https://www.redfin.com/MA/Allston/17-Radcliffe-Rd-02134/unit-10/home/11833006 | D43: 2026-04-01 | E43: 415000 | F43: 399 | G43: 1 | H43: 1 | I43: 668 | J43: No | K43: 0 spaces | L43: =Assumptions!B3 | M43: =E43-L43 | N43: =-PMT(Assumptions!B2/12,Assumptions!B4*12,M43) | O43: =E43*Assumptions!B5/12 | P43: =Assumptions!B6 | Q43: =Assumptions!B7+Assumptions!B8 | R43: =N43+F43+O43+P43+Q43 | S43: 0 | T43: =R43-S43*MAX(IFERROR(G43-1,0),0) | U43: 1.9 | V43: 11.6 | W43: 11.2 | X43: 2.05 | Y43: Yellow
A44: 95 2nd St #3, Cambridge, MA 02141 | B44: Cambridge | C44: https://www.redfin.com/MA/Cambridge/95-Second-St-02141/unit-3/home/22200369 | D44: 2026-04-02 | E44: 560000 | F44: 500 | G44: 2 | H44: 1 | I44: 507 | J44: No | K44: 0 spaces | L44: =Assumptions!B3 | M44: =E44-L44 | N44: =-PMT(Assumptions!B2/12,Assumptions!B4*12,M44) | O44: =E44*Assumptions!B5/12 | P44: =Assumptions!B6 | Q44: =Assumptions!B7+Assumptions!B8 | R44: =N44+F44+O44+P44+Q44 | S44: 1625 | T44: =R44-S44*MAX(IFERROR(G44-1,0),0) | U44: 1.1 | V44: 7.5 | W44: 2.1 | X44: 2.05 | Y44: Yellow
A45: 32 Newman Rd #1, Malden, MA 02148 | B45: Malden | C45: https://www.redfin.com/MA/Malden/32-Newman-Rd-02148/unit-1/home/11391853 | D45: 2026-04-09 | E45: 325000 | F45: 440 | G45: 1 | H45: 1 | I45: 441 | J45: No | K45: 1 space | L45: =Assumptions!B3 | M45: =E45-L45 | N45: =-PMT(Assumptions!B2/12,Assumptions!B4*12,M45) | O45: =E45*Assumptions!B5/12 | P45: =Assumptions!B6 | Q45: =Assumptions!B7+Assumptions!B8 | R45: =N45+F45+O45+P45+Q45 | S45: 0 | T45: =R45-S45*MAX(IFERROR(G45-1,0),0) | U45: 3.1 | V45: 12.8 | W45: 10.7 | X45: 2.05 | Y45: Yellow
A46: 80 Main St #9, Malden, MA 02148 | B46: Malden | C46: https://www.redfin.com/MA/Malden/80-Main-St-02148/unit-9/home/11391543 | D46: 2026-02-12 | E46: 355900 | F46: 426 | G46: 1 | H46: 1 | I46: 605 | J46: No | K46: 1 space | L46: =Assumptions!B3 | M46: =E46-L46 | N46: =-PMT(Assumptions!B2/12,Assumptions!B4*12,M46) | O46: =E46*Assumptions!B5/12 | P46: =Assumptions!B6 | Q46: =Assumptions!B7+Assumptions!B8 | R46: =N46+F46+O46+P46+Q46 | S46: 0 | T46: =R46-S46*MAX(IFERROR(G46-1,0),0) | U46: 2.3 | V46: 12.4 | W46: 10 | X46: 2.05 | Y46: Yellow
A47: 80 Main St #4, Malden, MA 02148 | B47: Malden | C47: https://www.redfin.com/MA/Malden/80-Main-St-02148/unit-4/home/11391525 | D47: 2026-01-20 | E47: 335000 | F47: 430 | G47: 1 | H47: 1 | I47: 578 | J47: No | K47: 1 space | L47: =Assumptions!B3 | M47: =E47-L47 | N47: =-PMT(Assumptions!B2/12,Assumptions!B4*12,M47) | O47: =E47*Assumptions!B5/12 | P47: =Assumptions!B6 | Q47: =Assumptions!B7+Assumptions!B8 | R47: =N47+F47+O47+P47+Q47 | S47: 0 | T47: =R47-S47*MAX(IFERROR(G47-1,0),0) | U47: 2.3 | V47: 12.4 | W47: 10 | X47: 2.05 | Y47: Yellow
A48: 1691 Commonwealth Ave #31, Brighton, MA 02135 | B48: Brighton | C48: https://www.redfin.com/MA/Brighton/1691-Commonwealth-Ave-02135/unit-31/home/9020583 | E48: 414900 | F48: 360 | G48: 1 | H48: 1 | I48: 520 | J48: No | K48: 0 spaces | L48: =Assumptions!B3 | M48: =E48-L48 | N48: =-PMT(Assumptions!B2/12,Assumptions!B4*12,M48) | O48: =E48*Assumptions!B5/12 | P48: =Assumptions!B6 | Q48: =Assumptions!B7+Assumptions!B8 | R48: =N48+F48+O48+P48+Q48 | S48: 0 | T48: =R48-S48*MAX(IFERROR(G48-1,0),0) | U48: 1.6 | V48: 14.9 | W48: 14.5 | X48: 2 | Y48: Yellow
A49: 191 Washington St, Boston, MA 02135 | B49: Brighton | C49: https://www.redfin.com/MA/Boston/191-Washington-St-02135/home/184088757 | E49: 564800 | F49: 0 | G49: 1 | H49: 1 | I49: 498 | J49: No | K49: 0 spaces | L49: =Assumptions!B3 | M49: =E49-L49 | N49: =-PMT(Assumptions!B2/12,Assumptions!B4*12,M49) | O49: =E49*Assumptions!B5/12 | P49: =Assumptions!B6 | Q49: =Assumptions!B7+Assumptions!B8 | R49: =N49+F49+O49+P49+Q49 | S49: 0 | T49: =R49-S49*MAX(IFERROR(G49-1,0),0) | U49: 2.1 | V49: 13.6 | W49: 13.2 | X49: 2 | Y49: Yellow
A50: 17 Buckingham St #3, Somerville, MA 02143 | B50: Somerville | C50: https://www.redfin.com/MA/Somerville/17-Buckingham-St-02143/unit-3/home/200344678 | E50: 474999 | F50: 233 | G50: 1 | H50: 1 | I50: 595 | J50: No | K50: 1 space | L50: =Assumptions!B3 | M50: =E50-L50 | N50: =-PMT(Assumptions!B2/12,Assumptions!B4*12,M50) | O50: =E50*Assumptions!B5/12 | P50: =Assumptions!B6 | Q50: =Assumptions!B7+Assumptions!B8 | R50: =N50+F50+O50+P50+Q50 | S50: 0 | T50: =R50-S50*MAX(IFERROR(G50-1,0),0) | U50: 3.2 | V50: 11.7 | W50: 5.9 | X50: 2 | Y50: Yellow
A51: 367 Somerville Ave Unit G, Somerville, MA 02143 | B51: Somerville | C51: https://www.redfin.com/MA/Somerville/367-Somerville-Ave-02143/unit-G/home/8751476 | E51: 425000 | F51: 304 | G51: 1 | H51: 1 | I51: 419 | J51: No | K51: 0 spaces | L51: =Assumptions!B3 | M51: =E51-L51 | N51: =-PMT(Assumptions!B2/12,Assumptions!B4*12,M51) | O51: =E51*Assumptions!B5/12 | P51: =Assumptions!B6 | Q51: =Assumptions!B7+Assumptions!B8 | R51: =N51+F51+O51+P51+Q51 | S51: 0 | T51: =R51-S51*MAX(IFERROR(G51-1,0),0) | U51: 2.1 | V51: 10.3 | W51: 6 | X51: 2 | Y51: Yellow
A52: 5 Waldo Ave Unit 2A, Somerville, MA 02143 | B52: Somerville | C52: https://www.redfin.com/MA/Somerville/5-Waldo-Ave-02143/unit-2A/home/8759932 | E52: 425000 | F52: 317 | G52: 1 | H52: 1 | I52: 530 | J52: No | K52: 0 spaces | L52: =Assumptions!B3 | M52: =E52-L52 | N52: =-PMT(Assumptions!B2/12,Assumptions!B4*12,M52) | O52: =E52*Assumptions!B5/12 | P52: =Assumptions!B6 | Q52: =Assumptions!B7+Assumptions!B8 | R52: =N52+F52+O52+P52+Q52 | S52: 0 | T52: =R52-S52*MAX(IFERROR(G52-1,0),0) | U52: 3.2 | V52: 11.7 | W52: 6 | X52: 2 | Y52: Yellow
A53: 1263 Commonwealth Ave #4, Allston, MA 02134 | B53: Allston | C53: https://www.redfin.com/MA/Allston/1263-Commonwealth-Ave-02134/unit-4/home/8995479 | E53: 575000 | F53: 430 | G53: 2 | H53: 1 | I53: 968 | J53: No | K53: 1 space | L53: =Assumptions!B3 | M53: =E53-L53 | N53: =-PMT(Assumptions!B2/12,Assumptions!B4*12,M53) | O53: =E53*Assumptions!B5/12 | P53: =Assumptions!B6 | Q53: =Assumptions!B7+Assumptions!B8 | R53: =N53+F53+O53+P53+Q53 | S53: 1235 | T53: =R53-S53*MAX(IFERROR(G53-1,0),0) | U53: 1.3 | V53: 12.1 | W53: 11.7 | X53: 2 | Y53: Yellow
A54: 1666 Commonwealth Ave Unit 66-24, Brighton, MA 02135 | B54: Brighton | C54: https://www.redfin.com/MA/Brighton/1666-Commonwealth-Ave-02135/unit-66-24/home/200890931 | E54: 449900 | F54: 343 | G54: 1 | H54: 1 | I54: 573 | J54: No | K54: 0 spaces | L54: =Assumptions!B3 | M54: =E54-L54 | N54: =-PMT(Assumptions!B2/12,Assumptions!B4*12,M54) | O54: =E54*Assumptions!B5/12 | P54: =Assumptions!B6 | Q54: =Assumptions!B7+Assumptions!B8 | R54: =N54+F54+O54+P54+Q54 | S54: 0 | T54: =R54-S54*MAX(IFERROR(G54-1,0),0) | U54: 2.5 | V54: 14.2 | W54: 13.8 | X54: 2 | Y54: Yellow
A55: 18 Glenville Ave Unit 3A, Allston, MA 02134 | B55: Allston | C55: https://www.redfin.com/MA/Allston/18-Glenville-Ave-02134/unit-3A/home/8995847 | E55: 399900 | F55: 427 | G55: 1 | H55: 1 | I55: 495 | J55: No | K55: 0 spaces | L55: =Assumptions!B3 | M55: =E55-L55 | N55: =-PMT(Assumptions!B2/12,Assumptions!B4*12,M55) | O55: =E55*Assumptions!B5/12 | P55: =Assumptions!B6 | Q55: =Assumptions!B7+Assumptions!B8 | R55: =N55+F55+O55+P55+Q55 | S55: 0 | T55: =R55-S55*MAX(IFERROR(G55-1,0),0) | U55: 0.6 | V55: 11.1 | W55: 10.7 | X55: 2 | Y55: Yellow
A56: 44 Washington St #508, Brookline, MA 02445 | B56: Brookline | C56: https://www.redfin.com/MA/Brookline/44-Washington-St-02445/unit-508/home/11485671 | E56: 419000 | F56: 491 | G56: 0 | H56: 1 | I56: 500 | J56: No | K56: 0 spaces | L56: =Assumptions!B3 | M56: =E56-L56 | N56: =-PMT(Assumptions!B2/12,Assumptions!B4*12,M56) | O56: =E56*Assumptions!B5/12 | P56: =Assumptions!B6 | Q56: =Assumptions!B7+Assumptions!B8 | R56: =N56+F56+O56+P56+Q56 | S56: 0 | T56: =R56-S56*MAX(IFERROR(G56-1,0),0) | U56: 1.4 | V56: 14 | W56: 12.3 | X56: 2 | Y56: Yellow
A57: 1496 Commonwealth Ave Unit 9E, Brighton, MA 02135 | B57: Brighton | C57: https://www.redfin.com/MA/Brighton/1496-Commonwealth-Ave-02135/unit-9E/home/201193887 | E57: 425000 | F57: 297 | G57: 1 | H57: 1 | I57: 525 | J57: No | K57: 0 spaces | L57: =Assumptions!B3 | M57: =E57-L57 | N57: =-PMT(Assumptions!B2/12,Assumptions!B4*12,M57) | O57: =E57*Assumptions!B5/12 | P57: =Assumptions!B6 | Q57: =Assumptions!B7+Assumptions!B8 | R57: =N57+F57+O57+P57+Q57 | S57: 0 | T57: =R57-S57*MAX(IFERROR(G57-1,0),0) | U57: 0.8 | V57: 12.9 | W57: 12.5 | X57: 2 | Y57: Yellow
A58: 474 Broadway #25, Somerville, MA 02145 | B58: Somerville | C58: https://www.redfin.com/MA/Somerville/474-Broadway-02145/unit-25/home/8709234 | E58: 399000 | F58: 419 | G58: 1 | H58: 1 | I58: 640 | J58: No | K58: 1 space | L58: =Assumptions!B3 | M58: =E58-L58 | N58: =-PMT(Assumptions!B2/12,Assumptions!B4*12,M58) | O58: =E58*Assumptions!B5/12 | P58: =Assumptions!B6 | Q58: =Assumptions!B7+Assumptions!B8 | R58: =N58+F58+O58+P58+Q58 | S58: 0 | T58: =R58-S58*MAX(IFERROR(G58-1,0),0) | U58: 2.1 | V58: 11.1 | W58: 8.5 | X58: 2 | Y58: Yellow
A59: 115 W Sqantum #607, Quincy, MA 02171 | B59: Quincy | C59: https://www.redfin.com/MA/Quincy/115-W-Squantum-St-02171/unit-607/home/9025296 | D59: 2026-04-10 | E59: 368000 | F59: 416 | G59: 1 | H59: 1 | I59: 765 | J59: No | K59: 1 space | L59: =Assumptions!B3 | M59: =E59-L59 | N59: =-PMT(Assumptions!B2/12,Assumptions!B4*12,M59) | O59: =E59*Assumptions!B5/12 | P59: =Assumptions!B6 | Q59: =Assumptions!B7+Assumptions!B8 | R59: =N59+F59+O59+P59+Q59 | S59: 0 | T59: =R59-S59*MAX(IFERROR(G59-1,0),0) | U59: 2.6 | V59: 13.4 | W59: 17.4 | X59: 2 | Y59: Yellow
A60: 28 Hibiscus Ave, Waltham, MA 02451 | B60: Waltham | C60: https://www.redfin.com/MA/Waltham/28-Hibiscus-Ave-02451/home/11802693 | D60: 2026-04-12 | E60: 585000 | F60: 0 | G60: 3 | H60: 1.5 | I60: 1303 | J60: No | K60: 3 spaces | L60: =Assumptions!B3 | M60: =E60-L60 | N60: =-PMT(Assumptions!B2/12,Assumptions!B4*12,M60) | O60: =E60*Assumptions!B5/12 | P60: =Assumptions!B6 | Q60: =Assumptions!B7+Assumptions!B8 | R60: =N60+F60+O60+P60+Q60 | S60: 1235 | T60: =R60-S60*MAX(IFERROR(G60-1,0),0) | U60: 14.4 | V60: 26.9 | W60: 24.8 | X60: 2 | Y60: Yellow
A61: 36 Bellvista Rd #36, Boston, MA 02135 | B61: Brighton | C61: https://www.redfin.com/MA/Boston/36-Bellvista-Rd-02135/unit-36/home/201241136 | D61: 2026-04-08 | E61: 467500 | F61: 451 | G61: 1 | H61: 1 | I61: 760 | J61: No | K61: 1 space | L61: =Assumptions!B3 | M61: =E61-L61 | N61: =-PMT(Assumptions!B2/12,Assumptions!B4*12,M61) | O61: =E61*Assumptions!B5/12 | P61: =Assumptions!B6 | Q61: =Assumptions!B7+Assumptions!B8 | R61: =N61+F61+O61+P61+Q61 | S61: 0 | T61: =R61-S61*MAX(IFERROR(G61-1,0),0) | U61: 2.3 | V61: 12.6 | W61: 12.2 | X61: 2 | Y61: Yellow
A62: 533 Cambridge St #308, Allston, MA 02134 | B62: Allston | C62: https://www.redfin.com/MA/Allston/533-Cambridge-St-02134/unit-308/home/12469714 | D62: 2026-04-09 | E62: 545911 | F62: 270 | G62: 1 | H62: 1 | I62: 885 | J62: No | K62: 1 space | L62: =Assumptions!B3 | M62: =E62-L62 | N62: =-PMT(Assumptions!B2/12,Assumptions!B4*12,M62) | O62: =E62*Assumptions!B5/12 | P62: =Assumptions!B6 | Q62: =Assumptions!B7+Assumptions!B8 | R62: =N62+F62+O62+P62+Q62 | S62: 0 | T62: =R62-S62*MAX(IFERROR(G62-1,0),0) | U62: 2.8 | V62: 11.1 | W62: 10.8 | X62: 2 | Y62: Yellow
A63: 9 Clyde #9, Somerville, MA 02145 | B63: Somerville | C63: https://www.redfin.com/MA/Somerville/9-Clyde-St-02145/unit-9/home/187141476 | D63: 2026-04-09 | E63: 569000 | F63: 220 | G63: 1 | H63: 1 | I63: 712 | J63: No | K63: 1 space | L63: =Assumptions!B3 | M63: =E63-L63 | N63: =-PMT(Assumptions!B2/12,Assumptions!B4*12,M63) | O63: =E63*Assumptions!B5/12 | P63: =Assumptions!B6 | Q63: =Assumptions!B7+Assumptions!B8 | R63: =N63+F63+O63+P63+Q63 | S63: 0 | T63: =R63-S63*MAX(IFERROR(G63-1,0),0) | U63: 2.4 | V63: 13 | W63: 10.1 | X63: 2 | Y63: Yellow
A64: 150 Madison Ave, Quincy, MA 02169 | B64: Quincy | C64: https://www.redfin.com/MA/Quincy/150-Madison-Ave-02169/home/8954563 | D64: 2026-04-14 | E64: 525000 | F64: 0 | G64: 2 | H64: 1 | I64: 1078 | J64: No | K64: 2 spaces | L64: =Assumptions!B3 | M64: =E64-L64 | N64: =-PMT(Assumptions!B2/12,Assumptions!B4*12,M64) | O64: =E64*Assumptions!B5/12 | P64: =Assumptions!B6 | Q64: =Assumptions!B7+Assumptions!B8 | R64: =N64+F64+O64+P64+Q64 | S64: 1170 | T64: =R64-S64*MAX(IFERROR(G64-1,0),0) | U64: 4.8 | V64: 20.1 | W64: 24.1 | X64: 2 | Y64: Yellow
A65: 140 Kenrick #8, Brighton, MA 02135 | B65: Brighton | C65: https://www.redfin.com/MA/Brighton/140-Kenrick-St-02135/unit-8/home/9043024 | D65: 2026-04-14 | E65: 460000 | F65: 434 | G65: 2 | H65: 1 | I65: 646 | J65: No | K65: 2 spaces | L65: =Assumptions!B3 | M65: =E65-L65 | N65: =-PMT(Assumptions!B2/12,Assumptions!B4*12,M65) | O65: =E65*Assumptions!B5/12 | P65: =Assumptions!B6 | Q65: =Assumptions!B7+Assumptions!B8 | R65: =N65+F65+O65+P65+Q65 | S65: 1300 | T65: =R65-S65*MAX(IFERROR(G65-1,0),0) | U65: 5.2 | V65: 16.5 | W65: 16.6 | X65: 2 | Y65: Yellow
A66: 1-Bedroom Plan, Quincy, MA 02169 | B66: Quincy | C66: https://www.redfin.com/MA/Quincy/Quincy/1-Bedroom/home/197950895 | E66: 399000 | F66: 0 | G66: 1 | H66: 1 | I66: 500 | J66: No | K66: Unknown | L66: =Assumptions!B3 | M66: =E66-L66 | N66: =-PMT(Assumptions!B2/12,Assumptions!B4*12,M66) | O66: =E66*Assumptions!B5/12 | P66: =Assumptions!B6 | Q66: =Assumptions!B7+Assumptions!B8 | R66: =N66+F66+O66+P66+Q66 | S66: 0 | T66: =R66-S66*MAX(IFERROR(G66-1,0),0) | U66: 1.4 | V66: 17.1 | W66: 21.2 | X66: 1.95 | Y66: Yellow
A67: 2-Bedrooms Plan, Quincy, MA 02169 | B67: Quincy | C67: https://www.redfin.com/MA/Quincy/Quincy/2-Bedrooms/home/197950891 | E67: 599000 | F67: 0 | G67: 2 | H67: 2 | I67: 900 | J67: No | K67: Unknown | L67: =Assumptions!B3 | M67: =E67-L67 | N67: =-PMT(Assumptions!B2/12,Assumptions!B4*12,M67) | O67: =E67*Assumptions!B5/12 | P67: =Assumptions!B6 | Q67: =Assumptions!B7+Assumptions!B8 | R67: =N67+F67+O67+P67+Q67 | S67: 1170 | T67: =R67-S67*MAX(IFERROR(G67-1,0),0) | U67: 1.4 | V67: 17.1 | W67: 21.2 | X67: 1.95 | Y67: Yellow
A68: 31 Warren St Unit B1, Waltham, MA 02453 | B68: Waltham | C68: https://www.redfin.com/MA/Waltham/31-Warren-St-02453/unit-B1/home/11815449 | E68: 429000 | F68: 497 | G68: 2 | H68: 1 | I68: 708 | J68: No | K68: 2 spaces | L68: =Assumptions!B3 | M68: =E68-L68 | N68: =-PMT(Assumptions!B2/12,Assumptions!B4*12,M68) | O68: =E68*Assumptions!B5/12 | P68: =Assumptions!B6 | Q68: =Assumptions!B7+Assumptions!B8 | R68: =N68+F68+O68+P68+Q68 | S68: 1235 | T68: =R68-S68*MAX(IFERROR(G68-1,0),0) | U68: 10.5 | V68: 19.2 | W68: 18 | X68: 1.95 | Y68: Yellow
A69: 42 Bryon Rd #6, Chestnut Hill, MA 02132 | B69: Newton | C69: https://www.redfin.com/MA/Chestnut-Hill/42-Bryon-Rd-02467/unit-6/home/9204495 | E69: 449900 | F69: 465 | G69: 2 | H69: 1 | I69: 780 | J69: No | K69: 2 spaces | L69: =Assumptions!B3 | M69: =E69-L69 | N69: =-PMT(Assumptions!B2/12,Assumptions!B4*12,M69) | O69: =E69*Assumptions!B5/12 | P69: =Assumptions!B6 | Q69: =Assumptions!B7+Assumptions!B8 | R69: =N69+F69+O69+P69+Q69 | S69: 1430 | T69: =R69-S69*MAX(IFERROR(G69-1,0),0) | U69: 6.1 | V69: 23.2 | W69: 21.6 | X69: 1.95 | Y69: Yellow
A70: 7 Lothian Rd Unit B, Brighton, MA 02135 | B70: Brighton | C70: https://www.redfin.com/MA/Brighton/7-Lothian-Rd-02135/unit-B/home/9025402 | E70: 539900 | F70: 417 | G70: 3 | H70: 1 | I70: 900 | J70: No | K70: 0 spaces | L70: =Assumptions!B3 | M70: =E70-L70 | N70: =-PMT(Assumptions!B2/12,Assumptions!B4*12,M70) | O70: =E70*Assumptions!B5/12 | P70: =Assumptions!B6 | Q70: =Assumptions!B7+Assumptions!B8 | R70: =N70+F70+O70+P70+Q70 | S70: 1300 | T70: =R70-S70*MAX(IFERROR(G70-1,0),0) | U70: 1.2 | V70: 16 | W70: 14.4 | X70: 1.95 | Y70: Yellow
A71: 6 Washington Ave #11, Cambridge, MA 02140 | B71: Cambridge | C71: https://www.redfin.com/MA/Cambridge/6-Washington-Ave-02140/unit-11/home/11585376 | E71: 469000 | F71: 320 | G71: 0 | H71: 1 | I71: 433 | J71: No | K71: 0 spaces | L71: =Assumptions!B3 | M71: =E71-L71 | N71: =-PMT(Assumptions!B2/12,Assumptions!B4*12,M71) | O71: =E71*Assumptions!B5/12 | P71: =Assumptions!B6 | Q71: =Assumptions!B7+Assumptions!B8 | R71: =N71+F71+O71+P71+Q71 | S71: 0 | T71: =R71-S71*MAX(IFERROR(G71-1,0),0) | U71: 2.1 | V71: 15.8 | W71: 10.3 | X71: 1.95 | Y71: Yellow
A72: 26 Friend St, Waltham, MA 02453 | B72: Waltham | C72: https://www.redfin.com/MA/Waltham/26-Friend-St-02453/home/11818417 | E72: 549900 | F72: 0 | G72: 3 | H72: 1.5 | I72: 788 | J72: No | K72: 2 spaces | L72: =Assumptions!B3 | M72: =E72-L72 | N72: =-PMT(Assumptions!B2/12,Assumptions!B4*12,M72) | O72: =E72*Assumptions!B5/12 | P72: =Assumptions!B6 | Q72: =Assumptions!B7+Assumptions!B8 | R72: =N72+F72+O72+P72+Q72 | S72: 1235 | T72: =R72-S72*MAX(IFERROR(G72-1,0),0) | U72: 9.3 | V72: 19 | W72: 19.5 | X72: 1.95 | Y72: Yellow
A73: 156 West St, Quincy, MA 02169 | B73: Quincy | C73: https://www.redfin.com/MA/Quincy/156-West-St-02169/home/8965188 | E73: 579000 | F73: 0 | G73: 2 | H73: 1.5 | I73: 1088 | J73: No | K73: 4 spaces | L73: =Assumptions!B3 | M73: =E73-L73 | N73: =-PMT(Assumptions!B2/12,Assumptions!B4*12,M73) | O73: =E73*Assumptions!B5/12 | P73: =Assumptions!B6 | Q73: =Assumptions!B7+Assumptions!B8 | R73: =N73+F73+O73+P73+Q73 | S73: 1170 | T73: =R73-S73*MAX(IFERROR(G73-1,0),0) | U73: 4.2 | V73: 16.2 | W73: 20.3 | X73: 1.95 | Y73: Yellow
A74: 134 Sherman St, Quincy, MA 02170 | B74: Quincy | C74: https://www.redfin.com/MA/Quincy/134-Sherman-St-02170/home/8992856 | E74: 589000 | F74: 0 | G74: 2 | H74: 1 | I74: 1001 | J74: No | K74: 5 spaces | L74: =Assumptions!B3 | M74: =E74-L74 | N74: =-PMT(Assumptions!B2/12,Assumptions!B4*12,M74) | O74: =E74*Assumptions!B5/12 | P74: =Assumptions!B6 | Q74: =Assumptions!B7+Assumptions!B8 | R74: =N74+F74+O74+P74+Q74 | S74: 1170 | T74: =R74-S74*MAX(IFERROR(G74-1,0),0) | U74: 3.6 | V74: 15.2 | W74: 19.3 | X74: 1.95 | Y74: Yellow
A75: 114 Strathmore Rd #404, Brighton, MA 02135 | B75: Brighton | C75: https://www.redfin.com/MA/Brighton/114-Strathmore-Rd-02135/unit-404/home/9026666 | E75: 409000 | F75: 377 | G75: 0 | H75: 1 | I75: 481 | J75: No | K75: 0 spaces | L75: =Assumptions!B3 | M75: =E75-L75 | N75: =-PMT(Assumptions!B2/12,Assumptions!B4*12,M75) | O75: =E75*Assumptions!B5/12 | P75: =Assumptions!B6 | Q75: =Assumptions!B7+Assumptions!B8 | R75: =N75+F75+O75+P75+Q75 | S75: 0 | T75: =R75-S75*MAX(IFERROR(G75-1,0),0) | U75: 1.6 | V75: 15.6 | W75: 13.9 | X75: 1.95 | Y75: Yellow
A76: 26 Waverly St #410, Brighton, MA 02135 | B76: Brighton | C76: https://www.redfin.com/MA/Brighton/26-Waverly-St-02135/unit-410/home/9010706 | D76: 2026-04-08 | E76: 530000 | F76: 484 | G76: 2 | H76: 1 | I76: 800 | J76: No | K76: 1 space | L76: =Assumptions!B3 | M76: =E76-L76 | N76: =-PMT(Assumptions!B2/12,Assumptions!B4*12,M76) | O76: =E76*Assumptions!B5/12 | P76: =Assumptions!B6 | Q76: =Assumptions!B7+Assumptions!B8 | R76: =N76+F76+O76+P76+Q76 | S76: 1300 | T76: =R76-S76*MAX(IFERROR(G76-1,0),0) | U76: 5.9 | V76: 12.5 | W76: 12.2 | X76: 1.95 | Y76: Yellow
A77: 110 Lanark Rd #10, Brighton, MA 02135 | B77: Brighton | C77: https://www.redfin.com/MA/Brighton/110-Lanark-Rd-02135/unit-10/home/9022452 | D77: 2026-04-08 | E77: 425000 | F77: 494 | G77: 1 | H77: 1 | I77: 553 | J77: No | K77: 0 spaces | L77: =Assumptions!B3 | M77: =E77-L77 | N77: =-PMT(Assumptions!B2/12,Assumptions!B4*12,M77) | O77: =E77*Assumptions!B5/12 | P77: =Assumptions!B6 | Q77: =Assumptions!B7+Assumptions!B8 | R77: =N77+F77+O77+P77+Q77 | S77: 0 | T77: =R77-S77*MAX(IFERROR(G77-1,0),0) | U77: 0.9 | V77: 14.8 | W77: 14.1 | X77: 1.95 | Y77: Yellow
A78: 90 Kilsyth Rd #32, Brighton, MA 02135 | B78: Brighton | C78: https://www.redfin.com/MA/Brighton/90-Kilsyth-Rd-02135/unit-32/home/9021275 | D78: 2026-04-09 | E78: 459000 | F78: 461 | G78: 1 | H78: 1 | I78: 639 | J78: No | K78: 0 spaces | L78: =Assumptions!B3 | M78: =E78-L78 | N78: =-PMT(Assumptions!B2/12,Assumptions!B4*12,M78) | O78: =E78*Assumptions!B5/12 | P78: =Assumptions!B6 | Q78: =Assumptions!B7+Assumptions!B8 | R78: =N78+F78+O78+P78+Q78 | S78: 0 | T78: =R78-S78*MAX(IFERROR(G78-1,0),0) | U78: 1.1 | V78: 15 | W78: 13.8 | X78: 1.95 | Y78: Yellow
A79: 35 Homer Ave #7, Cambridge, MA 02138 | B79: Watertown | C79: https://www.redfin.com/MA/Cambridge/35-Homer-Ave-02138/unit-7/home/12442078 | E79: 500000 | F79: 325 | G79: 1 | H79: 1 | I79: 504 | J79: No | K79: 1 space | L79: =Assumptions!B3 | M79: =E79-L79 | N79: =-PMT(Assumptions!B2/12,Assumptions!B4*12,M79) | O79: =E79*Assumptions!B5/12 | P79: =Assumptions!B6 | Q79: =Assumptions!B7+Assumptions!B8 | R79: =N79+F79+O79+P79+Q79 | S79: 0 | T79: =R79-S79*MAX(IFERROR(G79-1,0),0) | U79: 5 | V79: 14.2 | W79: 11.8 | X79: 1.9 | Y79: Yellow
A80: 4 Franklin St #202, Boston, MA 02134 | B80: Allston | C80: https://www.redfin.com/MA/Boston/4-Franklin-St-02134/unit-202/home/190592119 | E80: 588000 | F80: 243 | G80: 1 | H80: 1 | I80: 641 | J80: No | K80: 1 space | L80: =Assumptions!B3 | M80: =E80-L80 | N80: =-PMT(Assumptions!B2/12,Assumptions!B4*12,M80) | O80: =E80*Assumptions!B5/12 | P80: =Assumptions!B6 | Q80: =Assumptions!B7+Assumptions!B8 | R80: =N80+F80+O80+P80+Q80 | S80: 0 | T80: =R80-S80*MAX(IFERROR(G80-1,0),0) | U80: 1.4 | V80: 9.7 | W80: 9.3 | X80: 1.9 | Y80: Yellow
A81: 111 Jersey St #15, Boston, MA 02215 | B81: Brookline | C81: https://www.redfin.com/MA/Boston/111-Jersey-St-02215/unit-15/home/9317643 | E81: 529000 | F81: 281 | G81: 1 | H81: 1 | I81: 395 | J81: No | K81: 0 spaces | L81: =Assumptions!B3 | M81: =E81-L81 | N81: =-PMT(Assumptions!B2/12,Assumptions!B4*12,M81) | O81: =E81*Assumptions!B5/12 | P81: =Assumptions!B6 | Q81: =Assumptions!B7+Assumptions!B8 | R81: =N81+F81+O81+P81+Q81 | S81: 0 | T81: =R81-S81*MAX(IFERROR(G81-1,0),0) | U81: 1.1 | V81: 11.3 | W81: 8.4 | X81: 1.9 | Y81: Yellow
A82: 549 Centre St #2, Newton, MA 02458 | B82: Newton | C82: https://www.redfin.com/MA/Newton/549-Centre-St-02458/unit-2/home/11411108 | E82: 450000 | F82: 333 | G82: 1 | H82: 1 | I82: 522 | J82: No | K82: 0 spaces | L82: =Assumptions!B3 | M82: =E82-L82 | N82: =-PMT(Assumptions!B2/12,Assumptions!B4*12,M82) | O82: =E82*Assumptions!B5/12 | P82: =Assumptions!B6 | Q82: =Assumptions!B7+Assumptions!B8 | R82: =N82+F82+O82+P82+Q82 | S82: 0 | T82: =R82-S82*MAX(IFERROR(G82-1,0),0) | U82: 5.8 | V82: 13.9 | W82: 14.5 | X82: 1.9 | Y82: Yellow
A83: 35 Glencoe St #43, Brighton, MA 02134 | B83: Watertown | C83: https://www.redfin.com/MA/Brighton/35-Glencoe-St-02135/unit-43/home/9015948 | E83: 475000 | F83: 454 | G83: 1 | H83: 1 | I83: 697 | J83: No | K83: 1 space | L83: =Assumptions!B3 | M83: =E83-L83 | N83: =-PMT(Assumptions!B2/12,Assumptions!B4*12,M83) | O83: =E83*Assumptions!B5/12 | P83: =Assumptions!B6 | Q83: =Assumptions!B7+Assumptions!B8 | R83: =N83+F83+O83+P83+Q83 | S83: 0 | T83: =R83-S83*MAX(IFERROR(G83-1,0),0) | U83: 3.1 | V83: 12.9 | W83: 12.6 | X83: 1.9 | Y83: Yellow
A84: 241 Hurley St #1, Cambridge, MA 02141 | B84: Cambridge | C84: https://www.redfin.com/MA/Cambridge/241-Hurley-St-02141/unit-1/home/11603214 | E84: 515000 | F84: 350 | G84: 1 | H84: 1 | I84: 403 | J84: No | K84: 0 spaces | L84: =Assumptions!B3 | M84: =E84-L84 | N84: =-PMT(Assumptions!B2/12,Assumptions!B4*12,M84) | O84: =E84*Assumptions!B5/12 | P84: =Assumptions!B6 | Q84: =Assumptions!B7+Assumptions!B8 | R84: =N84+F84+O84+P84+Q84 | S84: 0 | T84: =R84-S84*MAX(IFERROR(G84-1,0),0) | U84: 1.6 | V84: 8 | W84: 2.1 | X84: 1.9 | Y84: Yellow
A85: 86 East Howard St #107, Quincy, MA 02169 | B85: Quincy | C85: https://www.redfin.com/MA/Quincy/86-E-Howard-St-02169/unit-107/home/9036654 | D85: 2026-04-09 | E85: 450000 | F85: 416 | G85: 2 | H85: 1 | I85: 1029 | J85: No | K85: 2 spaces | L85: =Assumptions!B3 | M85: =E85-L85 | N85: =-PMT(Assumptions!B2/12,Assumptions!B4*12,M85) | O85: =E85*Assumptions!B5/12 | P85: =Assumptions!B6 | Q85: =Assumptions!B7+Assumptions!B8 | R85: =N85+F85+O85+P85+Q85 | S85: 1170 | T85: =R85-S85*MAX(IFERROR(G85-1,0),0) | U85: 6.8 | V85: 21.4 | W85: 25.5 | X85: 1.9 | Y85: Yellow
A86: 25 Wellington St #1, Waltham, MA 02451 | B86: Waltham | C86: https://www.redfin.com/MA/Waltham/25-Wellington-St-02451/unit-1/home/11823207 | D86: 2026-04-08 | E86: 585000 | F86: 225 | G86: 3 | H86: 2 | I86: 1226 | J86: No | K86: 0 spaces | L86: =Assumptions!B3 | M86: =E86-L86 | N86: =-PMT(Assumptions!B2/12,Assumptions!B4*12,M86) | O86: =E86*Assumptions!B5/12 | P86: =Assumptions!B6 | Q86: =Assumptions!B7+Assumptions!B8 | R86: =N86+F86+O86+P86+Q86 | S86: 1235 | T86: =R86-S86*MAX(IFERROR(G86-1,0),0) | U86: 9.8 | V86: 22.8 | W86: 22.2 | X86: 1.9 | Y86: Yellow
A87: 75 Park St #8, Brookline, MA 02446 | B87: Brookline | C87: https://www.redfin.com/MA/Brookline/75-Park-St-02446/unit-8/home/11467606 | D87: 2026-04-09 | E87: 400000 | F87: 288 | G87: 0 | H87: 1 | I87: 395 | J87: No | K87: 0 spaces | L87: =Assumptions!B3 | M87: =E87-L87 | N87: =-PMT(Assumptions!B2/12,Assumptions!B4*12,M87) | O87: =E87*Assumptions!B5/12 | P87: =Assumptions!B6 | Q87: =Assumptions!B7+Assumptions!B8 | R87: =N87+F87+O87+P87+Q87 | S87: 0 | T87: =R87-S87*MAX(IFERROR(G87-1,0),0) | X87: 1.9 | Y87: Yellow
A88: 131 Park Dr #2, Boston, MA 02215 | B88: Brookline | C88: https://www.redfin.com/MA/Boston/131-Park-Dr-02215/unit-2/home/9241298 | D88: 2026-04-13 | E88: 499000 | F88: 0 | G88: 0 | H88: 1 | I88: 350 | J88: No | K88: Unknown | L88: =Assumptions!B3 | M88: =E88-L88 | N88: =-PMT(Assumptions!B2/12,Assumptions!B4*12,M88) | O88: =E88*Assumptions!B5/12 | P88: =Assumptions!B6 | Q88: =Assumptions!B7+Assumptions!B8 | R88: =N88+F88+O88+P88+Q88 | S88: 0 | T88: =R88-S88*MAX(IFERROR(G88-1,0),0) | X88: 1.9 | Y88: Yellow
A89: 542 Riverside Ave, Medford, MA 02155 | B89: Medford | C89: https://www.redfin.com/MA/Medford/542-Riverside-Ave-02155/home/11801613 | D89: 2026-04-07 | E89: 535000 | F89: 0 | G89: 2 | H89: 1 | I89: 948 | J89: No | K89: 1 space | L89: =Assumptions!B3 | M89: =E89-L89 | N89: =-PMT(Assumptions!B2/12,Assumptions!B4*12,M89) | O89: =E89*Assumptions!B5/12 | P89: =Assumptions!B6 | Q89: =Assumptions!B7+Assumptions!B8 | R89: =N89+F89+O89+P89+Q89 | S89: 1235 | T89: =R89-S89*MAX(IFERROR(G89-1,0),0) | X89: 1.9 | Y89: Yellow
A90: 20 Whitney Unit U:1, Quincy, MA 02169 | B90: Quincy | C90: https://www.redfin.com/MA/Quincy/20-Whitney-Rd-02169/unit-U-1/home/200248173 | E90: 499000 | F90: 200 | G90: 1 | H90: 1 | I90: 638 | J90: No | K90: 1 space | L90: =Assumptions!B3 | M90: =E90-L90 | N90: =-PMT(Assumptions!B2/12,Assumptions!B4*12,M90) | O90: =E90*Assumptions!B5/12 | P90: =Assumptions!B6 | Q90: =Assumptions!B7+Assumptions!B8 | R90: =N90+F90+O90+P90+Q90 | S90: 0 | T90: =R90-S90*MAX(IFERROR(G90-1,0),0) | U90: 1.4 | V90: 17.1 | W90: 21.2 | X90: 1.85 | Y90: Yellow
A91: 20 Whitney Rd #101, Quincy, MA 02169 | B91: Quincy | C91: https://www.redfin.com/MA/Quincy/20-Whitney-Rd-02169/unit-101/home/196906729 | E91: 499000 | F91: 0 | G91: 1 | H91: 1 | I91: 575 | J91: No | K91: Unknown | L91: =Assumptions!B3 | M91: =E91-L91 | N91: =-PMT(Assumptions!B2/12,Assumptions!B4*12,M91) | O91: =E91*Assumptions!B5/12 | P91: =Assumptions!B6 | Q91: =Assumptions!B7+Assumptions!B8 | R91: =N91+F91+O91+P91+Q91 | S91: 0 | T91: =R91-S91*MAX(IFERROR(G91-1,0),0) | U91: 1.4 | V91: 17.1 | W91: 21.2 | X91: 1.85 | Y91: Yellow
A92: 56 Ralph St #3, Watertown, MA 02472 | B92: Watertown | C92: https://www.redfin.com/MA/Watertown/56-Ralph-St-02472/unit-3/home/57314411 | E92: 474900 | F92: 183 | G92: 1 | H92: 1 | I92: 983 | J92: No | K92: 2 spaces | L92: =Assumptions!B3 | M92: =E92-L92 | N92: =-PMT(Assumptions!B2/12,Assumptions!B4*12,M92) | O92: =E92*Assumptions!B5/12 | P92: =Assumptions!B6 | Q92: =Assumptions!B7+Assumptions!B8 | R92: =N92+F92+O92+P92+Q92 | S92: 0 | T92: =R92-S92*MAX(IFERROR(G92-1,0),0) | U92: 8.9 | V92: 18.8 | W92: 16.4 | X92: 1.85 | Y92: Yellow
A93: 1945 Commonwealth Ave #4, Brighton, MA 02135 | B93: Brighton | C93: https://www.redfin.com/MA/Brighton/1945-Commonwealth-Ave-02135/unit-4/home/9242382 | E93: 439000 | F93: 364 | G93: 1 | H93: 1 | I93: 605 | J93: No | K93: 0 spaces | L93: =Assumptions!B3 | M93: =E93-L93 | N93: =-PMT(Assumptions!B2/12,Assumptions!B4*12,M93) | O93: =E93*Assumptions!B5/12 | P93: =Assumptions!B6 | Q93: =Assumptions!B7+Assumptions!B8 | R93: =N93+F93+O93+P93+Q93 | S93: 0 | T93: =R93-S93*MAX(IFERROR(G93-1,0),0) | U93: 1.8 | V93: 16.7 | W93: 15 | X93: 1.85 | Y93: Yellow
A94: 26 Chiswick Rd #6, Brighton, MA 02135 | B94: Brighton | C94: https://www.redfin.com/MA/Brighton/26-Chiswick-Rd-02135/unit-6/home/9026723 | E94: 368000 | F94: 472 | G94: 1 | H94: 1 | I94: 470 | J94: No | K94: 0 spaces | L94: =Assumptions!B3 | M94: =E94-L94 | N94: =-PMT(Assumptions!B2/12,Assumptions!B4*12,M94) | O94: =E94*Assumptions!B5/12 | P94: =Assumptions!B6 | Q94: =Assumptions!B7+Assumptions!B8 | R94: =N94+F94+O94+P94+Q94 | S94: 0 | T94: =R94-S94*MAX(IFERROR(G94-1,0),0) | U94: 1.4 | V94: 15.6 | W94: 13.8 | X94: 1.85 | Y94: Yellow
A95: 10 Washington Ave #3, Waltham, MA 02453 | B95: Waltham | C95: https://www.redfin.com/MA/Waltham/10-Washington-Ave-02453/unit-3/home/69378071 | E95: 575000 | F95: 200 | G95: 2 | H95: 1 | I95: 1021 | J95: No | K95: 1 space | L95: =Assumptions!B3 | M95: =E95-L95 | N95: =-PMT(Assumptions!B2/12,Assumptions!B4*12,M95) | O95: =E95*Assumptions!B5/12 | P95: =Assumptions!B6 | Q95: =Assumptions!B7+Assumptions!B8 | R95: =N95+F95+O95+P95+Q95 | S95: 1235 | T95: =R95-S95*MAX(IFERROR(G95-1,0),0) | U95: 6 | V95: 19.5 | W95: 20 | X95: 1.85 | Y95: Yellow
A96: 76 Taft Ave #1, West Newton, MA 02465 | B96: Newton | C96: https://www.redfin.com/MA/West-Newton/76-Taft-Ave-02465/unit-1/home/11433253 | E96: 599000 | F96: 200 | G96: 2 | H96: 1 | I96: 862 | J96: No | K96: 3 spaces | L96: =Assumptions!B3 | M96: =E96-L96 | N96: =-PMT(Assumptions!B2/12,Assumptions!B4*12,M96) | O96: =E96*Assumptions!B5/12 | P96: =Assumptions!B6 | Q96: =Assumptions!B7+Assumptions!B8 | R96: =N96+F96+O96+P96+Q96 | S96: 1430 | T96: =R96-S96*MAX(IFERROR(G96-1,0),0) | U96: 7.1 | V96: 18.1 | W96: 18.7 | X96: 1.85 | Y96: Yellow
A97: 28 Sidlaw Rd #2, Brighton, MA 02135 | B97: Brighton | C97: https://www.redfin.com/MA/Brighton/28-Sidlaw-Rd-02135/unit-2/home/9007059 | E97: 399900 | F97: 414 | G97: 1 | H97: 1 | I97: 638 | J97: No | K97: 0 spaces | L97: =Assumptions!B3 | M97: =E97-L97 | N97: =-PMT(Assumptions!B2/12,Assumptions!B4*12,M97) | O97: =E97*Assumptions!B5/12 | P97: =Assumptions!B6 | Q97: =Assumptions!B7+Assumptions!B8 | R97: =N97+F97+O97+P97+Q97 | S97: 0 | T97: =R97-S97*MAX(IFERROR(G97-1,0),0) | U97: 1.2 | V97: 16.1 | W97: 14.5 | X97: 1.85 | Y97: Yellow
A98: 388 Washington St #101, Quincy, MA 02169 | B98: Quincy | C98: https://www.redfin.com/MA/Quincy/388-Washington-St-02169/unit-101/home/201094286 | E98: 599000 | F98: 375 | G98: 2 | H98: 2 | I98: 983 | J98: No | K98: 1 space | L98: =Assumptions!B3 | M98: =E98-L98 | N98: =-PMT(Assumptions!B2/12,Assumptions!B4*12,M98) | O98: =E98*Assumptions!B5/12 | P98: =Assumptions!B6 | Q98: =Assumptions!B7+Assumptions!B8 | R98: =N98+F98+O98+P98+Q98 | S98: 1170 | T98: =R98-S98*MAX(IFERROR(G98-1,0),0) | U98: 2.7 | V98: 18.8 | W98: 22.9 | X98: 1.85 | Y98: Yellow
A99: 16 Littlefield St, Quincy, MA 02169 | B99: Quincy | C99: https://www.redfin.com/MA/Quincy/16-Littlefield-St-02169/home/8913868 | E99: 567000 | F99: 0 | G99: 4 | H99: 1.5 | I99: 1274 | J99: No | K99: 4 spaces | L99: =Assumptions!B3 | M99: =E99-L99 | N99: =-PMT(Assumptions!B2/12,Assumptions!B4*12,M99) | O99: =E99*Assumptions!B5/12 | P99: =Assumptions!B6 | Q99: =Assumptions!B7+Assumptions!B8 | R99: =N99+F99+O99+P99+Q99 | S99: 1170 | T99: =R99-S99*MAX(IFERROR(G99-1,0),0) | U99: 8.7 | V99: 23.6 | W99: 27.7 | X99: 1.85 | Y99: Yellow
A100: 200 Falls Blvd Unit E101, Quincy, MA 02169 | B100: Quincy | C100: https://www.redfin.com/MA/Quincy/200-Falls-Blvd-02169/unit-E101/home/11496568 | E100: 449000 | F100: 494 | G100: 2 | H100: 2 | I100: 774 | J100: No | K100: 1 space | L100: =Assumptions!B3 | M100: =E100-L100 | N100: =-PMT(Assumptions!B2/12,Assumptions!B4*12,M100) | O100: =E100*Assumptions!B5/12 | P100: =Assumptions!B6 | Q100: =Assumptions!B7+Assumptions!B8 | R100: =N100+F100+O100+P100+Q100 | S100: 1170 | T100: =R100-S100*MAX(IFERROR(G100-1,0),0) | U100: 7.2 | V100: 21.8 | W100: 25.9 | X100: 1.85 | Y100: Yellow
...
